Workbook

Sheet Табели
A2: =Ин.яз!B5 -> Адилбеков Бектур
A3: =TODAY() -> 46120 | E3: Пропуски
A4: № | B4: Дисциплина | C4: Сессия | D4: Средний балл | E4: Уваж. | F4: Неуваж.
A5: 1 | B5: Иностранный язык в профессиональной деятельности | D5: =Ин.яз!AN5 -> 3.6 | E5: =Ин.яз!AO5 -> 1 | F5: =Ин.яз!AP5 -> 13
A6: 2 | B6: Физическая культура | D6: =Физ.ра!BL5 -> 4.4 | E6: =Физ.ра!BM5 -> 0 | F6: =Физ.ра!BN5 -> 6
A7: 3 | B7: История | C7: =CONCATENATE(История!AC5) -> 3 | D7: =История!AD5 -> 3.8333333 | E7: =История!AE5 -> 0 | F7: =История!AF5 -> 0
A8: 4 | B8: Проектирование и разработка интерфейсов пользователя | C8: =CONCATENATE(ПиРИП!AP5) | D8: =ПиРИП!AQ5 -> 2.8888889 | E8: =ПиРИП!AR5 -> 0 | F8: =ПиРИП!AS5 -> 10
A9: 5 | B9: Элементы высшей математики | C9: =CONCATENATE('Элемент выш мат'!BQ5) | D9: ='Элемент выш мат'!BR5 -> 3.3333333 | E9: ='Элемент выш мат'!BS5 -> 1 | F9: ='Элемент выш мат'!BT5 -> 10
A10: 6 | B10: Архитектура аппаратных средств | C10: =CONCATENATE('арх.ап.средств'!AP5) | D10: ='арх.ап.средств'!AQ5 -> 5 | E10: ='арх.ап.средств'!AR5 -> 0 | F10: ='арх.ап.средств'!AS5 -> 11
A11: 7 | B11: Операционные системы и среды | C11: =CONCATENATE('Опер.систем-среды'!AV5) | D11: ='Опер.систем-среды'!AW5 -> 2 | E11: ='Опер.систем-среды'!AX5 -> 0 | F11: ='Опер.систем-среды'!AY5 -> 11
A12: 8 | B12: Основы алгоритмизации и программирования | C12: =CONCATENATE('Основы алгоритмизации'!CC5) | D12: ='Основы алгоритмизации'!CD5 -> 2.5 | E12: ='Основы алгоритмизации'!CE5 -> 0 | F12: ='Основы алгоритмизации'!CF5 -> 11
A13: 9 | B13: Основы проектирования баз данных | C13: =CONCATENATE('Осн.пр.Базы данных'!BB5) | D13: ='Осн.пр.Базы данных'!BC5 -> 2.3333333 | E13: ='Осн.пр.Базы данных'!BD5 -> 0 | F13: ='Осн.пр.Базы данных'!BE5 -> 14
A14: 10 | B14: Численные методы | C14: =CONCATENATE('Числ метод'!AI5) -> 2 | D14: ='Числ метод'!AJ5 -> 2.75 | E14: ='Числ метод'!AK5 -> 0 | F14: ='Числ метод'!AL5 -> 2
A15: 11 | B15: Компьютерные сети | C15: =CONCATENATE('Комп сеть'!Y5) -> н | D15: ='Комп сеть'!Z5 -> 3.7857143 | E15: ='Комп сеть'!AA5 -> 0 | F15: ='Комп сеть'!AB5 -> 4
A16: 12 | B16: Теория вероятности и математическая статистика | C16: =CONCATENATE('Теор.вероят и мат.стат'!BX5) | D16: ='Теор.вероят и мат.стат'!BY5 -> 2 | E16: ='Теор.вероят и мат.стат'!BZ5 -> 0 | F16: ='Теор.вероят и мат.стат'!CA5 -> 8
A17: 13 | B17: Дискретная математика | C17: =CONCATENATE('Дискрет.мат '!BQ5) | D17: ='Дискрет.мат '!BR5 -> 2 | E17: ='Дискрет.мат '!BS5 -> 0 | F17: ='Дискрет.мат '!BT5 -> 6
A18: 14 | B18: Разработка программных модулей | C18: =CONCATENATE('Разработка кода ИС'!AO5) | D18: ='Разработка кода ИС'!AP5 -> Нет оценок | E18: ='Разработка кода ИС'!AQ5 -> 0 | F18: ='Разработка кода ИС'!AR5 -> 6
A19: 15 | B19: Внедрение и поддержка компьютерных систем | D19: ='Внедр.подд.комп.систем'!BC5 -> Нет оценок | E19: ='Внедр.подд.комп.систем'!BD5 -> 0 | F19: ='Внедр.подд.комп.систем'!BE5 -> 0
A20: 16 | B20: Обеспечение качества функционирования компьютерных систем | D20: ='Тестирование ИС'!CA5 -> Нет оценок | E20: ='Тестирование ИС'!CB5 -> 0 | F20: ='Тестирование ИС'!CC5 -> 4
A21: 17 | B21: Психология общения | D21: =Псих.общ!BW5 -> Нет оценок | E21: =Псих.общ!BX5 -> 0 | F21: =Псих.общ!BY5 -> 7
A22: 18 | B22: Технология разработки и защиты баз данных | D22: ='Тех.разра.БД'!AA5 -> Нет оценок | E22: ='Тех.разра.БД'!AB5 -> 0 | F22: ='Тех.разра.БД'!AC5 -> 0
A23: 19 | B23: Безопасность жизнедеятельности | D23: =БЖ!AA5 -> 3.6666667 | E23: =БЖ!AB5 -> 0 | F23: =БЖ!AC5 -> 0
A24: 20. | B24: Графический дизайн и мультимедия | C24: ='Граф диз и мульт'!Z6 -> 0 | D24: ='Граф диз и мульт'!AA6 -> 3.3333333 | E24: ='Граф диз и мульт'!AB6 -> 0 | F24: ='Граф диз и мульт'!AC6 -> 6
A25: 21. | B25: Проектирование и дизайн информационных систем | D25: ='Проектирование и дизайн ИС'!AP5 -> 4 | E25: ='Проектирование и дизайн ИС'!AQ5 -> 0 | F25: ='Проектирование и дизайн ИС'!AR5 -> 15
D26: =IFERROR(AVERAGE(D5:D25),"") -> 3.2140377 | E26: =SUM(E5:E25) -> 2 | F26: =SUM(F5:F25) -> 144
E27: Общее количество пропусков
E28: =SUM(E26:F26) -> 146
A30: =Ин.яз!B6 -> Ахметов Артём Рамилевич
A31: =TODAY() -> 46120 | E31: Пропуски
A32: № | B32: Дисциплина | C32: Сессия | D32: Средний балл | E32: Уваж. | F32: Неуваж.
A33: 1 | B33: Иностранный язык в профессиональной деятельности | D33: =Ин.яз!AN6 -> 3.7 | E33: =Ин.яз!AO6 -> 0 | F33: =Ин.яз!AP6 -> 7
A34: 2 | B34: Физическая культура | D34: =Физ.ра!BL6 -> 4 | E34: =Физ.ра!BM6 -> 0 | F34: =Физ.ра!BN6 -> 1
A35: 3 | B35: История | C35: =CONCATENATE(История!AC32) | D35: =История!AD6 -> 3.6666667 | E35: =История!AE32 -> 0 | F35: =История!AF32 -> 0
A36: 4 | B36: Проектирование и разработка интерфейсов пользователя | C36: =CONCATENATE(ПиРИП!AP33) | D36: =ПиРИП!AQ6 -> 4.0833333 | E36: =ПиРИП!AR33 -> 0 | F36: =ПиРИП!AS33 -> 0
A37: 5 | B37: Элементы высшей математики | C37: =CONCATENATE('Элемент выш мат'!BQ32) | D37: ='Элемент выш мат'!BR6 -> 4.125 | E37: ='Элемент выш мат'!BS32 -> 0 | F37: ='Элемент выш мат'!BT32 -> 0
A38: 6 | B38: Архитектура аппаратных средств | C38: =CONCATENATE('арх.ап.средств'!AP31) | D38: ='арх.ап.средств'!AQ6 -> 4.2666667 | E38: ='арх.ап.средств'!AR31 -> 0 | F38: ='арх.ап.средств'!AS31 -> 0
A39: 7 | B39: Операционные системы и среды | C39: =CONCATENATE('Опер.систем-среды'!AV32) | D39: ='Опер.систем-среды'!AW6 -> 3.5 | E39: ='Опер.систем-среды'!AX32 -> 0 | F39: ='Опер.систем-среды'!AY32 -> 0
A40: 8 | B40: Основы алгоритмизации и программирования | C40: =CONCATENATE('Основы алгоритмизации'!CC32) | D40: ='Основы алгоритмизации'!CD6 -> 2.6666667 | E40: ='Основы алгоритмизации'!CE32 -> 0 | F40: ='Основы алгоритмизации'!CF32 -> 0
A41: 9 | B41: Основы проектирования баз данных | C41: =CONCATENATE('Осн.пр.Базы данных'!BB32) | D41: ='Осн.пр.Базы данных'!BC6 -> 3.3333333 | E41: ='Осн.пр.Базы данных'!BD32 -> 0 | F41: ='Осн.пр.Базы данных'!BE32 -> 0
A42: 10 | B42: Численные методы | C42: =CONCATENATE('Числ метод'!AI32) | D42: ='Числ метод'!AJ6 -> 3.6666667 | E42: ='Числ метод'!AK32 -> 0 | F42: ='Числ метод'!AL32 -> 0
A43: 11 | B43: Компьютерные сети | C43: =CONCATENATE('Комп сеть'!Y32) -> 0 | D43: ='Комп сеть'!Z6 -> 4.1333333 | E43: ='Комп сеть'!AA32 -> 0 | F43: ='Комп сеть'!AB32 -> 0
A44: 12 | B44: Теория вероятности и математическая статистика | C44: =CONCATENATE('Теор.вероят и мат.стат'!BX32) | D44: ='Теор.вероят и мат.стат'!BY6 -> 3.25 | E44: ='Теор.вероят и мат.стат'!BZ32 -> 0 | F44: ='Теор.вероят и мат.стат'!CA32 -> 0
A45: 13 | B45: Дискретная математика | C45: =CONCATENATE('Дискрет.мат '!BQ32) | D45: ='Дискрет.мат '!BR6 -> 2 | E45: ='Дискрет.мат '!BS32 -> 0 | F45: ='Дискрет.мат '!BT32 -> 0
A46: 14 | B46: Разработка программных модулей | C46: =CONCATENATE('Разработка кода ИС'!AO32) | D46: ='Разработка кода ИС'!AP6 -> 2.5 | E46: ='Разработка кода ИС'!AQ32 -> 0 | F46: ='Разработка кода ИС'!AR32 -> 0
A47: 15 | B47: Внедрение и поддержка компьютерных систем | D47: ='Внедр.подд.комп.систем'!BC6 -> Нет оценок | E47: ='Внедр.подд.комп.систем'!BD32 -> 0 | F47: ='Внедр.подд.комп.систем'!BE32 -> 0
A48: 16 | B48: Обеспечение качества функционирования компьютерных систем | D48: ='Тестирование ИС'!CA6 -> 5 | E48: ='Тестирование ИС'!CB32 -> 0 | F48: ='Тестирование ИС'!CC32 -> 0
A49: 17 | B49: Психология общения | D49: =Псих.общ!BW6 -> 4 | E49: =Псих.общ!BX6 -> 0 | F49: =Псих.общ!BY6 -> 4
A50: 18 | B50: Технология разработки и защиты баз данных | D50: ='Тех.разра.БД'!AA6 -> Нет оценок | E50: ='Тех.разра.БД'!AB32 -> 0 | F50: ='Тех.разра.БД'!AC32 -> 0
A51: 19 | B51: Безопасность жизнедеятельности | D51: =БЖ!AA6 -> 3.4285714 | E51: =БЖ!AB32 -> 0 | F51: =БЖ!AC32 -> 0
A52: 20. | B52: Графический дизайн и мультимедия | C52: ='Граф диз и мульт'!Z5 -> 0 | D52: ='Граф диз и мульт'!AA5 -> 4.3333333 | E52: ='Граф диз и мульт'!AB5 -> 0 | F52: ='Граф диз и мульт'!AC5 -> 0
A53: 21. | B53: Проектирование и дизайн информационных систем | D53: ='Проектирование и дизайн ИС'!AP6 -> 4.1818182 | E53: ='Проектирование и дизайн ИС'!AQ32 -> 0 | F53: ='Проектирование и дизайн ИС'!AR32 -> 0
D54: =IFERROR(AVERAGE(D33:D53),"") -> 3.6755468 | E54: =SUM(E33:E53) -> 0 | F54: =SUM(F33:F53) -> 12
E55: Общее количество пропусков
E56: =SUM(E54:F54) -> 12
A58: =Ин.яз!B7 -> Бараников Владислав Михайлович
A59: =TODAY() -> 46120 | E59: Пропуски
A60: № | B60: Дисциплина | C60: Сессия | D60: Средний балл | E60: Уваж. | F60: Неуваж.
A61: 1 | B61: Иностранный язык в профессиональной деятельности | D61: =Ин.яз!AN7 -> 3.6923077 | E61: =Ин.яз!AO7 -> 0 | F61: =Ин.яз!AP7 -> 1
A62: 2 | B62: Физическая культура | D62: =Физ.ра!BL7 -> 5 | E62: =Физ.ра!BM7 -> 0 | F62: =Физ.ра!BN7 -> 0
A63: 3 | B63: История | C63: =CONCATENATE(История!AC59) | D63: =История!AD7 -> 3.875 | E63: =История!AE7 -> 0 | F63: =История!AF7 -> 0
A64: 4 | B64: Проектирование и разработка интерфейсов пользователя | C64: =CONCATENATE(ПиРИП!AP60) | D64: =ПиРИП!AQ7 -> 4.3684211 | E64: =ПиРИП!AR7 -> 0 | F64: =ПиРИП!AS7 -> 0
A65: 5 | B65: Элементы высшей математики | C65: =CONCATENATE('Элемент выш мат'!BQ59) | D65: ='Элемент выш мат'!BR7 -> 3.7857143 | E65: ='Элемент выш мат'!BS7 -> 0 | F65: ='Элемент выш мат'!BT7 -> 1
A66: 6 | B66: Архитектура аппаратных средств | C66: =CONCATENATE('арх.ап.средств'!AP58) | D66: ='арх.ап.средств'!AQ7 -> 4.4666667 | E66: ='арх.ап.средств'!AR7 -> 0 | F66: ='арх.ап.средств'!AS7 -> 0
A67: 7 | B67: Операционные системы и среды | C67: =CONCATENATE('Опер.систем-среды'!AV59) | D67: ='Опер.систем-среды'!AW7 -> 2.5 | E67: ='Опер.систем-среды'!AX7 -> 0 | F67: ='Опер.систем-среды'!AY7 -> 0
A68: 8 | B68: Основы алгоритмизации и программирования | C68: =CONCATENATE('Основы алгоритмизации'!CC59) | D68: ='Основы алгоритмизации'!CD7 -> 2.6666667 | E68: ='Основы алгоритмизации'!CE7 -> 0 | F68: ='Основы алгоритмизации'!CF7 -> 3
A69: 9 | B69: Основы проектирования баз данных | C69: =CONCATENATE('Осн.пр.Базы данных'!BB59) | D69: ='Осн.пр.Базы данных'!BC7 -> 3 | E69: ='Осн.пр.Базы данных'!BD7 -> 0 | F69: ='Осн.пр.Базы данных'!BE7 -> 1
A70: 10 | B70: Численные методы | C70: =CONCATENATE('Числ метод'!AI59) | D70: ='Числ метод'!AJ7 -> 3.7777778 | E70: ='Числ метод'!AK7 -> 0 | F70: ='Числ метод'!AL7 -> 0
A71: 11 | B71: Компьютерные сети | C71: =CONCATENATE('Комп сеть'!Y59) | D71: ='Комп сеть'!Z7 -> 4.7647059 | E71: ='Комп сеть'!AA7 -> 0 | F71: ='Комп сеть'!AB7 -> 0
A72: 12 | B72: Теория вероятности и математическая статистика | C72: =CONCATENATE('Теор.вероят и мат.стат'!BX59) | D72: ='Теор.вероят и мат.стат'!BY7 -> 4 | E72: ='Теор.вероят и мат.стат'!BZ7 -> 0 | F72: ='Теор.вероят и мат.стат'!CA7 -> 0
A73: 13 | B73: Дискретная математика | C73: =CONCATENATE('Дискрет.мат '!BQ59) | D73: ='Дискрет.мат '!BR7 -> 4 | E73: ='Дискрет.мат '!BS7 -> 0 | F73: ='Дискрет.мат '!BT7 -> 0
A74: 14 | B74: Разработка программных модулей | C74: =CONCATENATE('Разработка кода ИС'!AO59) | D74: ='Разработка кода ИС'!AP7 -> 5 | E74: ='Разработка кода ИС'!AQ7 -> 0 | F74: ='Разработка кода ИС'!AR7 -> 0
A75: 15 | B75: Внедрение и поддержка компьютерных систем | D75: ='Внедр.подд.комп.систем'!BC7 -> Нет оценок | E75: ='Внедр.подд.комп.систем'!BD7 -> 0 | F75: ='Внедр.подд.комп.систем'!BE7 -> 0
A76: 16 | B76: Обеспечение качества функционирования компьютерных систем | D76: ='Тестирование ИС'!CA7 -> 5 | E76: ='Тестирование ИС'!CB7 -> 0 | F76: ='Тестирование ИС'!CC7 -> 1
A77: 17 | B77: Психология общения | D77: =Псих.общ!BW7 -> 4.25 | E77: =Псих.общ!BX7 -> 0 | F77: =Псих.общ!BY7 -> 0
A78: 18 | B78: Технология разработки и защиты баз данных | D78: ='Тех.разра.БД'!AA7 -> Нет оценок | E78: ='Тех.разра.БД'!AB7 -> 0 | F78: ='Тех.разра.БД'!AC7 -> 0
A79: 19 | B79: Безопасность жизнедеятельности | D79: =БЖ!AA7 -> 4.1428571 | E79: =БЖ!AB7 -> 0 | F79: =БЖ!AC7 -> 0
A80: 20. | B80: Графический дизайн и мультимедия | C80: ='Граф диз и мульт'!Z7 -> 0 | D80: ='Граф диз и мульт'!AA7 -> 5 | E80: ='Граф диз и мульт'!AB7 -> 0 | F80: ='Граф диз и мульт'!AC7 -> 1
A81: 21. | B81: Проектирование и дизайн информационных систем | D81: ='Проектирование и дизайн ИС'!AP7 -> 4.7857143 | E81: ='Проектирование и дизайн ИС'!AQ7 -> 0 | F81: ='Проектирование и дизайн ИС'!AR7 -> 1
D82: =IFERROR(AVERAGE(D61:D81),"") -> 4.1092543 | E82: =SUM(E61:E81) -> 0 | F82: =SUM(F61:F81) -> 9
E83: Общее количество пропусков
E84: =SUM(E82:F82) -> 9
A86: =Ин.яз!B8 -> Борсук Артём Дмитриевич
A87: =TODAY() -> 46120 | E87: Пропуски
A88: № | B88: Дисциплина | C88: Сессия | D88: Средний балл | E88: Уваж. | F88: Неуваж.
A89: 1 | B89: Иностранный язык в профессиональной деятельности | D89: =Ин.яз!AN8 -> 3.4545455 | E89: =Ин.яз!AO8 -> 0 | F89: =Ин.яз!AP8 -> 4
A90: 2 | B90: Физическая культура | D90: =Физ.ра!BL8 -> 4.6 | E90: =Физ.ра!BM8 -> 0 | F90: =Физ.ра!BN8 -> 1
A91: 3 | B91: История | C91: =CONCATENATE(История!AC86) | D91: =История!AD8 -> 3.75 | E91: =История!AE8 -> 0 | F91: =История!AF8 -> 0
A92: 4 | B92: Проектирование и разработка интерфейсов пользователя | C92: =CONCATENATE(ПиРИП!AP87) | D92: =ПиРИП!AQ8 -> 3.8461538 | E92: =ПиРИП!AR8 -> 0 | F92: =ПиРИП!AS8 -> 6
A93: 5 | B93: Элементы высшей математики | C93: =CONCATENATE('Элемент выш мат'!BQ86) | D93: ='Элемент выш мат'!BR8 -> 3.3333333 | E93: ='Элемент выш мат'!BS8 -> 0 | F93: ='Элемент выш мат'!BT8 -> 6
A94: 6 | B94: Архитектура аппаратных средств | C94: =CONCATENATE('арх.ап.средств'!AP85) | D94: ='арх.ап.средств'!AQ8 -> 4.6 | E94: ='арх.ап.средств'!AR8 -> 0 | F94: ='арх.ап.средств'!AS8 -> 0
A95: 7 | B95: Операционные системы и среды | C95: =CONCATENATE('Опер.систем-среды'!AV86) | D95: ='Опер.систем-среды'!AW8 -> 2.5 | E95: ='Опер.систем-среды'!AX8 -> 0 | F95: ='Опер.систем-среды'!AY8 -> 9
A96: 8 | B96: Основы алгоритмизации и программирования | C96: =CONCATENATE('Основы алгоритмизации'!CC86) | D96: ='Основы алгоритмизации'!CD8 -> 2.5714286 | E96: ='Основы алгоритмизации'!CE8 -> 0 | F96: ='Основы алгоритмизации'!CF8 -> 7
A97: 9 | B97: Основы проектирования баз данных | C97: =CONCATENATE('Осн.пр.Базы данных'!BB86) | D97: ='Осн.пр.Базы данных'!BC8 -> 3 | E97: ='Осн.пр.Базы данных'!BD8 -> 0 | F97: ='Осн.пр.Базы данных'!BE8 -> 6
A98: 10 | B98: Численные методы | C98: =CONCATENATE('Числ метод'!AI86) | D98: ='Числ метод'!AJ8 -> 3 | E98: ='Числ метод'!AK8 -> 0 | F98: ='Числ метод'!AL8 -> 0
A99: 11 | B99: Компьютерные сети | C99: =CONCATENATE('Комп сеть'!Y86) | D99: ='Комп сеть'!Z8 -> 4.2142857 | E99: ='Комп сеть'!AA8 -> 0 | F99: ='Комп сеть'!AB8 -> 0
A100: 12 | B100: Теория вероятности и математическая статистика | C100: =CONCATENATE('Теор.вероят и мат.стат'!BX86) | D100: ='Теор.вероят и мат.стат'!BY8 -> 3.3333333 | E100: ='Теор.вероят и мат.стат'!BZ8 -> 0 | F100: ='Теор.вероят и мат.стат'!CA8 -> 2
A101: 13 | B101: Дискретная математика | C101: =CONCATENATE('Дискрет.мат '!BQ86) | D101: ='Дискрет.мат '!BR8 -> 2.5 | E101: ='Дискрет.мат '!BS8 -> 0 | F101: ='Дискрет.мат '!BT8 -> 1
A102: 14 | B102: Разработка программных модулей | C102: =CONCATENATE('Разработка кода ИС'!AO86) | D102: ='Разработка кода ИС'!AP8 -> Нет оценок | E102: ='Разработка кода ИС'!AQ8 -> 0 | F102: ='Разработка кода ИС'!AR8 -> 1
A103: 15 | B103: Внедрение и поддержка компьютерных систем | D103: ='Внедр.подд.комп.систем'!BC8 -> Нет оценок | E103: ='Внедр.подд.комп.систем'!BD8 -> 0 | F103: ='Внедр.подд.комп.систем'!BE8 -> 0
A104: 16 | B104: Обеспечение качества функционирования компьютерных систем | D104: ='Тестирование ИС'!CA8 -> Нет оценок | E104: ='Тестирование ИС'!CB8 -> 0 | F104: ='Тестирование ИС'!CC8 -> 4
...

Sheet История
A1: История
A2: Ляхина Дарья Сергеевна
A3: 9 | B3: 9 | C3: 9 | D3: 9 | E3: 9 | F3: 9 | G3: 9 | H3: 10 | I3: 10 | J3: 10 | K3: 10 | L3: 10 | M3: 10 | O3: 11 | P3: 11 | Q3: 11 | R3: 11 | S3: 11 | T3: 12 | U3: 12 | V3: 12 | W3: 12 | X3: 12 | Y3: 12 | Z3: 12 | AA3: 12 | AB3: 12 | AC3: 3 сем | AE3: Пропуски
A4: 2 | B4: 8 | C4: 12 | D4: 18 | E4: 19 | F4: 23 | G4: 26 | H4: 8 | I4: 15 | J4: 15 | K4: 16 | L4: 24 | M4: 28 | O4: 5 | P4: 5 | Q4: 7 | R4: 20 | S4: 24 | T4: 1 | U4: 2 | V4: 4 | W4: 11 | X4: 13 | Y4: 15 | Z4: 18 | AA4: 19 | AB4: 19 | AC4: ДЗ | AD4: Средний балл | AE4: Уваж. | AF4: Неуваж.
E5: 5 | F5: н/отр | H5: н/отр | I5: 4 | K5: н/отр | L5: н/отр | O5: н/отр | P5: н/отр | Q5: 4 | S5: 4 | W5: 3 | Y5: н/отр | AC5: 3 | AD5: =IFERROR(AVERAGE(A5:AC5),"Нет оценок") -> 3.8333333 | AE5: =COUNTIF(A5:AB5,"н/у") -> 0 | AF5: =COUNTIF(A5:AC5,"н") -> 0
B6: н/отр | E6: 5 | I6: н/у/отр | J6: н/у/отр | K6: оп | L6: 2 | O6: н/отр | P6: н/отр | Q6: 4 | R6: н/отр | S6: 4 | V6: н/отр | W6: н/отр | Y6: 4 | AC6: 3 | AD6: =IFERROR(AVERAGE(A6:AC6),"Нет оценок") -> 3.6666667 | AE6: =COUNTIF(A6:AB6,"н/у") -> 0 | AF6: =COUNTIF(A6:AC6,"н") -> 0
B7: н/отр | E7: 4 | I7: 5 | L7: 5 | N7: + | Q7: 4 | S7: 4 | V7: н/отр | W7: 4 | Y7: 2 | AC7: 3 | AD7: =IFERROR(AVERAGE(A7:AC7),"Нет оценок") -> 3.875 | AE7: =COUNTIF(A7:AB7,"н/у") -> 0 | AF7: =COUNTIF(A7:AC7,"н") -> 0
B8: н/отр | C8: н/отр | D8: н/отр | E8: н/отр | I8: н/отр | J8: н/отр | K8: н/отр | L8: 2 | O8: н/отр | P8: н/отр | Q8: н/отр | S8: 4 | T8: оп | W8: н/отр | Y8: 5 | AA8: н/отр | AB8: н/отр | AC8: 4 | AD8: =IFERROR(AVERAGE(A8:AC8),"Нет оценок") -> 3.75 | AE8: =COUNTIF(A8:AB8,"н/у") -> 0 | AF8: =COUNTIF(A8:AC8,"н") -> 0
C9: оп | E9: 5 | F9: н/отр | I9: н/отр | J9: н/отр | K9: н/отр | L9: н/отр | N9: + | O9: н/отр | P9: н/отр | Q9: 4 | S9: 5 | W9: н/отр | Y9: 4 | AC9: 3 | AD9: =IFERROR(AVERAGE(A9:AC9),"Нет оценок") -> 4.2 | AE9: =COUNTIF(A9:AB9,"н/у") -> 0 | AF9: =COUNTIF(A9:AC9,"н") -> 0
B10: 4 | E10: 5 | I10: 5 | L10: 5 | Q10: 3 | S10: 4 | W10: 4 | Y10: 5 | AC10: 4 | AD10: =IFERROR(AVERAGE(A10:AC10),"Нет оценок") -> 4.3333333 | AE10: =COUNTIF(A10:AB10,"н/у") -> 0 | AF10: =COUNTIF(A10:AC10,"н") -> 0
B11: 5 | C11: н/отр | E11: 5 | G11: н/у/отр | I11: 5 | L11: 3 | O11: н/отр | Q11: 4 | R11: н/у/отр | S11: 5 | W11: 5 | Y11: 5 | Z11: 4 | AC11: 4 | AD11: =IFERROR(AVERAGE(A11:AC11),"Нет оценок") -> 4.5 | AE11: =COUNTIF(A11:AB11,"н/у") -> 0 | AF11: =COUNTIF(A11:AC11,"н") -> 0
A12: н/отр | B12: н/отр | C12: н/отр | D12: н/отр | E12: н/отр | F12: н/отр | I12: 2 | L12: 2 | Q12: 4 | S12: 3 | W12: 4 | Y12: 3 | AC12: 3 | AD12: =IFERROR(AVERAGE(A12:AC12),"Нет оценок") -> 3 | AE12: =COUNTIF(A12:AB12,"н/у") -> 0 | AF12: =COUNTIF(A12:AC12,"н") -> 0
B13: оп | E13: 3 | F13: н/отр | I13: н/отр | J13: н/отр | K13: н/отр | L13: н/отр | O13: н/отр | Q13: н/отр | S13: 3 | W13: 3 | X13: н/отр | Y13: 3 | AC13: 4 | AD13: =IFERROR(AVERAGE(A13:AC13),"Нет оценок") -> 3.2 | AE13: =COUNTIF(A13:AB13,"н/у") -> 0 | AF13: =COUNTIF(A13:AC13,"н") -> 0
B14: 5 | E14: 5 | I14: н/отр | J14: н/отр | K14: н/отр | L14: н/отр | N14: + | Q14: 5 | S14: 4 | W14: 4 | Y14: 4 | AC14: 5 | AD14: =IFERROR(AVERAGE(A14:AC14),"Нет оценок") -> 4.5714286 | AE14: =COUNTIF(A14:AB14,"н/у") -> 0 | AF14: =COUNTIF(A14:AC14,"н") -> 0
E15: 4 | I15: н/отр | J15: н/отр | L15: н/отр | N15: + | O15: н/отр | Q15: 4 | S15: 5 | T15: + | W15: 3 | Y15: 4 | AC15: 4 | AD15: =IFERROR(AVERAGE(A15:AC15),"Нет оценок") -> 4 | AE15: =COUNTIF(A15:AB15,"н/у") -> 0 | AF15: =COUNTIF(A15:AC15,"н") -> 0
E16: 4 | I16: н/отр | J16: н/отр | L16: 2 | Q16: н/отр | R16: н/у/отр | S16: н/у/отр | W16: 4 | Y16: 5 | AC16: 3 | AD16: =IFERROR(AVERAGE(A16:AC16),"Нет оценок") -> 3.6 | AE16: =COUNTIF(A16:AB16,"н/у") -> 0 | AF16: =COUNTIF(A16:AC16,"н") -> 0
B17: оп | C17: н/отр | E17: 5 | G17: н/отр | H17: н/отр | I17: 4 | K17: оп | L17: 2 | M17: н/отр | O17: н/отр | P17: н/отр | Q17: н/отр | R17: н/отр | S17: 4 | T17: оп | U17: н/отр | W17: н/отр | X17: н/отр | Y17: 3 | Z17: н/отр | AC17: 3 | AD17: =IFERROR(AVERAGE(A17:AC17),"Нет оценок") -> 3.5 | AE17: =COUNTIF(A17:AB17,"н/у") -> 0 | AF17: =COUNTIF(A17:AC17,"н") -> 0
E18: 5 | I18: 5 | L18: н/отр | N18: + | Q18: 3 | S18: 4 | W18: 4 | Y18: 5 | AC18: 4 | AD18: =IFERROR(AVERAGE(A18:AC18),"Нет оценок") -> 4.2857143 | AE18: =COUNTIF(A18:AB18,"н/у") -> 0 | AF18: =COUNTIF(A18:AC18,"н") -> 0
B19: н/отр | E19: 4 | G19: н/отр | I19: 4 | K19: н/отр | L19: н/отр | Q19: 4 | S19: 4 | T19: + | W19: н/отр | Y19: 5 | AC19: 3 | AD19: =IFERROR(AVERAGE(A19:AC19),"Нет оценок") -> 4 | AE19: =COUNTIF(A19:AB19,"н/у") -> 0 | AF19: =COUNTIF(A19:AC19,"н") -> 0
C20: н/отр | E20: 5 | I20: 5 | L20: 4 | Q20: 5 | S20: 5 | W20: 5 | Y20: 5 | AC20: 5 | AD20: =IFERROR(AVERAGE(A20:AC20),"Нет оценок") -> 4.875 | AE20: =COUNTIF(A20:AB20,"н/у") -> 0 | AF20: =COUNTIF(A20:AC20,"н") -> 0
E21: 4 | F21: н/отр | I21: 4 | K21: оп | L21: н/отр | Q21: 4 | S21: 4 | W21: н/отр | X21: оп | Y21: 4 | AC21: 3 | AD21: =IFERROR(AVERAGE(A21:AC21),"Нет оценок") -> 3.8333333 | AE21: =COUNTIF(A21:AB21,"н/у") -> 0 | AF21: =COUNTIF(A21:AC21,"н") -> 0
E22: 5 | I22: 3 | J22: н/отр | L22: 5 | N22: + | Q22: 5 | S22: 5 | W22: 5 | Y22: 5 | AC22: 5 | AD22: =IFERROR(AVERAGE(A22:AC22),"Нет оценок") -> 4.75 | AE22: =COUNTIF(A22:AB22,"н/у") -> 0 | AF22: =COUNTIF(A22:AC22,"н") -> 0
C23: оп | E23: н/отр | F23: н/у/отр | G23: н/у/отр | I23: 2 | J23: н/отр | K23: оп | L23: н/отр | N23: + | Q23: 4 | S23: 5 | W23: н/отр | X23: н/отр | Y23: 5 | AA23: н/отр | AB23: н/отр | AC23: 4 | AD23: =IFERROR(AVERAGE(A23:AC23),"Нет оценок") -> 4 | AE23: =COUNTIF(A23:AB23,"н/у") -> 0 | AF23: =COUNTIF(A23:AC23,"н") -> 0
E24: 5 | I24: 5 | L24: 4 | N24: + | Q24: 5 | S24: 4 | V24: н/отр | W24: н/у/отр | X24: н/у/отр | Y24: 5 | AC24: 5 | AD24: =IFERROR(AVERAGE(A24:AC24),"Нет оценок") -> 4.7142857 | AE24: =COUNTIF(A24:AB24,"н/у") -> 0 | AF24: =COUNTIF(A24:AC24,"н") -> 0
E25: 3 | F25: н/отр | G25: н/отр | I25: н/отр | J25: н/отр | L25: н/отр | M25: н/отр | N25: + | Q25: 4 | R25: н/отр | S25: 4 | T25: н/отр | U25: н/отр | V25: н/отр | W25: 2 | X25: н/отр | Y25: 2 | AA25: н/отр | AB25: н/отр | AC25: 3 | AD25: =IFERROR(AVERAGE(A25:AC25),"Нет оценок") -> 3 | AE25: =COUNTIF(A25:AB25,"н/у") -> 0 | AF25: =COUNTIF(A25:AC25,"н") -> 0
AD26: =IFERROR(AVERAGE(A26:AC26),"Нет оценок") -> Нет оценок | AE26: =COUNTIF(A26:AB26,"н/у") -> 0 | AF26: =COUNTIF(A26:AC26,"н") -> 0
E27: 2 | I27: 5 | L27: 2 | M27: н/у/отр | Q27: 2 | S27: 2 | T27: + | W27: 3 | Y27: 5 | AC27: 3 | AD27: =IFERROR(AVERAGE(A27:AC27),"Нет оценок") -> 3 | AE27: =COUNTIF(A27:AB27,"н/у") -> 0 | AF27: =COUNTIF(A27:AC27,"н") -> 0
E28: 3 | I28: н/отр | J28: н/отр | K28: н/отр | L28: н/отр | N28: + | Q28: 5 | S28: 5 | W28: 2 | Y28: 4 | AC28: 4 | AD28: =IFERROR(AVERAGE(A28:AC28),"Нет оценок") -> 3.8333333 | AE28: =COUNTIF(A28:AB28,"н/у") -> 0 | AF28: =COUNTIF(A28:AC28,"н") -> 0
AD29: =IFERROR(AVERAGE(AD5:AD28),"") -> 3.9270186 | AE29: =SUM(AE5:AE28) -> 0 | AF29: =SUM(AF5:AF28) -> 0

Sheet Ин.яз
A1: Наименование предмета | C1: Иностранный язык в профессиональной деятельности
A2: ФИО преподавателя | C2: Скоросова Анна Владимировна
A3: ИСиП 24/2 | B3: Месяц | C3: 9 | D3: 9 | E3: 9 | F3: 10 | G3: 11 | H3: 11 | I3: 11 | J3: 11 | K3: 12 | L3: 12 | M3: 12 | N3: 12 | O3: 12 | P3: 12 | Q3: 12 | R3: 1 | S3: 1 | T3: 1 | U3: 2 | V3: 2 | W3: 2 | X3: 2 | Y3: 3 | Z3: 3 | AO3: Пропуски
B4: Число | C4: 10 | D4: 15 | E4: 23 | F4: 13 | G4: 24 | H4: 25 | I4: 28 | J4: 29 | K4: 2 | L4: 4 | M4: 10 | N4: 12 | O4: 16 | P4: 17 | Q4: 23 | R4: 13 | S4: 17 | T4: 31 | U4: 14 | V4: 16 | W4: 24 | X4: 28 | Y4: 3 | Z4: 4 | AN4: Средний балл | AO4: Уваж. | AP4: Неуваж.
A5: 1. | B5: Адилбеков Бектур | D5: 2 | E5: 5 | F5: 5 | H5: н | I5: н | J5: н | K5: н | L5: н | M5: н | N5: н | O5: н | Q5: н\3 | R5: н | S5: н | T5: н | U5: н/у | V5: н | W5: 2 | X5: + | Y5: н | Z5: 4 | AN5: =IFERROR(AVERAGE(C5:AM5),"Нет оценок") -> 3.6 | AO5: =COUNTIF(C5:AM5,"н/у") -> 1 | AP5: =COUNTIF(C5:AM5,"н") -> 13
A6: 2. | B6: Ахметов Артём Рамилевич | D6: 4 | E6: 5 | F6: н | G6: 5 | H6: 5 | I6: 2 | K6: 4 | L6: 3 | M6: н/отр | N6: н/отр | Q6: 4 | R6: н | S6: 3 | T6: н | V6: 2 | W6: н | X6: н | Y6: н | Z6: н | AN6: =IFERROR(AVERAGE(C6:AM6),"Нет оценок") -> 3.7 | AO6: =COUNTIF(C6:AM6,"н/у") -> 0 | AP6: =COUNTIF(C6:AM6,"н") -> 7
A7: 3. | B7: Бараников Владислав Михайлович | D7: 4 | E7: н/отр | F7: 4 | H7: 2 | I7: 3 | J7: 2 | K7: 4 | L7: н/отр | N7: н/отр | Q7: 4 | R7: 4 | S7: 5 | T7: 4 | U7: н | V7: 3 | W7: 4 | X7: + | Y7: + | Z7: 5 | AN7: =IFERROR(AVERAGE(C7:AM7),"Нет оценок") -> 3.6923077 | AO7: =COUNTIF(C7:AM7,"н/у") -> 0 | AP7: =COUNTIF(C7:AM7,"н") -> 1
A8: 4. | B8: Борсук Артём Дмитриевич | D8: н/отр | E8: н/отр | F8: н/отр | G8: 4 | H8: 2 | I8: 3 | J8: 2 | K8: 4 | L8: 3 | N8: н | Q8: 4 | R8: 5 | S8: н | T8: 4 | U8: н | V8: 3 | W8: н | X8: + | Y8: + | Z8: 4 | AN8: =IFERROR(AVERAGE(C8:AM8),"Нет оценок") -> 3.4545455 | AO8: =COUNTIF(C8:AM8,"н/у") -> 0 | AP8: =COUNTIF(C8:AM8,"н") -> 4
A9: 5. | B9: Гильманов Ильназ Максимович | D9: 3 | E9: н/отр | F9: 4 | G9: 2 | H9: 2 | I9: 3 | J9: 4 | K9: 4 | L9: 3 | N9: н/отр | Q9: 4 | R9: 5 | S9: 4 | T9: 4 | V9: 4 | W9: н | X9: + | Y9: н | Z9: 3 | AN9: =IFERROR(AVERAGE(C9:AM9),"Нет оценок") -> 3.5 | AO9: =COUNTIF(C9:AM9,"н/у") -> 0 | AP9: =COUNTIF(C9:AM9,"н") -> 2
A10: 6. | B10: Говтва Илья Денисович | C10: 5 | D10: 5 | E10: 5 | F10: 5 | G10: 5 | H10: 3 | I10: 2 | J10: 5 | K10: 5 | L10: 5 | M10: 5 | N10: н/отр | Q10: 4 | R10: 5 | S10: 5 | T10: 5 | V10: 5 | W10: 4 | X10: + | Y10: + | Z10: 5 | AN10: =IFERROR(AVERAGE(C10:AM10),"Нет оценок") -> 4.6111111 | AO10: =COUNTIF(C10:AM10,"н/у") -> 0 | AP10: =COUNTIF(C10:AM10,"н") -> 0
A11: 7. | B11: Горшков Владислав Васильевич | D11: 3 | E11: 4 | F11: 4 | H11: 3 | I11: 3 | J11: 2 | K11: 4 | L11: 3 | N11: н/отр | Q11: 4 | R11: 4 | S11: 4 | T11: 4 | V11: 4 | W11: н | X11: + | Y11: + | Z11: 4 | AN11: =IFERROR(AVERAGE(C11:AM11),"Нет оценок") -> 3.5714286 | AO11: =COUNTIF(C11:AM11,"н/у") -> 0 | AP11: =COUNTIF(C11:AM11,"н") -> 1
A12: 8. | B12: Гришко Илья Алексеевич | C12: н/отр | D12: н/отр | E12: н/отр | F12: 3 | H12: 2 | I12: 2 | J12: 2 | K12: 3 | L12: 4 | N12: н | Q12: н\3 | R12: н | S12: 4 | T12: 3 | V12: 4 | X12: + | Y12: н | Z12: 4 | AN12: =IFERROR(AVERAGE(C12:AM12),"Нет оценок") -> 3.1 | AO12: =COUNTIF(C12:AM12,"н/у") -> 0 | AP12: =COUNTIF(C12:AM12,"н") -> 3
A13: 9. | B13: Катков Константин Александрович | C13: 5 | D13: 2 | E13: н | F13: н | H13: н | I13: 2 | J13: н | K13: 2 | L13: 2 | M13: н | N13: н | Q13: н | R13: 2 | S13: н | T13: 2 | V13: н | X13: н | Y13: н | Z13: 2 | AN13: =IFERROR(AVERAGE(C13:AM13),"Нет оценок") -> 2.375 | AO13: =COUNTIF(C13:AM13,"н/у") -> 0 | AP13: =COUNTIF(C13:AM13,"н") -> 11
A14: 10. | B14: Корнеев Андрей Александрович | C14: 5 | D14: 4 | E14: н/отр | F14: н/отр | G14: 4 | H14: 2 | I14: 3 | J14: 4 | K14: 3 | L14: 3 | M14: 2 | N14: 5 | Q14: 4 | R14: 3 | S14: 5 | T14: 4 | V14: 3 | W14: 5 | X14: + | Y14: н | Z14: 3 | AN14: =IFERROR(AVERAGE(C14:AM14),"Нет оценок") -> 3.6470588 | AO14: =COUNTIF(C14:AM14,"н/у") -> 0 | AP14: =COUNTIF(C14:AM14,"н") -> 1
A15: 11. | B15: Макаров Максим Алексеевич | D15: 3 | E15: н/у | F15: 4 | H15: 2 | I15: 2 | K15: 3 | L15: 3 | M15: 5 | N15: н | Q15: 3 | R15: 4 | S15: н | T15: 4 | V15: 3 | X15: + | Y15: н | Z15: 3 | AN15: =IFERROR(AVERAGE(C15:AM15),"Нет оценок") -> 3.25 | AO15: =COUNTIF(C15:AM15,"н/у") -> 1 | AP15: =COUNTIF(C15:AM15,"н") -> 3
A16: 13. | B16: Муллагалиев Вадим Радмилович | C16: 2 | D16: 4 | E16: н/отр | F16: н/отр | G16: н/у/отр | H16: н/у/отр | I16: 2 | J16: 4 | K16: 2 | L16: 3 | N16: н | Q16: 4 | R16: 2 | S16: 5 | T16: 4 | V16: 4 | W16: 4 | X16: + | Y16: н | Z16: 5 | AN16: =IFERROR(AVERAGE(C16:AM16),"Нет оценок") -> 3.4615385 | AO16: =COUNTIF(C16:AM16,"н/у") -> 0 | AP16: =COUNTIF(C16:AM16,"н") -> 2
A17: 12. | B17: Натфуллин Камиль Данисович | C17: н | D17: 3 | E17: н | F17: н | H17: 3 | I17: 4 | J17: 4 | K17: н | L17: 3 | M17: н | N17: н | Q17: н\3 | R17: н/отр | S17: 3 | T17: 4 | V17: н | W17: н | X17: + | Y17: н | Z17: н | AN17: =IFERROR(AVERAGE(C17:AM17),"Нет оценок") -> 3.4285714 | AO17: =COUNTIF(C17:AM17,"н/у") -> 0 | AP17: =COUNTIF(C17:AM17,"н") -> 10
A18: 14. | B18: Носков Ярослав Евгеньевич | D18: 3 | E18: н | F18: 4 | G18: 3 | H18: 2 | I18: 2 | J18: 4 | K18: 4 | L18: 5 | N18: н | Q18: 4 | R18: н | S18: 5 | T18: 4 | V18: 4 | X18: + | Y18: н | Z18: 4 | AN18: =IFERROR(AVERAGE(C18:AM18),"Нет оценок") -> 3.6923077 | AO18: =COUNTIF(C18:AM18,"н/у") -> 0 | AP18: =COUNTIF(C18:AM18,"н") -> 4
A19: 15. | B19: Осыка Владислав Сергеевич | D19: 3 | E19: н/отр | F19: 4 | G19: 2 | H19: 2 | I19: 2 | J19: 2 | K19: 4 | L19: 5 | M19: н/отр | N19: н | Q19: 3 | R19: 5 | S19: 5 | T19: 5 | V19: 4 | W19: 3 | X19: + | Y19: н | Z19: н | AN19: =IFERROR(AVERAGE(C19:AM19),"Нет оценок") -> 3.5 | AO19: =COUNTIF(C19:AM19,"н/у") -> 0 | AP19: =COUNTIF(C19:AM19,"н") -> 3
A20: 16. | B20: Романов Михаил Васильевич | D20: 4 | E20: 5 | F20: 5 | H20: 5 | I20: н/отр | K20: 5 | L20: 5 | M20: н/отр | N20: н/отр | Q20: 4 | R20: 5 | S20: 5 | T20: 5 | V20: 5 | X20: н | Y20: + | Z20: н | AN20: =IFERROR(AVERAGE(C20:AM20),"Нет оценок") -> 4.8181818 | AO20: =COUNTIF(C20:AM20,"н/у") -> 0 | AP20: =COUNTIF(C20:AM20,"н") -> 2
A21: 17. | B21: Руфуллаев Ибрагим Фуадович | C21: 2 | D21: 4 | E21: н/отр | F21: 4 | G21: 3 | H21: 2 | I21: 2 | J21: н/отр | K21: 3 | L21: 4 | M21: н/отр | N21: н | Q21: н\3 | R21: 4 | S21: 4 | T21: 3 | V21: 2 | W21: 3 | X21: + | Y21: н | Z21: 4 | AN21: =IFERROR(AVERAGE(C21:AM21),"Нет оценок") -> 3.1428571 | AO21: =COUNTIF(C21:AM21,"н/у") -> 0 | AP21: =COUNTIF(C21:AM21,"н") -> 2
A22: 18. | B22: Сарычев Данила Андреевич | C22: 5 | D22: 4 | E22: н/отр | F22: 4 | G22: 4 | H22: 4 | I22: 3 | J22: 5 | K22: 3 | L22: 5 | N22: н/отр | Q22: н\3 | R22: 5 | S22: 4 | T22: н | U22: н | V22: 4 | W22: н | X22: + | Y22: + | Z22: 4 | AN22: =IFERROR(AVERAGE(C22:AM22),"Нет оценок") -> 4.1538462 | AO22: =COUNTIF(C22:AM22,"н/у") -> 0 | AP22: =COUNTIF(C22:AM22,"н") -> 3
A23: 19. | B23: Сурков Кирилл Александрович | C23: 5 | D23: 5 | E23: н/у/отр | F23: н/отр | G23: 5 | H23: 4 | I23: н | J23: 5 | K23: 5 | L23: н/отр | M23: н | N23: н | O23: н | Q23: 4 | R23: н | S23: н | T23: 4 | U23: н | V23: 5 | W23: н | X23: н | Y23: н | Z23: 5 | AN23: =IFERROR(AVERAGE(C23:AM23),"Нет оценок") -> 4.7 | AO23: =COUNTIF(C23:AM23,"н/у") -> 0 | AP23: =COUNTIF(C23:AM23,"н") -> 10
A24: 20. | B24: Усатов Тимофей Анатольевич | D24: 3 | E24: 4 | F24: 5 | H24: 2 | I24: 2 | J24: 4 | K24: 5 | L24: н/отр | M24: н/у/отр | N24: н/отр | Q24: 4 | R24: 4 | S24: 5 | T24: 4 | V24: 4 | W24: 3 | X24: + | Y24: н/отр | Z24: 5 | AN24: =IFERROR(AVERAGE(C24:AM24),"Нет оценок") -> 3.8571429 | AO24: =COUNTIF(C24:AM24,"н/у") -> 0 | AP24: =COUNTIF(C24:AM24,"н") -> 0
A25: 21. | B25: Халитов Кирилл Родионович | D25: н | E25: н | F25: н | H25: н | I25: 4 | J25: н | K25: н/у | L25: н/у | M25: н | N25: н | O25: н | Q25: н\3 | R25: н | S25: н | T25: н | U25: н | V25: н | X25: + | Y25: н | Z25: 4 | AN25: =IFERROR(AVERAGE(C25:AM25),"Нет оценок") -> 4 | AO25: =COUNTIF(C25:AM25,"н/у") -> 2 | AP25: =COUNTIF(C25:AM25,"н") -> 14
A26: 21. | B26: Хорошилов Игорь Александрович | AN26: =IFERROR(AVERAGE(C26:AM26),"Нет оценок") -> Нет оценок | AO26: =COUNTIF(C26:AM26,"н/у") -> 0 | AP26: =COUNTIF(C26:AM26,"н") -> 0
A27: 22. | B27: Хрычев Мирон Евгеньевич | D27: 4 | E27: н | F27: 4 | G27: 2 | H27: 2 | I27: 4 | J27: н | K27: 2 | L27: 3 | N27: н | Q27: 4 | R27: н | S27: 4 | T27: 4 | V27: 3 | X27: 2 | Y27: н | Z27: н | AN27: =IFERROR(AVERAGE(C27:AM27),"Нет оценок") -> 3.1666667 | AO27: =COUNTIF(C27:AM27,"н/у") -> 0 | AP27: =COUNTIF(C27:AM27,"н") -> 6
A28: 23. | B28: Цапов Илья Валерьевич | D28: 4 | E28: н/отр | F28: н/у/отр | G28: н/отр | H28: н/отр | I28: 3 | J28: н/отр | K28: 5 | L28: н | M28: н/отр | N28: н | Q28: 4 | R28: н | S28: н | T28: 4 | U28: н | V28: 5 | W28: 2 | X28: + | Y28: н | Z28: 3 | AN28: =IFERROR(AVERAGE(C28:AM28),"Нет оценок") -> 3.75 | AO28: =COUNTIF(C28:AM28,"н/у") -> 0 | AP28: =COUNTIF(C28:AM28,"н") -> 6
A29: Дата | B29: Тема / ДЗ | AN29: =IFERROR(AVERAGE(AN5:AN28),"") -> 3.6596767 | AO29: =SUM(AO5:AO28) -> 4 | AP29: =SUM(AP5:AP28) -> 108
A30: 10\09 | B30: Biligual people. Question word order
A31: 15\09 | B31: Formal\informal letters.
A32: 23\09 | B32: Видеолекция. Computers. ex 1-8 | P32: - | Q32: к\р
A33: 13\10 | B33: Задание на moodle
A34: 24\11 | B34: Relationship. Present and past Tenses
A35: 25\11 | B35: Relationship. Present and past Tenses зачет\отработка
A36: 28\11 | B36: p. Present and past Tenses test
A37: 29\11 | B37: Reading telecoms trends
A38: 2\12 | B38: History of computers hardware
A39: 4\12 | B39: Computers and IT in the modern world
A40: 10\12 | B40: Information technologies in Russia and the world
A41: 12\12 | B41: Видеолекция. Задание на мудл
A42: 16\12 | B42: Проверка заданий
A43: 17\12 | B43: Отработа пропусков.
A44: 23\12 | B44: Контрольная работа.
... A53: 04\03 | B53: Test

Sheet ПиРИП
A1: Наименование предмета | C1: Проектирование и разработка интерфейсов пользователя
A2: ФИО преподавателя | C2: Коваленко Даниил Романович
A3: ИСиП 24/2 | B3: Месяц | C3: Сентябрь | G3: Октябрь | J3: Ноябрь | M3: Декабрь | Z3: Январь | AD3: Февраль | AG3: М | AH3: Апрель | AR3: Пропуски
B4: Число | C4: 2 | D4: 5 | F4: 26 | G4: 28 | I4: 29 | J4: 6 | K4: 7 | L4: КЛ | M4: 5 | N4: 6 | O4: 6 | P4: 8 | Q4: 8 | R4: 10 | S4: 11 | T4: 16 | U4: 17 | V4: 17 | W4: 22 | X4: 23 | Y4: 23 | Z4: 16 | AA4: 21 | AB4: 23 | AC4: 30 | AD4: 4 | AE4: 7 | AF4: 7 | AG4: 11 | AH4: 1 | AI4: 6 | AQ4: Средний балл | AR4: Уваж. | AS4: Неуваж.
A5: 1. | B5: Адилбеков Бектур | D5: 4 | F5: н | G5: \1 | I5: н | L5: 2 | M5: 3 | N5: 3 | O5: 3 | P5: 3 | Q5: 3 | R5: 3 | U5: н | V5: н | W5: н | X5: н | AA5: н | AB5: н | AG5: н | AH5: 2 | AI5: н | AQ5: =IFERROR(AVERAGE(C5:AP5),"Нет оценок") -> 2.8888889 | AR5: =COUNTIF(C5:AO5,"н/у") -> 0 | AS5: =COUNTIF(C5:AP5,"н") -> 10
A6: 2. | B6: Ахметов Артём Рамилевич | D6: 4 | G6: \2 | H6: 5 | L6: 5 | M6: 5 | N6: 3 | O6: 3 | P6: 3 | Q6: 3 | R6: 3 | U6: н | V6: н | X6: н | Z6: н | AB6: н | AC6: н | AD6: н | AE6: н | AF6: н | AG6: 5 | AH6: 5 | AI6: 5 | AQ6: =IFERROR(AVERAGE(C6:AP6),"Нет оценок") -> 4.0833333 | AR6: =COUNTIF(C6:AO6,"н/у") -> 0 | AS6: =COUNTIF(C6:AP6,"н") -> 9
A7: 3. | B7: Бараников Владислав Михайлович | C7: 5 | D7: 4 | E7: 5 | F7: 5 | G7: \3 | H7: 5 | L7: 4 | M7: 5 | N7: 4 | O7: 4 | P7: 5 | Q7: 5 | R7: 5 | T7: 4 | W7: 4 | Z7: 4 | AA7: 4 | AG7: 5 | AH7: 4 | AI7: 2 | AQ7: =IFERROR(AVERAGE(C7:AP7),"Нет оценок") -> 4.3684211 | AR7: =COUNTIF(C7:AO7,"н/у") -> 0 | AS7: =COUNTIF(C7:AP7,"н") -> 0
A8: 4. | B8: Борсук Артём Дмитриевич | C8: 5 | D8: 4 | G8: \4 | H8: 4 | L8: 5 | M8: 5 | N8: 3 | O8: 3 | P8: 3 | Q8: 3 | R8: 3 | W8: н | X8: н | Z8: н | AA8: н | AE8: н | AF8: н | AG8: 5 | AH8: 5 | AI8: 2 | AQ8: =IFERROR(AVERAGE(C8:AP8),"Нет оценок") -> 3.8461538 | AR8: =COUNTIF(C8:AO8,"н/у") -> 0 | AS8: =COUNTIF(C8:AP8,"н") -> 6
A9: 5. | B9: Гильманов Ильназ Максимович | D9: 5 | E9: 5 | F9: - | G9: \5 | H9: 5 | I9: 3 | L9: 3 | M9: 5 | N9: 4 | O9: 4 | P9: 3 | Q9: 3 | R9: 3 | T9: 5 | W9: н | AE9: н | AF9: н | AG9: 2 | AH9: 2 | AI9: 2 | AQ9: =IFERROR(AVERAGE(C9:AP9),"Нет оценок") -> 3.6 | AR9: =COUNTIF(C9:AO9,"н/у") -> 0 | AS9: =COUNTIF(C9:AP9,"н") -> 3
A10: 6. | B10: Говтва Илья Денисович | C10: 5 | D10: 5 | E10: 5 | F10: 5 | G10: \6 | H10: 5 | L10: 5 | M10: 5 | N10: 4 | O10: 4 | P10: 5 | Q10: 5 | R10: 5 | S10: 5 | T10: 5 | U10: 5 | V10: 5 | W10: 5 | Z10: 5 | AA10: 5 | AB10: 5 | AC10: 5 | AD10: 5 | AG10: 5 | AH10: 5 | AI10: 5 | AQ10: =IFERROR(AVERAGE(C10:AP10),"Нет оценок") -> 4.92 | AR10: =COUNTIF(C10:AO10,"н/у") -> 0 | AS10: =COUNTIF(C10:AP10,"н") -> 0
A11: 7. | B11: Горшков Владислав Васильевич | D11: 4 | F11: 3 | G11: \7 | H11: 5 | L11: 4 | M11: 5 | N11: 3 | O11: 3 | P11: 3 | Q11: 3 | R11: 3 | T11: 4 | X11: н | Z11: н | AE11: н | AF11: н | AG11: 5 | AH11: 3 | AI11: 2 | AQ11: =IFERROR(AVERAGE(C11:AP11),"Нет оценок") -> 3.5714286 | AR11: =COUNTIF(C11:AO11,"н/у") -> 0 | AS11: =COUNTIF(C11:AP11,"н") -> 4
A12: 8. | B12: Гришко Илья Алексеевич | D12: 2 | F12: - | G12: \8 | L12: 3 | M12: 5 | N12: 3 | O12: 3 | P12: 4 | Q12: 3 | R12: 4 | S12: 4 | T12: - | U12: 3 | V12: 4 | W12: 4 | Z12: 4 | AA12: 4 | AB12: 3 | AC12: 4 | AD12: 3 | AG12: 2 | AH12: 2 | AI12: 2 | AQ12: =IFERROR(AVERAGE(C12:AP12),"Нет оценок") -> 3.3 | AR12: =COUNTIF(C12:AO12,"н/у") -> 0 | AS12: =COUNTIF(C12:AP12,"н") -> 0
A13: 9. | B13: Катков Константин Александрович | C13: 5 | D13: 2 | F13: 2 | G13: \9 | H13: 5 | I13: н | L13: 5 | M13: н | N13: 2 | O13: 2 | P13: н | Q13: н | S13: н | T13: н | V13: н | X13: н | Z13: н | AA13: н | AE13: н | AF13: н | AG13: 2 | AH13: н | AI13: 2 | AQ13: =IFERROR(AVERAGE(C13:AP13),"Нет оценок") -> 3 | AR13: =COUNTIF(C13:AO13,"н/у") -> 0 | AS13: =COUNTIF(C13:AP13,"н") -> 13
A14: 10. | B14: Корнеев Андрей Александрович | D14: 2 | E14: 5 | F14: - | G14: \10 | H14: 5 | L14: 3 | M14: 5 | N14: 3 | O14: 3 | P14: 3 | Q14: 3 | R14: 3 | T14: - | AG14: 2 | AH14: 2 | AI14: 2 | AQ14: =IFERROR(AVERAGE(C14:AP14),"Нет оценок") -> 3.1538462 | AR14: =COUNTIF(C14:AO14,"н/у") -> 0 | AS14: =COUNTIF(C14:AP14,"н") -> 0
A15: 11. | B15: Макаров Максим Алексеевич | C15: 5 | D15: 3 | E15: 3 | F15: - | G15: \11 | H15: 5 | L15: 5 | M15: 5 | N15: 4 | O15: 4 | P15: 5 | Q15: 5 | R15: 5 | T15: 5 | X15: н | AG15: 5 | AH15: 5 | AI15: 5 | AQ15: =IFERROR(AVERAGE(C15:AP15),"Нет оценок") -> 4.6 | AR15: =COUNTIF(C15:AO15,"н/у") -> 0 | AS15: =COUNTIF(C15:AP15,"н") -> 1
A16: 13. | B16: Муллагалиев Вадим Радмилович | D16: 3 | F16: 5 | G16: \12 | H16: 5 | L16: 5 | M16: 2 | N16: 5 | O16: 4 | P16: 5 | Q16: 5 | R16: 5 | T16: 5 | W16: 4 | X16: н | Z16: 4 | AA16: 4 | AD16: н | AG16: 5 | AH16: 5 | AI16: 2 | AQ16: =IFERROR(AVERAGE(C16:AP16),"Нет оценок") -> 4.2941176 | AR16: =COUNTIF(C16:AO16,"н/у") -> 0 | AS16: =COUNTIF(C16:AP16,"н") -> 2
A17: 12. | B17: Натфуллин Камиль Данисович | D17: 4 | F17: н | G17: \13 | H17: н | I17: н | L17: 4 | M17: н | N17: 3 | O17: 3 | P17: н | Q17: н | S17: н | U17: н | V17: н | W17: н | X17: н | Z17: н | AG17: н | AH17: 2 | AI17: н | AQ17: =IFERROR(AVERAGE(C17:AP17),"Нет оценок") -> 3.2 | AR17: =COUNTIF(C17:AO17,"н/у") -> 0 | AS17: =COUNTIF(C17:AP17,"н") -> 14
A18: 14. | B18: Носков Ярослав Евгеньевич | D18: 5 | E18: 5 | F18: 5 | G18: \14 | H18: 5 | I18: н | L18: 4 | M18: 5 | N18: 3 | O18: 3 | P18: 5 | Q18: 5 | R18: 5 | T18: - | X18: н | AB18: н | AG18: 5 | AH18: 5 | AI18: 2 | AQ18: =IFERROR(AVERAGE(C18:AP18),"Нет оценок") -> 4.4285714 | AR18: =COUNTIF(C18:AO18,"н/у") -> 0 | AS18: =COUNTIF(C18:AP18,"н") -> 3
A19: 15. | B19: Осыка Владислав Сергеевич | D19: 5 | E19: 5 | F19: 4 | G19: \15 | H19: 4 | L19: 3 | M19: 5 | N19: 4 | O19: 4 | P19: 5 | Q19: 5 | R19: 4 | S19: 4 | T19: 4 | U19: 4 | V19: 4 | W19: 4 | Z19: 4 | AA19: 4 | AC19: н | AG19: 5 | AH19: 5 | AI19: 5 | AQ19: =IFERROR(AVERAGE(C19:AP19),"Нет оценок") -> 4.3333333 | AR19: =COUNTIF(C19:AO19,"н/у") -> 0 | AS19: =COUNTIF(C19:AP19,"н") -> 1
A20: 16. | B20: Романов Михаил Васильевич | D20: 5 | E20: 5 | F20: 5 | G20: \16 | H20: 5 | L20: 4 | M20: 5 | N20: 4 | O20: 4 | P20: 3 | Q20: 3 | R20: 3 | U20: н | V20: н | AD20: н | AG20: 2 | AH20: 2 | AI20: 2 | AQ20: =IFERROR(AVERAGE(C20:AP20),"Нет оценок") -> 3.7142857 | AR20: =COUNTIF(C20:AO20,"н/у") -> 0 | AS20: =COUNTIF(C20:AP20,"н") -> 3
A21: 17. | B21: Руфуллаев Ибрагим Фуадович | C21: 5 | D21: 5 | E21: 5 | F21: 5 | G21: \17 | H21: 5 | L21: 4 | M21: 5 | N21: 3 | O21: 3 | P21: 4 | Q21: 5 | R21: 5 | T21: - | Z21: н | AA21: н | AB21: н | AG21: 2 | AH21: н | AI21: 2 | AQ21: =IFERROR(AVERAGE(C21:AP21),"Нет оценок") -> 4.1428571 | AR21: =COUNTIF(C21:AO21,"н/у") -> 0 | AS21: =COUNTIF(C21:AP21,"н") -> 4
A22: 18. | B22: Сарычев Данила Андреевич | F22: 5 | G22: \18 | H22: 5 | L22: 5 | M22: 5 | N22: 5 | O22: 5 | P22: 5 | Q22: 5 | R22: 5 | S22: 5 | T22: 5 | U22: 5 | V22: 5 | W22: 5 | Z22: 5 | AA22: 5 | AB22: 5 | AC22: 5 | AD22: 5 | AG22: 5 | AH22: 5 | AI22: 5 | AQ22: =IFERROR(AVERAGE(C22:AP22),"Нет оценок") -> 5 | AR22: =COUNTIF(C22:AO22,"н/у") -> 0 | AS22: =COUNTIF(C22:AP22,"н") -> 0
A23: 19. | B23: Сурков Кирилл Александрович | C23: 5 | D23: 5 | E23: 5 | G23: \19 | H23: 5 | L23: 5 | M23: 4 | N23: 5 | O23: 5 | P23: 5 | Q23: 5 | R23: 5 | S23: 5 | U23: 5 | V23: 5 | W23: н | X23: н | Z23: н | AA23: н | AB23: н | AC23: н | AD23: н | AG23: н | AH23: 2 | AI23: н | AQ23: =IFERROR(AVERAGE(C23:AP23),"Нет оценок") -> 4.7333333 | AR23: =COUNTIF(C23:AO23,"н/у") -> 0 | AS23: =COUNTIF(C23:AP23,"н") -> 9
A24: 20. | B24: Усатов Тимофей Анатольевич | D24: 5 | E24: 5 | F24: 5 | G24: \20 | H24: 5 | L24: 5 | M24: 5 | N24: 4 | O24: 4 | P24: 5 | Q24: 5 | R24: 5 | S24: 5 | T24: - | U24: 5 | V24: 5 | W24: 5 | Z24: 5 | AA24: 5 | AB24: 5 | AC24: 5 | AD24: 5 | AG24: 5 | AH24: 5 | AI24: 5 | AQ24: =IFERROR(AVERAGE(C24:AP24),"Нет оценок") -> 4.9130435 | AR24: =COUNTIF(C24:AO24,"н/у") -> 0 | AS24: =COUNTIF(C24:AP24,"н") -> 0
A25: 21. | B25: Халитов Кирилл Родионович | D25: 4 | F25: н/у | G25: \1 | H25: н | I25: н | L25: 5 | M25: н | N25: 3 | O25: 3 | P25: н/у | Q25: н/у | R25: н | T25: н | U25: н | V25: н | W25: н | X25: н | Z25: н | AA25: н | AB25: н | AC25: н | AD25: н | AE25: н | AF25: н | AG25: 5 | AH25: 4 | AI25: н | AQ25: =IFERROR(AVERAGE(C25:AP25),"Нет оценок") -> 4 | AR25: =COUNTIF(C25:AO25,"н/у") -> 3 | AS25: =COUNTIF(C25:AP25,"н") -> 17
A26: 21. | B26: Хорошилов Игорь Александрович | AQ26: =IFERROR(AVERAGE(C26:AP26),"Нет оценок") -> Нет оценок | AR26: =COUNTIF(C26:AO26,"н/у") -> 0 | AS26: =COUNTIF(C26:AP26,"н") -> 0
A27: 22. | B27: Хрычёв Мирон Евгеньевич | D27: 2 | G27: \3 | H27: н/у | I27: н/у | L27: 2 | M27: н | N27: 3 | O27: 3 | P27: 4 | Q27: 3 | R27: 3 | T27: - | W27: 4 | X27: н | Z27: 4 | AA27: 4 | AB27: н | AG27: 5 | AH27: 5 | AI27: 5 | AQ27: =IFERROR(AVERAGE(C27:AP27),"Нет оценок") -> 3.6153846 | AR27: =COUNTIF(C27:AO27,"н/у") -> 2 | AS27: =COUNTIF(C27:AP27,"н") -> 3
A28: 23. | B28: Цапов Илья Валерьевич | D28: 3 | E28: 5 | G28: \4 | H28: 5 | L28: 5 | M28: 2 | N28: 5 | O28: 5 | P28: 5 | Q28: 5 | R28: 5 | S28: н | T28: 5 | X28: н | Z28: н | AA28: н | AB28: н | AC28: н | AG28: 2 | AH28: 2 | AI28: 2 | AQ28: =IFERROR(AVERAGE(C28:AP28),"Нет оценок") -> 4 | AR28: =COUNTIF(C28:AO28,"н/у") -> 0 | AS28: =COUNTIF(C28:AP28,"н") -> 6
N29: ПР 1 | O29: ПР 1 | P29: ПР 2 | Q29: ПР 2 | R29: ПР 2 | S29: ПР 3 | U29: ПР 3 | V29: ПР 3 | W29: ПР 4 | X29: ПР 4 | Z29: ПР 4 | AA29: ПР 4 | AB29: ПР 5 | AC29: ПР 5 | AD29: ПР 5 | AG29: Дневник | AH29: Дневник | AI29: Дневник | AQ29: =IFERROR(AVERAGE(AQ6:AQ28),"") -> 4.0371868 | AR29: =SUM(AR6:AR28) -> 5 | AS29: =SUM(AS6:AS28) -> 98
A30: Дата | B30: Тема / ДЗ
A31: 45902 | B31: 1.1. Категории пользовательских интерфейсов информационных систем (1-9 слайды) + Задание
A32: 45905 | B32: 1.1. Категории пользовательских интерфейсов информационных систем (9-15 слайды) + Задание
A33: 45926 | B33: 1.2. Элементы опыта взаимодействия в системе человек-компьютер (1-6 слайды) + Задание
A34: 45958 | B34: Задание по проектированию 1
A35: 45959 | B35: Задание по проектированию 2
A36: 45967 | B36: Подготовкак к коллоквиуму, письменные ответы на вопросы
A37: 45996 | B37: 2.1. Основы WEB дизайна
A38: 45997 | B38: Практическая работа 1 - html
A39: 45997 | B39: Практическая работа 1 - html
A40: 45999 | B40: Практическая работа 2 - html
A41: 45999 | B41: Практическая работа 2 - html
A42: 46001 | B42: Практическая работа 3 - html
... A55: 46118 | B55: Выполнение заданий по книге "Основы формального языка описания внешнего вида документа CSS" - 10 тема.

Sheet Физ.ра
A1: Наименование предмета | C1: Физическая культура
A2: ФИО преподавателя | C2: Патраков Андрей Иванович
A3: ИСиП 24/2 | B3: Месяц | C3: группа | D3: сен | E3: сен | F3: сен | G3: окт | H3: окт | I3: окт | J3: окт | K3: окт | L3: ноя | M3: ноя | N3: ноя | O3: дек | P3: дек | Q3: дек | T3: фев | U3: фев | V3: фев | W3: март | BJ3: 3 сем | BK3: 4 сем | BM3: Пропуски
B4: Число | C4: здоровья | D4: 3 | E4: 9 | F4: 23 | G4: 15 | H4: 24 | I4: 29 | J4: 29 | K4: 31 | L4: 5 | M4: 12 | N4: 21 | O4: 3 | P4: 12 | Q4: 12 | R4: 19 | T4: 18 | U4: 21 | V4: 21 | W4: 10 | BJ4: З | BK4: З | BL4: Средний балл | BM4: Уваж. | BN4: Неуваж.
A5: 1. | B5: Адилбеков Бектур | C5: осн | E5: 5 | F5: 5 | G5: н/отр | H5: 3 | I5: 5 | J5: 5 | K5: 5 | L5: н/отр | M5: 5 | N5: н | O5: н | P5: 3 | Q5: 5 | R5: н | T5: 3 | U5: н | V5: н | W5: н | BJ5: неявка | BL5: =IFERROR(AVERAGE(C5:BK5),"Нет оценок") -> 4.4 | BM5: =COUNTIF(C5:BK5,"н/у") -> 0 | BN5: =COUNTIF(C5:BK5,"н") -> 6
A6: 2. | B6: Ахметов Артём Рамилевич | C6: подг | E6: 5 | F6: 5 | G6: н/отр | H6: н/отр | I6: н/отр | J6: н/отр | K6: 3 | L6: н/отр | M6: 5 | N6: 3 | O6: 3 | P6: 3 | Q6: 3 | R6: 5 | T6: н | U6: 5 | V6: 5 | W6: 3 | BJ6: зачтено | BL6: =IFERROR(AVERAGE(C6:BK6),"Нет оценок") -> 4 | BM6: =COUNTIF(C6:BK6,"н/у") -> 0 | BN6: =COUNTIF(C6:BK6,"н") -> 1
A7: 3. | B7: Бараников Владислав Михайлович | C7: осн | E7: 5 | F7: 5 | G7: 5 | H7: 5 | I7: 5 | J7: 5 | K7: 5 | L7: 5 | M7: 5 | N7: 5 | O7: 5 | P7: 5 | Q7: 5 | R7: 5 | T7: 5 | U7: 5 | V7: 5 | W7: 5 | BJ7: зачтено | BL7: =IFERROR(AVERAGE(C7:BK7),"Нет оценок") -> 5 | BM7: =COUNTIF(C7:BK7,"н/у") -> 0 | BN7: =COUNTIF(C7:BK7,"н") -> 0
A8: 4. | B8: Борсук Артём Дмитриевич | C8: осн | E8: 3 | F8: 3 | G8: 5 | H8: н/отр | I8: 3 | J8: 5 | K8: 5 | L8: 5 | M8: 5 | N8: 5 | O8: 5 | P8: 5 | Q8: 5 | T8: 5 | U8: 5 | V8: 5 | W8: н | BJ8: зачтено | BL8: =IFERROR(AVERAGE(C8:BK8),"Нет оценок") -> 4.6 | BM8: =COUNTIF(C8:BK8,"н/у") -> 0 | BN8: =COUNTIF(C8:BK8,"н") -> 1
A9: 5. | B9: Гильманов Ильназ Максимович | C9: осн | E9: н/отр | F9: 3 | G9: 5 | H9: 5 | I9: 5 | J9: 5 | K9: 5 | L9: 5 | M9: 5 | N9: 5 | O9: 5 | P9: 5 | Q9: 5 | R9: 5 | T9: 5 | U9: 5 | V9: 5 | W9: н | BJ9: зачтено | BL9: =IFERROR(AVERAGE(C9:BK9),"Нет оценок") -> 4.875 | BM9: =COUNTIF(C9:BK9,"н/у") -> 0 | BN9: =COUNTIF(C9:BK9,"н") -> 1
A10: 6. | B10: Говтва Илья Денисович | C10: осн | E10: 5 | F10: 5 | G10: 5 | H10: 5 | I10: 5 | J10: 5 | K10: 5 | L10: 5 | M10: 5 | N10: 5 | O10: 5 | P10: 5 | Q10: 5 | R10: 5 | T10: 5 | U10: 5 | V10: 5 | W10: 5 | BJ10: зачтено | BL10: =IFERROR(AVERAGE(C10:BK10),"Нет оценок") -> 5 | BM10: =COUNTIF(C10:BK10,"н/у") -> 0 | BN10: =COUNTIF(C10:BK10,"н") -> 0
A11: 7. | B11: Горшков Владислав Васильевич | C11: осн | E11: 5 | F11: 5 | G11: 5 | H11: 5 | I11: 5 | J11: 5 | K11: 5 | L11: 5 | M11: 5 | N11: н/у | O11: 5 | P11: 5 | Q11: 5 | R11: 5 | T11: 5 | U11: н | V11: н | W11: 5 | BJ11: зачтено | BL11: =IFERROR(AVERAGE(C11:BK11),"Нет оценок") -> 5 | BM11: =COUNTIF(C11:BK11,"н/у") -> 1 | BN11: =COUNTIF(C11:BK11,"н") -> 2
A12: 8. | B12: Гришко Илья Алексеевич | C12: осн | E12: н/отр | F12: н/отр | G12: 5 | H12: 5 | I12: 3 | J12: 5 | K12: 5 | L12: 3 | M12: 4 | N12: 5 | O12: 5 | P12: 5 | Q12: 5 | R12: 5 | T12: 5 | U12: н | V12: н | W12: 3 | BJ12: зачтено | BL12: =IFERROR(AVERAGE(C12:BK12),"Нет оценок") -> 4.5 | BM12: =COUNTIF(C12:BK12,"н/у") -> 0 | BN12: =COUNTIF(C12:BK12,"н") -> 2
A13: 9. | B13: Катков Константин Александрович | C13: осн | E13: 5 | F13: 3 | G13: н/отр | H13: 3 | I13: н/отр | J13: н/отр | K13: н/отр | L13: 3 | M13: 5 | N13: 3 | O13: 5 | P13: н | Q13: н | R13: н | T13: н | U13: н | V13: н | W13: н | BJ13: неявка | BL13: =IFERROR(AVERAGE(C13:BK13),"Нет оценок") -> 3.8571429 | BM13: =COUNTIF(C13:BK13,"н/у") -> 0 | BN13: =COUNTIF(C13:BK13,"н") -> 7
A14: 10. | B14: Корнеев Андрей Александрович | C14: подг | E14: 5 | F14: 5 | G14: 5 | H14: н/отр | I14: 3 | J14: 5 | K14: 5 | L14: 5 | M14: 5 | O14: 5 | P14: 5 | Q14: 5 | T14: 5 | U14: 5 | V14: 5 | W14: 5 | BJ14: зачтено | BL14: =IFERROR(AVERAGE(C14:BK14),"Нет оценок") -> 4.8666667 | BM14: =COUNTIF(C14:BK14,"н/у") -> 0 | BN14: =COUNTIF(C14:BK14,"н") -> 0
A15: 11. | B15: Макаров Максим Алексеевич | C15: осн | E15: 5 | F15: н/у | G15: 5 | H15: 5 | I15: 5 | J15: 5 | K15: 5 | L15: 5 | M15: 5 | N15: 5 | O15: 5 | P15: 5 | Q15: 5 | T15: н | U15: 5 | V15: 5 | W15: 5 | BJ15: зачтено | BL15: =IFERROR(AVERAGE(C15:BK15),"Нет оценок") -> 5 | BM15: =COUNTIF(C15:BK15,"н/у") -> 1 | BN15: =COUNTIF(C15:BK15,"н") -> 1
A16: 13. | B16: Муллагалиев Вадим Радмилович | C16: осн | E16: 5 | F16: 5 | G16: 5 | H16: 5 | I16: 5 | J16: 5 | K16: 5 | L16: 5 | M16: 5 | N16: н/у | O16: 5 | P16: 5 | Q16: 5 | T16: 5 | U16: н | V16: н | W16: 5 | BJ16: зачтено | BL16: =IFERROR(AVERAGE(C16:BK16),"Нет оценок") -> 5 | BM16: =COUNTIF(C16:BK16,"н/у") -> 1 | BN16: =COUNTIF(C16:BK16,"н") -> 2
A17: 12. | B17: Натфуллин Камиль Данисович | C17: осн | D17: н/отр | E17: н/отр | F17: н/отр | G17: н/отр | H17: н/отр | I17: н/отр | J17: н/отр | K17: н/отр | L17: н/отр | M17: н/отр | N17: н/отр | O17: 3 | P17: 3 | Q17: 3 | T17: н | U17: н | V17: н | W17: н | BJ17: не зачтено | BL17: =IFERROR(AVERAGE(C17:BK17),"Нет оценок") -> 3 | BM17: =COUNTIF(C17:BK17,"н/у") -> 0 | BN17: =COUNTIF(C17:BK17,"н") -> 4
A18: 14. | B18: Носков Ярослав Евгеньевич | C18: подг | E18: 5 | F18: 5 | G18: 5 | H18: 5 | I18: н/отр | J18: н/отр | K18: 5 | L18: 3 | M18: 5 | N18: 5 | O18: 5 | P18: 5 | Q18: 5 | T18: 5 | U18: 5 | V18: 5 | W18: н | BJ18: зачтено | BL18: =IFERROR(AVERAGE(C18:BK18),"Нет оценок") -> 4.8571429 | BM18: =COUNTIF(C18:BK18,"н/у") -> 0 | BN18: =COUNTIF(C18:BK18,"н") -> 1
A19: 15. | B19: Осыка Владислав Сергеевич | C19: осн | E19: 5 | F19: 5 | G19: 5 | H19: 5 | I19: 5 | J19: 5 | K19: 5 | L19: н/отр | M19: 4 | N19: 5 | O19: 3 | P19: 5 | Q19: 5 | T19: 5 | U19: 5 | V19: 5 | W19: 5 | BJ19: зачтено | BL19: =IFERROR(AVERAGE(C19:BK19),"Нет оценок") -> 4.8125 | BM19: =COUNTIF(C19:BK19,"н/у") -> 0 | BN19: =COUNTIF(C19:BK19,"н") -> 0
A20: 16. | B20: Романов Михаил Васильевич | C20: осн | E20: 5 | F20: 5 | G20: 5 | H20: 5 | I20: 5 | J20: 5 | K20: 5 | L20: 5 | M20: 5 | N20: 5 | O20: 5 | T20: 5 | U20: н | V20: н | W20: 5 | BJ20: зачтено | BL20: =IFERROR(AVERAGE(C20:BK20),"Нет оценок") -> 5 | BM20: =COUNTIF(C20:BK20,"н/у") -> 0 | BN20: =COUNTIF(C20:BK20,"н") -> 2
A21: 17. | B21: Руфуллаев Ибрагим Фуадович | C21: осн | E21: 5 | F21: 5 | G21: н/отр | H21: 5 | I21: 3 | J21: 5 | K21: 4 | L21: 3 | M21: 5 | N21: 5 | O21: 5 | P21: 5 | Q21: 5 | T21: 5 | U21: 5 | V21: 5 | W21: 3 | BJ21: зачтено | BL21: =IFERROR(AVERAGE(C21:BK21),"Нет оценок") -> 4.5625 | BM21: =COUNTIF(C21:BK21,"н/у") -> 0 | BN21: =COUNTIF(C21:BK21,"н") -> 0
A22: 18. | B22: Сарычев Данила Андреевич | C22: осн | E22: 5 | F22: 5 | G22: н/отр | H22: н/отр | I22: 3 | J22: 5 | K22: 5 | L22: 5 | M22: 5 | O22: н/отр | P22: 5 | Q22: 5 | T22: 5 | U22: н | V22: н | W22: 5 | BJ22: зачтено | BL22: =IFERROR(AVERAGE(C22:BK22),"Нет оценок") -> 4.8181818 | BM22: =COUNTIF(C22:BK22,"н/у") -> 0 | BN22: =COUNTIF(C22:BK22,"н") -> 2
A23: 19. | B23: Сурков Кирилл Александрович | C23: спец | D23: н | E23: н | F23: н | G23: н | H23: н | I23: н | J23: н | K23: н | L23: н | M23: н | N23: н | O23: н | P23: н | Q23: н | T23: н | U23: 5 | V23: 5 | W23: н | BJ23: неявка | BL23: =IFERROR(AVERAGE(C23:BK23),"Нет оценок") -> 5 | BM23: =COUNTIF(C23:BK23,"н/у") -> 0 | BN23: =COUNTIF(C23:BK23,"н") -> 16
A24: 20. | B24: Усатов Тимофей Анатольевич | C24: осн | E24: 5 | F24: 5 | G24: 5 | H24: 5 | I24: 5 | J24: 5 | K24: 5 | L24: 5 | M24: 5 | N24: 5 | O24: 5 | T24: 5 | U24: 5 | V24: 5 | W24: 5 | BJ24: зачтено | BL24: =IFERROR(AVERAGE(C24:BK24),"Нет оценок") -> 5 | BM24: =COUNTIF(C24:BK24,"н/у") -> 0 | BN24: =COUNTIF(C24:BK24,"н") -> 0
A25: 21. | B25: Халитов Кирилл Родионович | C25: подг | D25: н/отр | E25: н/отр | F25: н | G25: н | H25: н | I25: н | J25: н | K25: н | L25: н | M25: 2 | N25: 3 | O25: н/у | P25: н | Q25: н | T25: н | U25: н | V25: н | W25: н | BJ25: неявка | BL25: =IFERROR(AVERAGE(C25:BK25),"Нет оценок") -> 2.5 | BM25: =COUNTIF(C25:BK25,"н/у") -> 1 | BN25: =COUNTIF(C25:BK25,"н") -> 13
A26: 21. | B26: Хорошилов Игорь Александрович | BJ26: зачтено | BL26: =IFERROR(AVERAGE(C26:BK26),"Нет оценок") -> Нет оценок | BM26: =COUNTIF(C26:BK26,"н/у") -> 0 | BN26: =COUNTIF(C26:BK26,"н") -> 0
A27: 22. | B27: Хрычев Мирон Евгеньевич | C27: осн | E27: 5 | F27: 5 | G27: 5 | H27: н/у | I27: н/у | J27: н/у | K27: н/у | L27: н/у | M27: н/у | N27: н/у | O27: н/у | P27: 5 | Q27: 5 | T27: н | U27: 5 | V27: 5 | W27: 5 | BJ27: зачтено | BL27: =IFERROR(AVERAGE(C27:BK27),"Нет оценок") -> 5 | BM27: =COUNTIF(C27:BK27,"н/у") -> 8 | BN27: =COUNTIF(C27:BK27,"н") -> 1
A28: 23. | B28: Цапов Илья Валерьевич | C28: подг | E28: 5 | F28: 5 | G28: н/у/ | H28: 5 | I28: 5 | J28: 5 | K28: н/отр | L28: н/отр | M28: 5 | N28: н/отр | O28: 5 | P28: 5 | Q28: 5 | T28: 5 | U28: 5 | V28: 5 | W28: 5 | BJ28: зачтено | BL28: =IFERROR(AVERAGE(C28:BK28),"Нет оценок") -> 5 | BM28: =COUNTIF(C28:BK28,"н/у") -> 0 | BN28: =COUNTIF(C28:BK28,"н") -> 0
A29: Дата | B29: Тема / ДЗ | BL29: =IFERROR(AVERAGE(BL5:BL28),"") -> 4.5934406 | BM29: =SUM(BM5:BM28) -> 12 | BN29: =SUM(BN5:BN28) -> 62
A30: 45903 | B30: Инструктаж по Ф.К.
A31: 45909 | B31: ОФП. (Геолог)
A32: 45923 | B32: ОФП+спортивные игры. (Геолог)
A33: 45945 | B33: ОФП+спортивные игры. (Геолог)
A34: 45954 | B34: ОФП+спортивные игры. (Геолог)
A35: 45959 | B35: ОФП+спортивные игры. (32 школа)
A36: 45959 | B36: ОФП+спортивные игры. (32 школа)
A37: 45961 | B37: ОФП+спортивные игры. (32 школа)
A38: 45966 | B38: ОФП+спортивные игры. (Геолог)
A39: 45973 | B39: ОФП+спортивные игры. (Геолог)
A40: 45982 | B40: ОФП+спортивные игры. (Геолог)
A41: 45994 | B41: ОФП+спортивные игры. (Геолог)
... A49: 46091 | B49: ОФП+спортивные игры. (Геолог)

Sheet Элемент выш мат
A1: Наименование предмета | C1: Элементы высшей математики
A2: ФИО преподавателя | C2: Алпаева Валентина Викторовна
A3: ИСиП 24/2 | B3: Месяц | C3: Сентябрь | H3: Октябрь | K3: Ноябрь | R3: Декабрь | Y3: Январь | AG3: Февраль | AJ3: Апрель | BQ3: 4 сем | BS3: Пропуски
B4: Число | C4: 5 | D4: 9 | E4: 9 | F4: 11 | G4: 17 | H4: 7 | I4: 9 | J4: 14 | K4: 10 | L4: 10 | M4: 17 | N4: 18 | O4: 18 | P4: 20 | R4: 4 | S4: 5 | T4: 5 | U4: 8 | V4: 10 | W4: 16 | X4: 26 | Y4: 12 | Z4: 19 | AA4: 20 | AB4: 21 | AC4: 23 | AD4: 26 | AE4: 27 | AF4: 31 | AG4: 3 | AH4: 6 | AI4: 14 | AJ4: 6 | BQ4: Экз | BR4: Средний балл | BS4: Уваж. | BT4: Неуваж.
A5: 1. | B5: Адилбеков Бектур | C5: + | E5: 2 | F5: 5 | G5: 5 | J5: 2 | K5: оп | P5: 2 | Q5: 3 | R5: н | S5: н | T5: 3 | U5: н | V5: н | W5: 3 | X5: н | Y5: + | Z5: оп | AA5: 5 | AB5: н | AC5: н | AF5: оп | AG5: н | AH5: н | AI5: н/у | AJ5: н | BR5: =IFERROR(AVERAGE(C5:BQ5),"Нет оценок") -> 3.3333333 | BS5: =COUNTIF(C5:BQ5,"н/у") -> 1 | BT5: =COUNTIF(C5:BQ5,"н") -> 10
A6: 2. | B6: Ахметов Артём Рамилевич | E6: 5 | F6: 5 | G6: + | H6: 5 | I6: н | J6: н/у | K6: н/отр | N6: оп | P6: н | R6: н | T6: 2 | V6: н | W6: н | X6: 5 | Y6: + | Z6: 5 | AA6: н | AB6: н | AC6: н | AF6: н | AG6: 2 | AH6: н | AI6: оп | AJ6: 4 | BR6: =IFERROR(AVERAGE(C6:BQ6),"Нет оценок") -> 4.125 | BS6: =COUNTIF(C6:BQ6,"н/у") -> 1 | BT6: =COUNTIF(C6:BQ6,"н") -> 10
A7: 3. | B7: Бараников Владислав Михайлович | E7: 4 | F7: 5 | G7: оп | H7: 5 | J7: 3 | N7: 4 | P7: 5 | Q7: 4 | R7: 4 | T7: 2 | W7: 3 | X7: 5 | Y7: + | Z7: 2 | AA7: ? | AB7: н/отр | AC7: 5 | AG7: 2 | AI7: н | AJ7: y | BR7: =IFERROR(AVERAGE(C7:BQ7),"Нет оценок") -> 3.7857143 | BS7: =COUNTIF(C7:BQ7,"н/у") -> 0 | BT7: =COUNTIF(C7:BQ7,"н") -> 1
A8: 4. | B8: Борсук Артём Дмитриевич | E8: 4 | F8: н | G8: н | H8: 4 | J8: 2 | K8: оп | N8: оп | P8: 2 | Q8: 3 | R8: 4 | T8: 2 | W8: н | X8: н | Y8: ? | Z8: 3 | AA8: ? | AB8: 3 | AC8: 5 | AE8: н | AG8: 4 | AI8: н | AJ8: 4 | BR8: =IFERROR(AVERAGE(C8:BQ8),"Нет оценок") -> 3.3333333 | BS8: =COUNTIF(C8:BQ8,"н/у") -> 0 | BT8: =COUNTIF(C8:BQ8,"н") -> 6
A9: 5. | B9: Гильманов Ильназ Максимович | E9: 4 | G9: + | I9: оп | J9: н/отр | P9: 2 | Q9: 4 | R9: оп | T9: 2 | W9: 3 | X9: н | Y9: + | Z9: 3 | AA9: 4 | AB9: 4 | AC9: 2 | AD9: н | AE9: н | AG9: 4 | AJ9: 5 | BR9: =IFERROR(AVERAGE(C9:BQ9),"Нет оценок") -> 3.3636364 | BS9: =COUNTIF(C9:BQ9,"н/у") -> 0 | BT9: =COUNTIF(C9:BQ9,"н") -> 3
A10: 6. | B10: Говтва Илья Денисович | E10: 4 | G10: 5 | H10: 5 | J10: 3 | P10: 5 | Q10: 4 | R10: 4 | S10: 4 | T10: 2 | U10: 4 | V10: оп | W10: 3 | X10: 5 | Y10: + | Z10: 3 | AA10: 5 | AB10: 4 | AC10: 5 | AG10: 4 | AJ10: 4 | BR10: =IFERROR(AVERAGE(C10:BQ10),"Нет оценок") -> 4.0555556 | BS10: =COUNTIF(C10:BQ10,"н/у") -> 0 | BT10: =COUNTIF(C10:BQ10,"н") -> 0
A11: 7. | B11: Горшков Владислав Васильевич | C11: н | E11: 5 | F11: н | G11: + | J11: 2 | K11: н/отр | M11: н/у/отр | N11: н/у | O11: н/у | P11: н/у | R11: 4 | T11: 2 | W11: 3 | X11: 5 | Y11: + | Z11: 3 | AA11: ? | AB11: 4 | AC11: 5 | AF11: н/отр | AG11: 4 | AI11: оп | AJ11: 3 | BR11: =IFERROR(AVERAGE(C11:BQ11),"Нет оценок") -> 3.6363636 | BS11: =COUNTIF(C11:BQ11,"н/у") -> 3 | BT11: =COUNTIF(C11:BQ11,"н") -> 2
A12: 8. | B12: Гришко Илья Алексеевич | C12: н/отр | E12: 4 | F12: н/отр | G12: н/отр | I12: н | K12: оп/+ | P12: 2 | T12: 2 | U12: 5 | V12: 2 | W12: 3 | X12: 4 | Y12: + | Z12: 3 | AA12: н | AB12: н | AC12: 4 | AD12: н | AG12: 2 | AJ12: 3 | BR12: =IFERROR(AVERAGE(C12:BQ12),"Нет оценок") -> 3.0909091 | BS12: =COUNTIF(C12:BQ12,"н/у") -> 0 | BT12: =COUNTIF(C12:BQ12,"н") -> 4
A13: 9. | B13: Катков Константин Александрович | D13: н | E13: 2 | G13: 2 | H13: 3 | I13: оп | M13: 4 | N13: н | O13: н | P13: 3 | R13: н | T13: 2 | U13: н | V13: 2 | W13: 2 | X13: н | Y13: н | Z13: 2 | AA13: н | AB13: н | AC13: н | AD13: н | AE13: н | AF13: н | AG13: н | AI13: н | AJ13: 2 | BR13: =IFERROR(AVERAGE(C13:BQ13),"Нет оценок") -> 2.4 | BS13: =COUNTIF(C13:BQ13,"н/у") -> 0 | BT13: =COUNTIF(C13:BQ13,"н") -> 15
A14: 10. | B14: Корнеев Андрей Александрович | E14: 2 | J14: н/отр | P14: 2 | T14: 2 | W14: 2 | X14: 2 | Y14: + | Z14: 2 | AA14: ? | AB14: н | AC14: 3 | AD14: н | AG14: н | AJ14: 2 | BR14: =IFERROR(AVERAGE(C14:BQ14),"Нет оценок") -> 2.125 | BS14: =COUNTIF(C14:BQ14,"н/у") -> 0 | BT14: =COUNTIF(C14:BQ14,"н") -> 3
A15: 11. | B15: Макаров Максим Алексеевич | E15: 4 | I15: н/отр | J15: 3 | K15: 4 | P15: 4 | R15: 4 | T15: 2 | V15: 2 | W15: 2 | X15: 5 | Z15: 3 | AA15: ? | AB15: 5 | AC15: 3 | AG15: н | AJ15: 2 | BR15: =IFERROR(AVERAGE(C15:BQ15),"Нет оценок") -> 3.3076923 | BS15: =COUNTIF(C15:BQ15,"н/у") -> 0 | BT15: =COUNTIF(C15:BQ15,"н") -> 1
A16: 13. | B16: Муллагалиев Вадим Радмилович | C16: н | E16: 4 | G16: н | J16: 3 | K16: оп | N16: н/отр | O16: н | P16: н/у | R16: 4 | T16: 2 | V16: оп | W16: 3 | X16: н | Y16: ? | Z16: 3 | AA16: н | AB16: н | AC16: 2 | AF16: н | AG16: 2 | AH16: н | AI16: оп | AJ16: 4 | BR16: =IFERROR(AVERAGE(C16:BQ16),"Нет оценок") -> 3 | BS16: =COUNTIF(C16:BQ16,"н/у") -> 1 | BT16: =COUNTIF(C16:BQ16,"н") -> 8
A17: 12. | B17: Натфуллин Камиль Данисович | E17: 4 | F17: н | G17: оп | H17: н | I17: н | J17: н | K17: н | L17: н | M17: н/у | N17: оп | P17: н | R17: н | T17: 2 | U17: н | V17: н | W17: 2 | X17: н | Y17: н | Z17: 3 | AA17: ? | AB17: н | AC17: 5 | AE17: н | AF17: оп | AG17: 4 | AH17: оп | AI17: оп | AJ17: н | BR17: =IFERROR(AVERAGE(C17:BQ17),"Нет оценок") -> 3.3333333 | BS17: =COUNTIF(C17:BQ17,"н/у") -> 1 | BT17: =COUNTIF(C17:BQ17,"н") -> 15
A18: 14. | B18: Носков Ярослав Евгеньевич | E18: 4 | G18: + | H18: 3 | J18: 2 | P18: 5 | T18: 2 | U18: н | W18: 2 | X18: н | Y18: + | Z18: 2 | AA18: ? | AB18: н | AC18: н | AD18: н | AG18: н | AJ18: 4 | BR18: =IFERROR(AVERAGE(C18:BQ18),"Нет оценок") -> 3 | BS18: =COUNTIF(C18:BQ18,"н/у") -> 0 | BT18: =COUNTIF(C18:BQ18,"н") -> 6
A19: 15. | B19: Осыка Владислав Сергеевич | E19: 3 | F19: 4 | G19: оп | H19: н/отр | J19: н/отр | K19: оп | N19: оп | O19: 4 | P19: 2 | Q19: 3 | R19: 3 | T19: 2 | U19: + | V19: оп | W19: 3 | X19: 5 | Y19: н | Z19: 3 | AA19: 5 | AB19: 4 | AC19: 2 | AG19: 4 | AJ19: 3 | BR19: =IFERROR(AVERAGE(C19:BQ19),"Нет оценок") -> 3.3333333 | BS19: =COUNTIF(C19:BQ19,"н/у") -> 0 | BT19: =COUNTIF(C19:BQ19,"н") -> 1
A20: 16. | B20: Романов Михаил Васильевич | E20: 4 | G20: + | J20: 2 | P20: 4 | Q20: 3 | R20: 3 | T20: 2 | U20: 4 | V20: н | W20: 3 | X20: 4 | Y20: + | Z20: 2 | AA20: н | AB20: 3 | AC20: н | AG20: 4 | AJ20: 2 | BR20: =IFERROR(AVERAGE(C20:BQ20),"Нет оценок") -> 3.0769231 | BS20: =COUNTIF(C20:BQ20,"н/у") -> 0 | BT20: =COUNTIF(C20:BQ20,"н") -> 3
A21: 17. | B21: Руфуллаев Ибрагим Фуадович | E21: 3 | G21: 4 | H21: 4 | J21: 2 | K21: оп | N21: + | P21: 2 | Q21: 4 | R21: 4 | T21: 2 | U21: + | V21: оп | W21: 3 | X21: 5 | Y21: + | Z21: 3 | AA21: н | AB21: н | AC21: н | AD21: н | AE21: н | AF21: + | AG21: н | AJ21: 4 | BR21: =IFERROR(AVERAGE(C21:BQ21),"Нет оценок") -> 3.3333333 | BS21: =COUNTIF(C21:BQ21,"н/у") -> 0 | BT21: =COUNTIF(C21:BQ21,"н") -> 6
A22: 18. | B22: Сарычев Данила Андреевич | C22: н/отр | E22: 4 | G22: 4 | J22: 2 | M22: + | P22: 5 | Q22: 3 | T22: 3 | U22: 4 | W22: 3 | X22: 4 | Y22: + | Z22: 3 | AA22: 4 | AB22: 4 | AC22: 2 | AF22: н | AG22: 4 | AI22: н | AJ22: 3 | BR22: =IFERROR(AVERAGE(C22:BQ22),"Нет оценок") -> 3.4666667 | BS22: =COUNTIF(C22:BQ22,"н/у") -> 0 | BT22: =COUNTIF(C22:BQ22,"н") -> 2
A23: 19. | B23: Сурков Кирилл Александрович | D23: н | E23: 4 | F23: 5 | G23: н | H23: 4 | I23: оп | J23: 3 | K23: оп/+ | M23: оп | N23: н | P23: 4 | Q23: 4 | R23: 4 | T23: 3 | V23: н | W23: н | X23: н | Y23: н | Z23: н | AA23: н | AB23: 3 | AC23: 5 | AD23: н | AE23: н | AF23: 4 | AG23: 4 | AH23: н | AI23: н | AJ23: н | BR23: =IFERROR(AVERAGE(C23:BQ23),"Нет оценок") -> 3.9166667 | BS23: =COUNTIF(C23:BQ23,"н/у") -> 0 | BT23: =COUNTIF(C23:BQ23,"н") -> 14
A24: 20. | B24: Усатов Тимофей Анатольевич | E24: 3 | G24: 4 | J24: 3 | R24: 4 | T24: 2 | U24: + | V24: н/у/отр | W24: 3 | X24: 5 | Y24: + | Z24: 3 | AA24: 4 | AB24: 4 | AC24: 4 | AF24: 4 | AG24: 4 | AJ24: 4 | BR24: =IFERROR(AVERAGE(C24:BQ24),"Нет оценок") -> 3.6428571 | BS24: =COUNTIF(C24:BQ24,"н/у") -> 0 | BT24: =COUNTIF(C24:BQ24,"н") -> 0
A25: 21. | B25: Халитов Кирилл Родионович | D25: н | E25: 2 | G25: н | I25: н | J25: 2 | K25: н | L25: н | N25: н | O25: н | P25: 2 | Q25: 3 | R25: н/у | S25: н/у | T25: н/у | U25: н/у | V25: 2 | W25: н | X25: н | Y25: 2 | Z25: н | AA25: н | AB25: н | AC25: н | AE25: н | AF25: н | AG25: н | AI25: н | AJ25: н | BR25: =IFERROR(AVERAGE(C25:BQ25),"Нет оценок") -> 2.1666667 | BS25: =COUNTIF(C25:BQ25,"н/у") -> 4 | BT25: =COUNTIF(C25:BQ25,"н") -> 18
A26: 21. | B26: Хорошилов Игорь Александрович | BR26: =IFERROR(AVERAGE(C26:BQ26),"Нет оценок") -> Нет оценок | BS26: =COUNTIF(C26:BQ26,"н/у") -> 0 | BT26: =COUNTIF(C26:BQ26,"н") -> 0
A27: 22. | B27: Хрычев Мирон Евгеньевич | E27: 4 | G27: + | J27: 2 | N27: н | P27: 3 | R27: н | T27: 2 | U27: н | W27: 3 | X27: 5 | Y27: + | Z27: 2 | AA27: ? | AB27: н | AC27: 2 | AG27: н | AJ27: 2 | BR27: =IFERROR(AVERAGE(C27:BQ27),"Нет оценок") -> 2.7777778 | BS27: =COUNTIF(C27:BQ27,"н/у") -> 0 | BT27: =COUNTIF(C27:BQ27,"н") -> 5
A28: 23. | B28: Цапов Илья Валерьевич | D28: н | E28: 3 | I28: н/у | J28: н/у | K28: оп | M28: 4 | P28: 3 | Q28: 4 | R28: 3 | T28: 3 | V28: 4 | W28: н | X28: н | Y28: ? | Z28: 4 | AA28: 4 | AB28: н | AC28: н | AD28: н | AG28: н | AI28: н | AJ28: н | BR28: =IFERROR(AVERAGE(C28:BQ28),"Нет оценок") -> 3.5555556 | BS28: =COUNTIF(C28:BQ28,"н/у") -> 2 | BT28: =COUNTIF(C28:BQ28,"н") -> 9
A29: Дата | B29: Тема / ДЗ | BR29: =IFERROR(AVERAGE(BR5:BR28),"") -> 3.2678109 | BS29: =SUM(BS5:BS28) -> 13 | BT29: =SUM(BT5:BT28) -> 142
A30: 05\09 | B30: Матрицы и операции над ними (Л)
A31: 09\09 | B31: Матрицы и операции над ними (дистант)
A32: 09\09 | B32: Определитель матрицы, свойства (дистантт, практическая) (Л) | O32: л | P32: п
A33: 11\09 | B33: Определитель матрицы, минор, алгебраическое дополнение
A34: 17\09 | B34: Обратная матрица
A35: 07\10 | B35: Решение СЛАУ
A36: 09\10 | B36: Матрицы и операции над ними (подготовка)
A37: 14\10 | B37: Матрицы и операции над ними (с/р)
A38: 10\11 | B38: Комплексные числа (Л)
A39: 10\11 | B39: Комплексные числа (ПЗ)
A40: 17\11 | B40: Тригонометрическая форма комплексного числа
A41: 18\11 | B41: Комплексные числа (ПЗ)
A42: 18\11 | B42: Комплексные числа (ПЗ) (домашнее)
A43: 20\11 | B43: Доклады
A44: 04\12 | B44: Решение уравнений с комплексными числами
... A61: 14\02 | B61: Понятие уравнения линии на плоскости. Составление уравнения прямой на плоскости.

Sheet арх.ап.средств
A1: Наименование предмета | C1: Архитектура аппаратных средств
A2: ФИО преподавателя | C2: Клейменов Степан Владимирович
A3: ИСиП 24/2 | B3: Дата | C3: 13.09. | F3: 45920 | G3: 45927 | J3: 45934 | M3: 18.10.25 | P3: 45958 | Q3: 45960 | T3: 45976 | U3: 45983 | W3: 46018 | AP3: 3 сем | AR3: Пропуски
B4: Темы | C4: согл.тем | F4: проц | G4: мат.плата | H4: сис.охлаж | I4: Опер.пам | J4: ssd | K4: ЖД | L4: видео | M4: блок пит | N4: корпус | O4: кулер | P4: монитор | Q4: коллоквиум | T4: сам раб | U4: сам раб | W4: Диф зачет | AP4: ДЗ | AQ4: Средний балл | AR4: Уваж. | AS4: Неуваж.
A5: 1. | B5: Адилбеков Бектур | E5: 5 | M5: н | N5: н | O5: н | Q5: н | R5: н | S5: н | T5: н | U5: н | V5: н | W5: н | X5: н | AQ5: =IFERROR(AVERAGE(C5:AP5),"Нет оценок") -> 5 | AR5: =COUNTIF(C5:AP5,"н/у") -> 0 | AS5: =COUNTIF(C5:AP5,"н") -> 11
A6: 2. | B6: Ахметов Артём Рамилевич | E6: 5 | F6: 5 | G6: 3 | H6: 4 | I6: 5 | J6: 5 | K6: 4 | L6: 3 | M6: 4 | N6: 4 | O6: 5 | P6: 5 | R6: 4 | S6: 4 | X6: 4 | AQ6: =IFERROR(AVERAGE(C6:AP6),"Нет оценок") -> 4.2666667 | AR6: =COUNTIF(C6:AP6,"н/у") -> 0 | AS6: =COUNTIF(C6:AP6,"н") -> 0
A7: 3. | B7: Бараников Владислав Михайлович | E7: 5 | F7: 5 | G7: 5 | H7: 4 | I7: 5 | J7: 5 | K7: 5 | L7: 4 | M7: 4 | N7: 4 | O7: 4 | P7: 5 | R7: 4 | S7: 4 | X7: 4 | AQ7: =IFERROR(AVERAGE(C7:AP7),"Нет оценок") -> 4.4666667 | AR7: =COUNTIF(C7:AP7,"н/у") -> 0 | AS7: =COUNTIF(C7:AP7,"н") -> 0
A8: 4. | B8: Борсук Артём Дмитриевич | E8: 5 | F8: 4 | G8: 4 | H8: 4 | I8: 5 | J8: 4 | K8: 5 | L8: 5 | M8: 5 | N8: 5 | O8: 5 | P8: 5 | R8: 4 | S8: 4 | X8: 5 | AQ8: =IFERROR(AVERAGE(C8:AP8),"Нет оценок") -> 4.6 | AR8: =COUNTIF(C8:AP8,"н/у") -> 0 | AS8: =COUNTIF(C8:AP8,"н") -> 0
A9: 5. | B9: Гильманов Ильназ Максимович | E9: 5 | F9: 3 | G9: 3 | H9: 3 | I9: 3 | J9: 3 | K9: 3 | L9: 3 | M9: 3 | N9: 3 | O9: 3 | P9: 3 | R9: 3 | S9: 3 | X9: 3 | AQ9: =IFERROR(AVERAGE(C9:AP9),"Нет оценок") -> 3.1333333 | AR9: =COUNTIF(C9:AP9,"н/у") -> 0 | AS9: =COUNTIF(C9:AP9,"н") -> 0
A10: 6. | B10: Говтва Илья Денисович | E10: 5 | F10: 5 | G10: 5 | H10: 5 | I10: 5 | J10: 5 | K10: 5 | L10: 5 | M10: 5 | N10: 5 | O10: 5 | P10: 5 | R10: 5 | S10: 5 | X10: 5 | AQ10: =IFERROR(AVERAGE(C10:AP10),"Нет оценок") -> 5 | AR10: =COUNTIF(C10:AP10,"н/у") -> 0 | AS10: =COUNTIF(C10:AP10,"н") -> 0
A11: 7. | B11: Горшков Владислав Васильевич | E11: 5 | F11: 3 | G11: н/у | H11: н/у | I11: н/у | J11: н/у | K11: н/у | L11: н/у | M11: 3 | N11: 3 | O11: 3 | P11: 3 | R11: 3 | S11: 3 | T11: н/у | U11: н/у | V11: н/у | X11: 3 | AQ11: =IFERROR(AVERAGE(C11:AP11),"Нет оценок") -> 3.2222222 | AR11: =COUNTIF(C11:AP11,"н/у") -> 9 | AS11: =COUNTIF(C11:AP11,"н") -> 0
A12: 8. | B12: Гришко Илья Алексеевич | E12: 5 | F12: 5 | G12: 5 | H12: 5 | I12: 5 | J12: 4 | K12: 4 | L12: 5 | M12: 5 | N12: 5 | O12: 5 | P12: 5 | R12: 4 | S12: 4 | X12: 5 | AQ12: =IFERROR(AVERAGE(C12:AP12),"Нет оценок") -> 4.7333333 | AR12: =COUNTIF(C12:AP12,"н/у") -> 0 | AS12: =COUNTIF(C12:AP12,"н") -> 0
A13: 9. | B13: Катков Константин Александрович | E13: 5 | F13: 3 | G13: 3 | H13: 3 | I13: 3 | J13: 3 | K13: 3 | L13: 3 | M13: 3 | N13: 3 | O13: 3 | P13: 3 | R13: 3 | S13: 3 | X13: 3 | AQ13: =IFERROR(AVERAGE(C13:AP13),"Нет оценок") -> 3.1333333 | AR13: =COUNTIF(C13:AP13,"н/у") -> 0 | AS13: =COUNTIF(C13:AP13,"н") -> 0
A14: 10. | B14: Корнеев Андрей Александрович | E14: 5 | F14: 3 | G14: 3 | H14: 3 | I14: 3 | J14: 3 | K14: 3 | L14: 3 | M14: 3 | N14: 3 | O14: 3 | P14: 3 | R14: 3 | S14: 3 | X14: 3 | AQ14: =IFERROR(AVERAGE(C14:AP14),"Нет оценок") -> 3.1333333 | AR14: =COUNTIF(C14:AP14,"н/у") -> 0 | AS14: =COUNTIF(C14:AP14,"н") -> 0
A15: 11. | B15: Макаров Максим Алексеевич | E15: 5 | F15: 4 | G15: 5 | H15: 3 | I15: 4 | J15: 5 | K15: 5 | L15: 5 | M15: 4 | N15: 4 | O15: 4 | P15: 5 | R15: 4 | S15: 4 | X15: 4 | AQ15: =IFERROR(AVERAGE(C15:AP15),"Нет оценок") -> 4.3333333 | AR15: =COUNTIF(C15:AP15,"н/у") -> 0 | AS15: =COUNTIF(C15:AP15,"н") -> 0
A16: 12. | B16: Муллагалиев Вадим Радмилович | E16: 5 | F16: 4 | G16: 4 | H16: 4 | I16: 4 | J16: 4 | K16: 4 | L16: 4 | M16: 4 | N16: 4 | O16: 4 | P16: 4 | R16: 3 | S16: 3 | X16: 4 | AQ16: =IFERROR(AVERAGE(C16:AP16),"Нет оценок") -> 3.9333333 | AR16: =COUNTIF(C16:AP16,"н/у") -> 0 | AS16: =COUNTIF(C16:AP16,"н") -> 0
A17: 13. | B17: Натфуллин Камиль Данисович | E17: 3 | F17: 3 | G17: 3 | H17: 3 | I17: 3 | J17: 3 | K17: 3 | L17: 3 | M17: 3 | N17: 3 | O17: 3 | P17: 3 | R17: 3 | S17: 3 | X17: 3 | AQ17: =IFERROR(AVERAGE(C17:AP17),"Нет оценок") -> 3 | AR17: =COUNTIF(C17:AP17,"н/у") -> 0 | AS17: =COUNTIF(C17:AP17,"н") -> 0
A18: 14. | B18: Носков Ярослав Евгеньевич | E18: 5 | Q18: н | R18: н | S18: н | T18: н/у | W18: н | X18: н | AQ18: =IFERROR(AVERAGE(C18:AP18),"Нет оценок") -> 5 | AR18: =COUNTIF(C18:AP18,"н/у") -> 1 | AS18: =COUNTIF(C18:AP18,"н") -> 5
A19: 15. | B19: Осыка Владислав Сергеевич | E19: 5 | F19: 5 | G19: 5 | H19: 5 | I19: 4 | J19: 4 | K19: 5 | L19: 5 | M19: 4 | N19: 5 | O19: 5 | P19: 5 | R19: 4 | S19: 3 | X19: 4 | AQ19: =IFERROR(AVERAGE(C19:AP19),"Нет оценок") -> 4.5333333 | AR19: =COUNTIF(C19:AP19,"н/у") -> 0 | AS19: =COUNTIF(C19:AP19,"н") -> 0
A20: 16. | B20: Романов Михаил Васильевич | E20: 5 | F20: 3 | G20: 3 | H20: 3 | I20: 3 | J20: 3 | K20: 3 | L20: 3 | M20: 3 | N20: 3 | O20: 3 | P20: 3 | R20: 3 | S20: 3 | X20: 3 | AQ20: =IFERROR(AVERAGE(C20:AP20),"Нет оценок") -> 3.1333333 | AR20: =COUNTIF(C20:AP20,"н/у") -> 0 | AS20: =COUNTIF(C20:AP20,"н") -> 0
A21: 18. | B21: Руфуллаев Ибрагим Фуадович | E21: 5 | F21: 5 | G21: 5 | H21: 4 | I21: 4 | J21: 5 | K21: 5 | L21: 5 | M21: 5 | N21: 4 | O21: 4 | P21: 5 | R21: 5 | S21: 5 | X21: 5 | AQ21: =IFERROR(AVERAGE(U21:AP21),"Нет оценок") -> 5 | AR21: =COUNTIF(U21:AP21,"н/у") -> 0 | AS21: =COUNTIF(U21:AP21,"н") -> 0
A22: 19. | B22: Сурков Кирилл Александрович | E22: 5 | F22: 4 | G22: 5 | H22: 4 | I22: 5 | J22: 5 | K22: 4 | L22: 3 | M22: 5 | N22: 4 | O22: 4 | P22: 5 | R22: 3 | S22: 4 | X22: 4 | AQ22: =IFERROR(AVERAGE(C22:AP22),"Нет оценок") -> 4.2666667 | AR22: =COUNTIF(C22:AP22,"н/у") -> 0 | AS22: =COUNTIF(C22:AP22,"н") -> 0
A23: 20. | B23: Усатов Тимофей Анатольевич | E23: 5 | F23: 5 | G23: 5 | H23: 5 | I23: 5 | J23: 5 | K23: 4 | L23: 4 | M23: 5 | N23: 5 | O23: 5 | P23: 5 | R23: 4 | S23: 4 | X23: 5 | AQ23: =IFERROR(AVERAGE(C23:AP23),"Нет оценок") -> 4.7333333 | AR23: =COUNTIF(C23:AP23,"н/у") -> 0 | AS23: =COUNTIF(C23:AP23,"н") -> 0
A24: 21. | B24: Халитов Кирилл Родионович | E24: 5 | F24: 5 | G24: 4 | H24: 5 | I24: 5 | J24: 4 | K24: 5 | L24: 5 | M24: 5 | N24: 5 | O24: 5 | P24: 5 | R24: 5 | S24: 5 | X24: 5 | AQ24: =IFERROR(AVERAGE(C24:AP24),"Нет оценок") -> 4.8666667 | AR24: =COUNTIF(C24:AP24,"н/у") -> 0 | AS24: =COUNTIF(C24:AP24,"н") -> 0
A25: 22. | B25: Хорошилов Игорь Александрович | AQ25: =IFERROR(AVERAGE(C25:AP25),"Нет оценок") -> Нет оценок | AR25: =COUNTIF(C25:AP25,"н/у") -> 0 | AS25: =COUNTIF(C25:AP25,"н") -> 0
A26: 23. | B26: Хрычев Мирон Евгеньевич | E26: 5 | F26: 3 | G26: 3 | H26: 3 | I26: 3 | J26: 3 | K26: 3 | L26: 3 | M26: 3 | N26: 3 | O26: 3 | P26: 3 | Q26: н/у | R26: 3 | S26: 3 | X26: 3 | AQ26: =IFERROR(AVERAGE(C26:AP26),"Нет оценок") -> 3.1333333 | AR26: =COUNTIF(C26:AP26,"н/у") -> 1 | AS26: =COUNTIF(C26:AP26,"н") -> 0
A27: 24. | B27: Цапов Илья Валерьевич | E27: 5 | F27: 4 | G27: 4 | H27: 4 | I27: 4 | J27: 4 | K27: 4 | L27: 4 | M27: 4 | N27: 4 | O27: 4 | P27: 4 | R27: 4 | S27: 4 | X27: 4 | AQ27: =IFERROR(AVERAGE(C27:AP27),"Нет оценок") -> 4.0666667 | AR27: =COUNTIF(C27:AP27,"н/у") -> 0 | AS27: =COUNTIF(C27:AP27,"н") -> 0
AQ28: =IFERROR(AVERAGE(AQ5:AQ27),"") -> 4.1222222 | AR28: =SUM(AR5:AR27) -> 11 | AS28: =SUM(AS5:AS27) -> 16
A29: Дата | B29: Тема / ДЗ

Sheet Опер.систем-среды
A1: Наименование предмета | C1: Операционные системы и среды
A2: ФИО преподавателя | C2: Штанов Юрий Николаевич
A3: ИСиП 24/2 | B3: Месяц | C3: 9 | D3: 9 | E3: 9 | F3: 10 | G3: 10 | H3: 10 | I3: 11 | J3: 11 | K3: 11 | L3: 11 | M3: 11 | N3: 12 | O3: 12 | P3: 12 | Q3: 12 | R3: 12 | S3: 12 | T3: 12 | U3: 2 | V3: 2 | W3: 3 | X3: 3 | AV3: 4 сем | AX3: Пропуски
B4: Число | C4: 11 | D4: 24 | E4: 24 | F4: 22 | G4: 25 | H4: 31 | I4: 22 | J4: 22 | K4: 25 | L4: 26 | M4: 26 | N4: 1 | O4: 6 | P4: 6 | Q4: 13 | R4: 15 | S4: 15 | T4: 20 | U4: 13 | V4: 27 | W4: 14 | X4: 14 | AV4: Экз | AW4: Средний балл | AX4: Уваж. | AY4: Неуваж.
A5: 1. | B5: Адилбеков Бектур | F5: + | H5: н | I5: н | J5: н | K5: н | N5: н | O5: н | P5: н | R5: н | S5: 2 | T5: н | W5: н | X5: н | AW5: =IFERROR(AVERAGE(C5:AV5),"Нет оценок") -> 2 | AX5: =COUNTIF(C5:AU5,"н/у") -> 0 | AY5: =COUNTIF(C5:AV5,"н") -> 11
A6: 2. | B6: Ахметов Артём Рамилевич | F6: н/у | I6: н | J6: н | K6: 3 | L6: н | M6: н | R6: л | S6: 4 | T6: + | U6: н | V6: л | W6: н | X6: н | AW6: =IFERROR(AVERAGE(C6:AV6),"Нет оценок") -> 3.5 | AX6: =COUNTIF(C6:AU6,"н/у") -> 1 | AY6: =COUNTIF(C6:AV6,"н") -> 7
A7: 3. | B7: Бараников Владислав Михайлович | F7: + | K7: 3 | S7: 2 | T7: + | V7: л | AW7: =IFERROR(AVERAGE(C7:AV7),"Нет оценок") -> 2.5 | AX7: =COUNTIF(C7:AU7,"н/у") -> 0 | AY7: =COUNTIF(C7:AV7,"н") -> 0
A8: 4. | B8: Борсук Артём Дмитриевич | F8: н | G8: н | I8: н | J8: н | K8: 2 | L8: н | M8: н | N8: н | R8: л | S8: 3 | T8: н | U8: н | AW8: =IFERROR(AVERAGE(C8:AV8),"Нет оценок") -> 2.5 | AX8: =COUNTIF(C8:AU8,"н/у") -> 0 | AY8: =COUNTIF(C8:AV8,"н") -> 9
A9: 5. | B9: Гильманов Ильназ Максимович | F9: н | I9: н/у | J9: н | K9: 5 | R9: л | S9: 3 | T9: н | AW9: =IFERROR(AVERAGE(C9:AV9),"Нет оценок") -> 4 | AX9: =COUNTIF(C9:AU9,"н/у") -> 1 | AY9: =COUNTIF(C9:AV9,"н") -> 3
A10: 6. | B10: Говтва Илья Денисович | F10: + | H10: н | K10: 5 | S10: 5 | T10: + | AW10: =IFERROR(AVERAGE(C10:AV10),"Нет оценок") -> 5 | AX10: =COUNTIF(C10:AU10,"н/у") -> 0 | AY10: =COUNTIF(C10:AV10,"н") -> 1
A11: 7. | B11: Горшков Владислав Васильевич | C11: н | F11: + | G11: н | I11: н | J11: н | K11: 2 | M11: н | S11: 4 | T11: + | AW11: =IFERROR(AVERAGE(C11:AV11),"Нет оценок") -> 3 | AX11: =COUNTIF(C11:AU11,"н/у") -> 0 | AY11: =COUNTIF(C11:AV11,"н") -> 5
A12: 8. | B12: Гришко Илья Алексеевич | C12: н | F12: + | K12: 2 | S12: 5 | T12: + | W12: н | X12: н | AW12: =IFERROR(AVERAGE(C12:AV12),"Нет оценок") -> 3.5 | AX12: =COUNTIF(C12:AU12,"н/у") -> 0 | AY12: =COUNTIF(C12:AV12,"н") -> 3
A13: 9. | B13: Катков Константин Александрович | D13: л | E13: н | F13: н | G13: н | H13: н | I13: н | J13: н | K13: 2 | M13: н | Q13: н | R13: л | S13: 2 | T13: н | U13: н | V13: л | W13: л | AW13: =IFERROR(AVERAGE(C13:AV13),"Нет оценок") -> 2 | AX13: =COUNTIF(C13:AU13,"н/у") -> 0 | AY13: =COUNTIF(C13:AV13,"н") -> 10
A14: 10. | B14: Корнеев Андрей Александрович | F14: н | G14: н | H14: н | K14: 2 | S14: 2 | T14: н | AW14: =IFERROR(AVERAGE(C14:AV14),"Нет оценок") -> 2 | AX14: =COUNTIF(C14:AU14,"н/у") -> 0 | AY14: =COUNTIF(C14:AV14,"н") -> 4
A15: 11. | B15: Макаров Максим Алексеевич | E15: н/у | F15: + | H15: н | K15: 4 | S15: 5 | T15: + | AW15: =IFERROR(AVERAGE(C15:AV15),"Нет оценок") -> 4.5 | AX15: =COUNTIF(C15:AU15,"н/у") -> 1 | AY15: =COUNTIF(C15:AV15,"н") -> 1
A16: 13. | B16: Муллагалиев Вадим Радмилович | F16: + | H16: н | I16: н/у | J16: н/у | K16: 4 | L16: н/у | M16: н/у | N16: н | S16: 4 | T16: + | AW16: =IFERROR(AVERAGE(C16:AV16),"Нет оценок") -> 4 | AX16: =COUNTIF(C16:AU16,"н/у") -> 4 | AY16: =COUNTIF(C16:AV16,"н") -> 2
A17: 12. | B17: Натфуллин Камиль Данисович | C17: н | F17: н | G17: н | H17: н | I17: н | J17: н | K17: 2 | M17: н | N17: н | Q17: н | R17: л | S17: 5 | T17: н | W17: н | X17: н | AW17: =IFERROR(AVERAGE(C17:AV17),"Нет оценок") -> 3.5 | AX17: =COUNTIF(C17:AU17,"н/у") -> 0 | AY17: =COUNTIF(C17:AV17,"н") -> 12
A18: 14. | B18: Носков Ярослав Евгеньевич | F18: н | K18: 5 | S18: 5 | T18: н | AW18: =IFERROR(AVERAGE(C18:AV18),"Нет оценок") -> 5 | AX18: =COUNTIF(C18:AU18,"н/у") -> 0 | AY18: =COUNTIF(C18:AV18,"н") -> 2
A19: 15. | B19: Осыка Владислав Сергеевич | F19: н/у | K19: 5 | S19: 3 | T19: + | AW19: =IFERROR(AVERAGE(C19:AV19),"Нет оценок") -> 4 | AX19: =COUNTIF(C19:AU19,"н/у") -> 1 | AY19: =COUNTIF(C19:AV19,"н") -> 0
A20: 16. | B20: Романов Михаил Васильевич | F20: + | K20: 4 | L20: н | M20: н | Q20: н | S20: 3 | T20: + | AW20: =IFERROR(AVERAGE(C20:AV20),"Нет оценок") -> 3.5 | AX20: =COUNTIF(C20:AU20,"н/у") -> 0 | AY20: =COUNTIF(C20:AV20,"н") -> 3
A21: 17. | B21: Руфуллаев Ибрагим Фуадович | F21: + | K21: 5 | R21: л | S21: 3 | T21: + | W21: н | X21: н | AW21: =IFERROR(AVERAGE(C21:AV21),"Нет оценок") -> 4 | AX21: =COUNTIF(C21:AU21,"н/у") -> 0 | AY21: =COUNTIF(C21:AV21,"н") -> 2
A22: 18. | B22: Сарычев Данила Андреевич | F22: + | K22: 5 | O22: н | P22: н | S22: 5 | T22: + | U22: н | W22: н | X22: н | AW22: =IFERROR(AVERAGE(C22:AV22),"Нет оценок") -> 5 | AX22: =COUNTIF(C22:AU22,"н/у") -> 0 | AY22: =COUNTIF(C22:AV22,"н") -> 5
A23: 19. | B23: Сурков Кирилл Александрович | C23: н | E23: н/у | F23: + | G23: н | H23: н | I23: н | J23: н | K23: 3 | L23: н | M23: н | N23: н | Q23: н | S23: 5 | T23: н | W23: н | X23: н | AW23: =IFERROR(AVERAGE(C23:AV23),"Нет оценок") -> 4 | AX23: =COUNTIF(C23:AU23,"н/у") -> 1 | AY23: =COUNTIF(C23:AV23,"н") -> 12
A24: 20. | B24: Усатов Тимофей Анатольевич | F24: + | K24: 5 | S24: 5 | T24: + | AW24: =IFERROR(AVERAGE(C24:AV24),"Нет оценок") -> 5 | AX24: =COUNTIF(C24:AU24,"н/у") -> 0 | AY24: =COUNTIF(C24:AV24,"н") -> 0
A25: 21. | B25: Халитов Кирилл Родионович | E25: н | F25: н | G25: н | H25: н | I25: н | J25: н | K25: н | L25: н | M25: н | N25: н/у | O25: н/у | P25: н/у | Q25: н | R25: л | S25: 2 | T25: н | U25: н | V25: л | W25: н | X25: н | AW25: =IFERROR(AVERAGE(C25:AV25),"Нет оценок") -> 2 | AX25: =COUNTIF(C25:AU25,"н/у") -> 3 | AY25: =COUNTIF(C25:AV25,"н") -> 14
A26: 21. | B26: Хорошилов Игорь Александрович | AW26: =IFERROR(AVERAGE(C26:AV26),"Нет оценок") -> Нет оценок | AX26: =COUNTIF(C26:AU26,"н/у") -> 0 | AY26: =COUNTIF(C26:AV26,"н") -> 0
A27: 22. | B27: Хрычев Мирон Евгеньевич | F27: + | G27: н/у | H27: н/у | K27: 4 | N27: н | S27: 2 | T27: + | W27: н | X27: н | AW27: =IFERROR(AVERAGE(C27:AV27),"Нет оценок") -> 3 | AX27: =COUNTIF(C27:AU27,"н/у") -> 2 | AY27: =COUNTIF(C27:AV27,"н") -> 3
A28: 23. | B28: Цапов Илья Валерьевич | E28: н | F28: н/у | H28: н | L28: н | M28: н | N28: с | R28: л | S28: 5 | T28: н | W28: л | AW28: =IFERROR(AVERAGE(C28:AV28),"Нет оценок") -> 5 | AX28: =COUNTIF(C28:AU28,"н/у") -> 1 | AY28: =COUNTIF(C28:AV28,"н") -> 5
A29: Дата | B29: Тема / ДЗ | AW29: =IFERROR(AVERAGE(AW5:AW28),"") -> 3.5869565 | AX29: =SUM(AX5:AX28) -> 15 | AY29: =SUM(AY5:AY28) -> 114
A30: 45911 | B30: Введение
A31: 45924 | B31: Введение: Виртуализация
A32: 45924 | B32: Операционная система Windows. История
A33: 45952 | B33: Операционная система Windows и Linux
A34: 45955 | B34: Практическая работа 1
A35: 45961 | B35: Программа VirtualBox
A36: 45983 | B36: Отказоустойчивость дисковых систем и восстанавливаемость_x000B_файловых систем
A37: 45983 | B37: Лицензии на программное обеспечение и документацию
A38: 45986 | B38: Практическая работа 1
A39: 45987 | B39: Практическая работа 2
A40: 45987 | B40: Практическая работа 2
A41: 45992 | B41: Практическая работа 2
... A51: 46095 | B51: Практическая работа 3: Организация удалённого доступа в OC Linux

Sheet Основы алгоритмизации
A1: Наименование предмета | C1: Основы алгоритмизации и программирования
A2: ФИО преподавателя | C2: Кузнецов Алексей Николаевич
A3: ИСиП 24/2 | B3: Месяц | C3: 9 | D3: 9 | E3: 9 | F3: 9 | G3: 9 | H3: 9 | I3: 9 | J3: 9 | K3: 9 | L3: 10 | M3: 10 | N3: 10 | O3: 10 | P3: 10 | Q3: 11 | R3: 11 | S3: 11 | T3: 11 | U3: 12 | V3: 1 | W3: 1 | X3: 2 | Y3: 2 | Z3: 3 | AA3: 3 | CC3: 4 сем | CE3: Пропуски
B4: Число | C4: 8 | D4: 11 | E4: 12 | F4: 16 | G4: 19 | H4: 22 | I4: 24 | J4: 25 | K4: 25 | L4: 8 | M4: 21 | N4: 22 | O4: 22 | P4: 31 | Q4: 14 | R4: 14 | S4: 23 | T4: 27 | U4: 9 | V4: 19 | W4: 24 | X4: 19 | Y4: 25 | Z4: 3 | AA4: 6 | CC4: Экз | CD4: Средний балл | CE4: Уваж. | CF4: Неуваж.
A5: 1. | B5: Адилбеков Бектур | C5: 2 | D5: 2 | E5: н | F5: 2 | G5: 3 | H5: 3 | I5: 3 | J5: 3 | K5: о | L5: н | M5: н | P5: н | Q5: н | R5: н | S5: 2 | T5: н | U5: н | V5: н | W5: н | Y5: н | CD5: =IFERROR(AVERAGE(C5:CC5),"Нет оценок") -> 2.5 | CE5: =COUNTIF(C5:CC5,"н/у") -> 0 | CF5: =COUNTIF(C5:CC5,"н") -> 11
A6: 2. | B6: Ахметов Артём Рамилевич | C6: н | D6: 3 | E6: 2 | F6: 2 | G6: 3 | H6: о | I6: 3 | J6: 3 | K6: 2 | M6: н/у | N6: н/у | O6: н/у | P6: н | S6: 3 | U6: 3 | W6: н | X6: н | CD6: =IFERROR(AVERAGE(C6:CC6),"Нет оценок") -> 2.6666667 | CE6: =COUNTIF(C6:CC6,"н/у") -> 3 | CF6: =COUNTIF(C6:CC6,"н") -> 4
A7: 3. | B7: Бараников Владислав Михайлович | C7: 3 | D7: 2 | E7: 2 | F7: 2 | G7: 3 | H7: 3 | I7: 3 | J7: н | K7: н | M7: н | S7: 3 | U7: 3 | W7: + | CD7: =IFERROR(AVERAGE(C7:CC7),"Нет оценок") -> 2.6666667 | CE7: =COUNTIF(C7:CC7,"н/у") -> 0 | CF7: =COUNTIF(C7:CC7,"н") -> 3
A8: 4. | B8: Борсук Артём Дмитриевич | C8: н | D8: 2 | E8: 2 | F8: н | G8: н | H8: н | I8: 3 | J8: 3 | K8: 2 | M8: н | N8: н | O8: н | S8: 3 | U8: 3 | W8: + | CD8: =IFERROR(AVERAGE(C8:CC8),"Нет оценок") -> 2.5714286 | CE8: =COUNTIF(C8:CC8,"н/у") -> 0 | CF8: =COUNTIF(C8:CC8,"н") -> 7
A9: 5. | B9: Гильманов Ильназ Максимович | C9: 2 | D9: 2 | E9: 2 | F9: 2 | G9: 3 | H9: 2 | I9: 3 | J9: 3 | K9: 3 | L9: 2 | S9: 3 | U9: 4 | W9: н | Y9: н | CD9: =IFERROR(AVERAGE(C9:CC9),"Нет оценок") -> 2.5833333 | CE9: =COUNTIF(C9:CC9,"н/у") -> 0 | CF9: =COUNTIF(C9:CC9,"н") -> 2
A10: 6. | B10: Говтва Илья Денисович | C10: 4 | D10: 3 | E10: 4 | F10: 5 | G10: 3 | H10: 3 | I10: 3 | J10: 3 | K10: 2 | P10: 5 | S10: 3 | U10: 4 | W10: + | CD10: =IFERROR(AVERAGE(C10:CC10),"Нет оценок") -> 3.5 | CE10: =COUNTIF(C10:CC10,"н/у") -> 0 | CF10: =COUNTIF(C10:CC10,"н") -> 0
A11: 7. | B11: Горшков Владислав Васильевич | C11: 2 | D11: 4 | E11: 3 | F11: 2 | G11: 3 | H11: 3 | I11: 3 | J11: 3 | Q11: н/у | R11: н/у | S11: 3 | U11: 3 | V11: н | W11: н | CD11: =IFERROR(AVERAGE(C11:CC11),"Нет оценок") -> 2.9 | CE11: =COUNTIF(C11:CC11,"н/у") -> 2 | CF11: =COUNTIF(C11:CC11,"н") -> 2
A12: 8. | B12: Гришко Илья Алексеевич | C12: н | D12: н | E12: 3 | F12: н | G12: 2 | H12: 2 | I12: 3 | J12: 3 | K12: 2 | S12: 3 | U12: 3 | W12: + | X12: н | CD12: =IFERROR(AVERAGE(C12:CC12),"Нет оценок") -> 2.625 | CE12: =COUNTIF(C12:CC12,"н/у") -> 0 | CF12: =COUNTIF(C12:CC12,"н") -> 4
A13: 9. | B13: Катков Константин Александрович | C13: 2 | D13: 2 | E13: 2 | F13: 2 | G13: 3 | H13: н | I13: 3 | J13: 2 | K13: 2 | L13: н | M13: н | P13: н | S13: 2 | U13: 2 | W13: н | Y13: н | CD13: =IFERROR(AVERAGE(C13:CC13),"Нет оценок") -> 2.2 | CE13: =COUNTIF(C13:CC13,"н/у") -> 0 | CF13: =COUNTIF(C13:CC13,"н") -> 6
A14: 10. | B14: Корнеев Андрей Александрович | C14: 2 | D14: 2 | E14: 2 | F14: 2 | G14: 3 | H14: 3 | I14: 3 | J14: 3 | K14: 2 | M14: 2 | N14: 2 | O14: 3 | P14: 3 | S14: 2 | U14: 3 | W14: + | Y14: н | CD14: =IFERROR(AVERAGE(C14:CC14),"Нет оценок") -> 2.4666667 | CE14: =COUNTIF(C14:CC14,"н/у") -> 0 | CF14: =COUNTIF(C14:CC14,"н") -> 1
A15: 11. | B15: Макаров Максим Алексеевич | C15: 2 | D15: 2 | E15: 2 | F15: 2 | G15: 3 | H15: 3 | I15: 3 | J15: 3 | K15: 3 | P15: н | Q15: 3 | S15: 3 | U15: 2 | W15: н | CD15: =IFERROR(AVERAGE(C15:CC15),"Нет оценок") -> 2.5833333 | CE15: =COUNTIF(C15:CC15,"н/у") -> 0 | CF15: =COUNTIF(C15:CC15,"н") -> 2
A16: 13. | B16: Муллагалиев Вадим Радмилович | C16: 3 | D16: 2 | E16: 2 | F16: 2 | G16: 3 | H16: 2 | I16: 3 | J16: 3 | K16: 2 | M16: 2 | P16: 3 | S16: 3 | U16: 3 | W16: н | CD16: =IFERROR(AVERAGE(C16:CC16),"Нет оценок") -> 2.5384615 | CE16: =COUNTIF(C16:CC16,"н/у") -> 0 | CF16: =COUNTIF(C16:CC16,"н") -> 1
A17: 12. | B17: Натфуллин Камиль Данисович | C17: 2 | D17: 3 | E17: 3 | F17: 2 | G17: н | H17: н | I17: 3 | J17: 3 | K17: н | L17: н | M17: н | P17: н | Q17: н/у | R17: н/у | S17: 3 | U17: 3 | W17: н | Y17: н | CD17: =IFERROR(AVERAGE(C17:CC17),"Нет оценок") -> 2.75 | CE17: =COUNTIF(C17:CC17,"н/у") -> 2 | CF17: =COUNTIF(C17:CC17,"н") -> 8
A18: 14. | B18: Носков Ярослав Евгеньевич | C18: 2 | D18: 2 | E18: 2 | F18: 2 | G18: 3 | H18: 3 | I18: 3 | J18: 3 | K18: 2 | M18: н | P18: н | S18: 2 | U18: 2 | W18: н | X18: н | Y18: н | CD18: =IFERROR(AVERAGE(C18:CC18),"Нет оценок") -> 2.3636364 | CE18: =COUNTIF(C18:CC18,"н/у") -> 0 | CF18: =COUNTIF(C18:CC18,"н") -> 5
A19: 15. | B19: Осыка Владислав Сергеевич | C19: 2 | D19: 2 | E19: 2 | F19: 2 | G19: 3 | H19: 3 | I19: 3 | J19: 2 | K19: 3 | M19: 2 | N19: 2 | O19: 4 | P19: 3 | Q19: 3 | S19: 3 | U19: 3 | W19: н | Y19: 3 | CD19: =IFERROR(AVERAGE(C19:CC19),"Нет оценок") -> 2.6470588 | CE19: =COUNTIF(C19:CC19,"н/у") -> 0 | CF19: =COUNTIF(C19:CC19,"н") -> 1
A20: 16. | B20: Романов Михаил Васильевич | C20: 3 | D20: 4 | E20: 4 | F20: 5 | G20: 3 | H20: 3 | I20: 3 | J20: 3 | Q20: н | R20: н | S20: 2 | U20: 3 | W20: н | CD20: =IFERROR(AVERAGE(C20:CC20),"Нет оценок") -> 3.3 | CE20: =COUNTIF(C20:CC20,"н/у") -> 0 | CF20: =COUNTIF(C20:CC20,"н") -> 3
A21: 17. | B21: Руфуллаев Ибрагим Фуадович | C21: 2 | D21: 3 | E21: 2 | F21: 2 | G21: 3 | H21: 3 | I21: 3 | J21: 3 | K21: 2 | Q21: 3 | R21: 3 | S21: 3 | U21: 3 | W21: н | Y21: н | CD21: =IFERROR(AVERAGE(C21:CC21),"Нет оценок") -> 2.6923077 | CE21: =COUNTIF(C21:CC21,"н/у") -> 0 | CF21: =COUNTIF(C21:CC21,"н") -> 2
A22: 18. | B22: Сарычев Данила Андреевич | C22: 2 | D22: 3 | E22: 2 | F22: 2 | G22: 3 | H22: 2 | I22: 3 | J22: 3 | K22: 2 | S22: 3 | U22: 3 | W22: + | CD22: =IFERROR(AVERAGE(C22:CC22),"Нет оценок") -> 2.5454545 | CE22: =COUNTIF(C22:CC22,"н/у") -> 0 | CF22: =COUNTIF(C22:CC22,"н") -> 0
A23: 19. | B23: Сурков Кирилл Александрович | D23: н | E23: 3 | F23: 2 | G23: н | H23: н/у | I23: н/у | J23: н/у | K23: н/у | N23: н | O23: н | P23: н | S23: 2 | T23: н | U23: 2 | W23: н | X23: н | Y23: н | CD23: =IFERROR(AVERAGE(C23:CC23),"Нет оценок") -> 2.25 | CE23: =COUNTIF(C23:CC23,"н/у") -> 4 | CF23: =COUNTIF(C23:CC23,"н") -> 9
A24: 20. | B24: Усатов Тимофей Анатольевич | C24: 4 | D24: 4 | E24: 4 | F24: 4 | G24: 3 | H24: 3 | I24: 3 | J24: 3 | K24: 2 | S24: 3 | U24: 4 | V24: 3 | W24: + | CD24: =IFERROR(AVERAGE(C24:CC24),"Нет оценок") -> 3.3333333 | CE24: =COUNTIF(C24:CC24,"н/у") -> 0 | CF24: =COUNTIF(C24:CC24,"н") -> 0
A25: 21. | B25: Халитов Кирилл Родионович | C25: 2 | D25: 2 | E25: 3 | F25: н | G25: 3 | H25: н | I25: н | J25: н/у | K25: н/у | L25: н | M25: н | O25: н | P25: н | S25: 2 | T25: н | U25: 2 | V25: н | W25: н | X25: н | Y25: н | CD25: =IFERROR(AVERAGE(C25:CC25),"Нет оценок") -> 2.3333333 | CE25: =COUNTIF(C25:CC25,"н/у") -> 2 | CF25: =COUNTIF(C25:CC25,"н") -> 12
A26: 21. | B26: Хорошилов Игорь Александрович | CD26: =IFERROR(AVERAGE(C26:CC26),"Нет оценок") -> Нет оценок | CE26: =COUNTIF(C26:CC26,"н/у") -> 0 | CF26: =COUNTIF(C26:CC26,"н") -> 0
A27: 22. | B27: Хрычев Мирон Евгеньевич | C27: 2 | D27: 3 | E27: 2 | F27: 2 | G27: 3 | H27: 3 | I27: 3 | J27: 3 | K27: 2 | P27: н/у | S27: 3 | U27: 2 | W27: н | CD27: =IFERROR(AVERAGE(C27:CC27),"Нет оценок") -> 2.5454545 | CE27: =COUNTIF(C27:CC27,"н/у") -> 1 | CF27: =COUNTIF(C27:CC27,"н") -> 1
A28: 23. | B28: Цапов Илья Валерьевич | C28: 3 | D28: 2 | E28: 2 | F28: 2 | G28: 3 | H28: 3 | I28: 3 | J28: 3 | K28: 2 | L28: н | N28: н/у | O28: н/у | P28: н | S28: 3 | U28: 2 | V28: н | W28: н | Y28: н | CD28: =IFERROR(AVERAGE(C28:CC28),"Нет оценок") -> 2.5454545 | CE28: =COUNTIF(C28:CC28,"н/у") -> 2 | CF28: =COUNTIF(C28:CC28,"н") -> 5
A29: Дата | B29: Тема / ДЗ | CD29: =IFERROR(AVERAGE(CD5:CD28),"") -> 2.6568517 | CE29: =SUM(CE5:CE28) -> 16 | CF29: =SUM(CF5:CF28) -> 89
A30: 45908 | B30: Введение в программирование на C++ https://onlinetestpad.com/h3s7xobt5oojs | C30: л
A31: 45911 | B31: Простые типы данных https://onlinetestpad.com/3kyb2wkijubpk | C31: л | P31: Л | Q31: П
A32: 45912 | B32: Производные типы данных https://onlinetestpad.com/e2t5svzlfiotc | C32: л | O32: План | P32: 32 | Q32: 30
A33: 45916 | B33: Поразрядные операции и маски; практические кейсы в С++ https://onlinetestpad.com/bgtbal7aia46i | C33: л | G33: =COUNTIF(C30:C80,"Л") -> 12 | O33: Факт | P33: =G33*2 -> 24 | Q33: =G34*2 -> 26
A34: 45919 | B34: Практическая работа 1 | C34: п | G34: =COUNTIF(C30:C80,"П") -> 13
A35: 45922 | B35: Практическая работа 2 | C35: п
A36: 45924 | B36: Практическая работа 3 | C36: п
A37: 45925 | B37: Практическая работа 4 | C37: п
A38: 45925 | B38: Ветвления: if/else; switch; антипаттерны и best practices. https://onlinetestpad.com/atfsn5gwsusp4 | C38: л
A39: 45938 | B39: Практическая работа 5 | C39: п
A40: 45940 | B40: Циклы: while/for/do‑while;вложенность; контроль условий. | C40: л
A41: 45951 | B41: Практическая работа 6 | C41: п
A42: 45952 | B42: Ввод/вывод подробно:форматирование, std::getline, парсинг. | C42: л
A43: 45952 | B43: Практическая работа 7 | C43: п
A44: 45961 | B44: Функции:объявление/определение, область видимости, прототипы. | C44: л
A45: 45975 | B45: Параметры: по значению, поссылке, const&; возврат значения. | C45: л
A46: 45975 | B46: Рекурсия: идеи, стек; задачи vs итерация; хвостовая рекурсия | C46: л
... A48: 45988 | B48: Практическая работа 8 | C48: п
A49: 46000 | B49: Контрольная работа
A50: 46041 | B50: Практическая работа 9 | C50: п
A51: 46046 | B51: Массивы C‑стиля и строки; работа с буферами; безопасность. | C51: л
A52: 46072 | B52: string: операции, поиск/замена; конвертации. | C52: л
A53: 46078 | B53: Практическая работа 10 | C53: п
A54: 46084 | B54: Практическая работа 11 | C54: п
A55: 6.3 | B55: Практическая работа 12 | C55: п

Sheet Осн.пр.Базы данных
A1: Наименование предмета | C1: Основы проектирования баз данных
A2: ФИО преподавателя | C2: Гирявый Владимир Владимирович
A3: ИСиП 24/2 | B3: Месяц | C3: 9 | D3: 9 | E3: 10 | F3: 10 | G3: 10 | H3: 10 | I3: 11 | J3: 11 | K3: 11 | L3: 11 | M3: 11 | N3: 12 | O3: 12 | Q3: 2 | R3: 3 | S3: 3 | T3: 3 | U3: 3 | V3: 3 | W3: 3 | X3: 4 | Y3: 4 | Z3: 4 | BB3: 4 сем | BD3: Пропуски
B4: Число | C4: 17 | D4: 17 | E4: 7 | F4: 20 | G4: 27 | H4: 30 | I4: 21 | J4: 21 | K4: 27 | L4: 28 | M4: 28 | N4: 3 | O4: 9 | Q4: 6 | R4: 2 | S4: 4 | T4: 5 | U4: 6 | V4: 12 | W4: 12 | X4: 6 | BB4: ДЗ | BC4: Средний балл | BD4: Уваж. | BE4: Неуваж.
A5: 1. | B5: Адилбеков Бектур | F5: н | G5: н | H5: 2 | I5: н | J5: н | K5: н | L5: н | M5: н | N5: н | O5: 3 | Q5: н | R5: н | S5: 2 | T5: н | U5: н | V5: н | X5: н | BC5: =IFERROR(AVERAGE(C5:BB5),"Нет оценок") -> 2.3333333 | BD5: =COUNTIF(C5:BA5,"н/у") -> 0 | BE5: =COUNTIF(C5:BB5,"н") -> 14
A6: 2. | B6: Ахметов Артём Рамилевич | H6: 3 | L6: оп | M6: 4 | O6: 3 | Q6: н | R6: оп | S6: н | T6: но | BC6: =IFERROR(AVERAGE(C6:BB6),"Нет оценок") -> 3.3333333 | BD6: =COUNTIF(C6:BA6,"н/у") -> 0 | BE6: =COUNTIF(C6:BB6,"н") -> 2
A7: 3. | B7: Бараников Владислав Михайлович | G7: оп | H7: 3 | I7: оп | L7: оп | M7: - | O7: 3 | R7: 3 | S7: 3 | X7: н | BC7: =IFERROR(AVERAGE(C7:BB7),"Нет оценок") -> 3 | BD7: =COUNTIF(C7:BA7,"н/у") -> 0 | BE7: =COUNTIF(C7:BB7,"н") -> 1
A8: 4. | B8: Борсук Артём Дмитриевич | C8: н | D8: н | F8: оп | G8: оп | H8: 2 | L8: н | M8: н | N8: н | O8: 4 | Q8: оп | R8: 3 | S8: 3 | U8: н | BC8: =IFERROR(AVERAGE(C8:BB8),"Нет оценок") -> 3 | BD8: =COUNTIF(C8:BA8,"н/у") -> 0 | BE8: =COUNTIF(C8:BB8,"н") -> 6
A9: 5. | B9: Гильманов Ильназ Максимович | G9: оп | H9: 3 | M9: - | O9: 4 | R9: 2 | S9: 2 | T9: н | BC9: =IFERROR(AVERAGE(C9:BB9),"Нет оценок") -> 2.75 | BD9: =COUNTIF(C9:BA9,"н/у") -> 0 | BE9: =COUNTIF(C9:BB9,"н") -> 1
A10: 6. | B10: Говтва Илья Денисович | G10: оп | H10: 3 | M10: - | O10: 3 | R10: 3 | S10: 3 | X10: . | BC10: =IFERROR(AVERAGE(C10:BB10),"Нет оценок") -> 3 | BD10: =COUNTIF(C10:BA10,"н/у") -> 0 | BE10: =COUNTIF(C10:BB10,"н") -> 0
A11: 7. | B11: Горшков Владислав Васильевич | F11: оп | H11: 3 | L11: оп | M11: - | O11: 2 | R11: 3 | S11: 3 | T11: но | W11: 3 | BC11: =IFERROR(AVERAGE(C11:BB11),"Нет оценок") -> 2.8 | BD11: =COUNTIF(C11:BA11,"н/у") -> 0 | BE11: =COUNTIF(C11:BB11,"н") -> 0
A12: 8. | B12: Гришко Илья Алексеевич | C12: н | D12: н | G12: оп | H12: 3 | M12: - | O12: 3 | R12: 3 | S12: - | BC12: =IFERROR(AVERAGE(C12:BB12),"Нет оценок") -> 3 | BD12: =COUNTIF(C12:BA12,"н/у") -> 0 | BE12: =COUNTIF(C12:BB12,"н") -> 2
A13: 9. | B13: Катков Константин Александрович | C13: оп | E13: оп | H13: 2 | M13: - | N13: н | O13: 2 | Q13: н | R13: оп- | S13: 2 | T13: н | U13: н | W13: 3 | X13: 4 | BC13: =IFERROR(AVERAGE(C13:BB13),"Нет оценок") -> 2.6 | BD13: =COUNTIF(C13:BA13,"н/у") -> 0 | BE13: =COUNTIF(C13:BB13,"н") -> 4
A14: 10. | B14: Корнеев Андрей Александрович | F14: н | G14: н | H14: 3 | M14: 4 | O14: 2 | R14: 3 | S14: - | T14: н | W14: 3 | BC14: =IFERROR(AVERAGE(C14:BB14),"Нет оценок") -> 3 | BD14: =COUNTIF(C14:BA14,"н/у") -> 0 | BE14: =COUNTIF(C14:BB14,"н") -> 3
A15: 11. | B15: Макаров Максим Алексеевич | H15: 3 | M15: 3 | O15: 2 | R15: 3 | S15: 3 | T15: но | W15: 3 | BC15: =IFERROR(AVERAGE(C15:BB15),"Нет оценок") -> 2.8333333 | BD15: =COUNTIF(C15:BA15,"н/у") -> 0 | BE15: =COUNTIF(C15:BB15,"н") -> 0
A16: 13. | B16: Муллагалиев Вадим Радмилович | C16: но | D16: но | H16: 2 | I16: н/у | J16: н/у | M16: - | O16: 3 | Q16: н | R16: 2 | S16: н | U16: оп | BC16: =IFERROR(AVERAGE(C16:BB16),"Нет оценок") -> 2.3333333 | BD16: =COUNTIF(C16:BA16,"н/у") -> 2 | BE16: =COUNTIF(C16:BB16,"н") -> 2
A17: 12. | B17: Натфуллин Камиль Данисович | D17: отп | E17: н | F17: н | H17: 3 | L17: оп | M17: - | O17: 4 | Q17: н | R17: н | S17: н | T17: но | X17: н | BC17: =IFERROR(AVERAGE(C17:BB17),"Нет оценок") -> 3.5 | BD17: =COUNTIF(C17:BA17,"н/у") -> 0 | BE17: =COUNTIF(C17:BB17,"н") -> 6
A18: 14. | B18: Носков Ярослав Евгеньевич | G18: оп | H18: 2 | M18: - | N18: н | O18: 3 | Q18: оп | R18: 2 | S18: 2 | T18: н | U18: н | BC18: =IFERROR(AVERAGE(C18:BB18),"Нет оценок") -> 2.25 | BD18: =COUNTIF(C18:BA18,"н/у") -> 0 | BE18: =COUNTIF(C18:BB18,"н") -> 3
A19: 15. | B19: Осыка Владислав Сергеевич | E19: но | G19: но | H19: 3 | M19: - | O19: 2 | Q19: оп | R19: 3 | S19: - | W19: 3 | BC19: =IFERROR(AVERAGE(C19:BB19),"Нет оценок") -> 2.75 | BD19: =COUNTIF(C19:BA19,"н/у") -> 0 | BE19: =COUNTIF(C19:BB19,"н") -> 0
A20: 16. | B20: Романов Михаил Васильевич | H20: 3 | M20: н | O20: 3 | R20: 2 | S20: н | BC20: =IFERROR(AVERAGE(C20:BB20),"Нет оценок") -> 2.6666667 | BD20: =COUNTIF(C20:BA20,"н/у") -> 0 | BE20: =COUNTIF(C20:BB20,"н") -> 2
A21: 17. | B21: Руфуллаев Ибрагим Фуадович | G21: оп | H21: 3 | I21: оп | L21: оп | M21: - | N21: 4 | O21: 2 | R21: 2 | S21: 2 | U21: н | W21: 3 | BC21: =IFERROR(AVERAGE(C21:BB21),"Нет оценок") -> 2.6666667 | BD21: =COUNTIF(C21:BA21,"н/у") -> 0 | BE21: =COUNTIF(C21:BB21,"н") -> 1
A22: 18. | B22: Сарычев Данила Андреевич | H22: 3 | M22: 3 | O22: 3 | R22: 3 | S22: 3 | V22: н | X22: . | BC22: =IFERROR(AVERAGE(C22:BB22),"Нет оценок") -> 3 | BD22: =COUNTIF(C22:BA22,"н/у") -> 0 | BE22: =COUNTIF(C22:BB22,"н") -> 1
A23: 19. | B23: Сурков Кирилл Александрович | G23: оп | H23: 5 | I23: н | J23: н | K23: н | L23: н | M23: н | O23: 4 | Q23: н | R23: н | S23: 2 | T23: оп | U23: н | V23: н | X23: 4 | BC23: =IFERROR(AVERAGE(C23:BB23),"Нет оценок") -> 3.75 | BD23: =COUNTIF(C23:BA23,"н/у") -> 0 | BE23: =COUNTIF(C23:BB23,"н") -> 9
A24: 20. | B24: Усатов Тимофей Анатольевич | H24: 3 | M24: - | O24: 3 | R24: 3 | S24: 3 | X24: . | BC24: =IFERROR(AVERAGE(C24:BB24),"Нет оценок") -> 3 | BD24: =COUNTIF(C24:BA24,"н/у") -> 0 | BE24: =COUNTIF(C24:BB24,"н") -> 0
A25: 21. | B25: Халитов Кирилл Родионович | F25: оп | G25: н | H25: 2 | I25: н | J25: н | K25: н | M25: н | N25: н/у | O25: 4 | R25: 2 | S25: 2 | T25: н | U25: н | X25: н | BC25: =IFERROR(AVERAGE(C25:BB25),"Нет оценок") -> 2.5 | BD25: =COUNTIF(C25:BA25,"н/у") -> 1 | BE25: =COUNTIF(C25:BB25,"н") -> 8
A26: 21. | B26: Хорошилов Игорь Александрович | BC26: =IFERROR(AVERAGE(C26:BB26),"Нет оценок") -> Нет оценок | BD26: =COUNTIF(C26:BA26,"н/у") -> 0 | BE26: =COUNTIF(C26:BB26,"н") -> 0
A27: 22. | B27: Хрычев Мирон Евгеньевич | G27: н/у | H27: 3 | I27: н | J27: н | M27: - | O27: 3 | R27: 2 | S27: н | X27: н | BC27: =IFERROR(AVERAGE(C27:BB27),"Нет оценок") -> 2.6666667 | BD27: =COUNTIF(C27:BA27,"н/у") -> 1 | BE27: =COUNTIF(C27:BB27,"н") -> 4
A28: 23. | B28: Цапов Илья Валерьевич | E28: оп | G28: оп | H28: 2 | I28: но | J28: но | M28: - | N28: н | O28: 3 | Q28: оп | R28: 2 | S28: 2 | T28: оп | U28: н | V28: н | BC28: =IFERROR(AVERAGE(C28:BB28),"Нет оценок") -> 2.25 | BD28: =COUNTIF(C28:BA28,"н/у") -> 0 | BE28: =COUNTIF(C28:BB28,"н") -> 3
A29: Дата | B29: Тема / ДЗ | G29: пз1 | H29: пз1 | K29: пз2 | M29: пз2 | O29: кр | Q29: лр2 | R29: лр2 | S29: лр2 | W29: кр | BC29: =IFERROR(AVERAGE(BC5:BC28),"") -> 2.8253623 | BD29: =SUM(BD5:BD28) -> 4 | BE29: =SUM(BE5:BE28) -> 72
A30: 45917 | B30: Введение в предмет. Актуальность АИС и БД.
A31: 45917 | B31: Состав и ф-ии СУБД 3ур архитектура
A32: 07/окт. | B32: Структурный подход к проектировнию АИС
A33: 20/окт. | B33: Структурный подход. Диаграммы потоков данных
A34: 27/окт. | B34: ПЗ 1. Моделирование процессов. DFD
A35: 30/окт. | B35: ПЗ 1. Моделирование процессов. DFD
A36: 45982 | B36: Видео-лекция. Концепции проектирования БД
A37: 45982 | B37: Видео-лекция. Инфологическое моделирование. Метод Сущность-связь
A38: 45988 | B38: ПЗ 2. Моделирование процессов. DFD
A39: 45989 | B39: ИЛМ. Метод "сущность-связь"
A40: 45989 | B40: ПЗ 2. Моделирование процессов. DFD
A41: 45994 | B41: Видео-лекция. Метод "сущность-связь". Д.З. Анализ модели Лабораторный практикум
A42: 46000 | B42: Контрольная работа
A44: 46059 | B44: ЛР 2. Построение инфологической модели БД
A45: 46083 | B45: ЛР 2. Построение инфологической модели БД. Метод IDEF1X
A46: 46085 | B46: ЛР 2. Построение инфологической модели БД. Метод Мартина
A47: 46086 | B47: Целостность базы данных
A48: 46087 | B48: Метод нормальных форм
... A51: 46118 | B51: Повторение

Sheet Числ метод
A1: Наименование предмета | C1: Численные методы
A2: ФИО преподавателя | C2: Алпаева Валентина Викторовна
A3: ИСиП 24/2 | B3: Месяц | C3: Сентябрь | I3: Октябрь | O3: Ноябрь | S3: Декабрь | AI3: 3 сем | AK3: Пропуски
B4: Число | C4: 2 | D4: 4 | E4: 8 | F4: 16 | G4: 17 | H4: 26 | I4: 10 | J4: 15 | K4: 16 | L4: 17 | M4: 21 | N4: 29 | O4: 1 | P4: 11 | Q4: 19 | R4: 19 | S4: 2 | T4: 13 | AI4: ДЗ | AJ4: Средний балл | AK4: Уваж. | AL4: Неуваж.
A5: 1. | B5: Адилбеков Бектур | D5: + | E5: + | F5: 2 | J5: н | K5: 3 | L5: 4 | M5: 2 | N5: н/отр | P5: 3 | Q5: 3 | R5: 3 | T5: н | AI5: 2 | AJ5: =IFERROR(AVERAGE(C5:AI5),"Нет оценок") -> 2.75 | AK5: =COUNTIF(C5:AI5,"н/у") -> 0 | AL5: =COUNTIF(C5:AI5,"н") -> 2
A6: 2. | B6: Ахметов Артём Рамилевич | D6: + | E6: н/отр | G6: 4 | H6: н/отр | J6: н/у/отр | K6: н/у/отр | L6: н/у/отр | M6: 4 | N6: н/отр | P6: 4 | Q6: оп | R6: 3 | T6: 3 | AI6: 4 | AJ6: =IFERROR(AVERAGE(C6:AI6),"Нет оценок") -> 3.6666667 | AK6: =COUNTIF(C6:AI6,"н/у") -> 0 | AL6: =COUNTIF(C6:AI6,"н") -> 0
A7: 3. | B7: Бараников Владислав Михайлович | D7: + | E7: + | F7: 5 | H7: н/отр | K7: 5 | L7: 4 | M7: 3 | N7: 3 | P7: 3 | Q7: 5 | R7: 3 | AI7: 3 | AJ7: =IFERROR(AVERAGE(C7:AI7),"Нет оценок") -> 3.7777778 | AK7: =COUNTIF(C7:AI7,"н/у") -> 0 | AL7: =COUNTIF(C7:AI7,"н") -> 0
A8: 4. | B8: Борсук Артём Дмитриевич | D8: + | E8: н/отр | F8: н/отр | G8: н/отр | H8: 4 | J8: н/отр | K8: н/отр | L8: н/отр | M8: 3 | N8: 2 | P8: 3 | Q8: 2 | R8: 3 | S8: 4 | T8: 3 | AI8: 3 | AJ8: =IFERROR(AVERAGE(C8:AI8),"Нет оценок") -> 3 | AK8: =COUNTIF(C8:AI8,"н/у") -> 0 | AL8: =COUNTIF(C8:AI8,"н") -> 0
A9: 5. | B9: Гильманов Ильназ Максимович | D9: + | E9: + | F9: 3 | H9: н/отр | J9: + | K9: 3 | M9: 3 | N9: н/отр | P9: 3 | Q9: 4 | R9: 3 | S9: оп | T9: 3 | AI9: 3 | AJ9: =IFERROR(AVERAGE(C9:AI9),"Нет оценок") -> 3.125 | AK9: =COUNTIF(C9:AI9,"н/у") -> 0 | AL9: =COUNTIF(C9:AI9,"н") -> 0
A10: 6. | B10: Говтва Илья Денисович | D10: + | E10: + | F10: 4 | J10: + | K10: 5 | L10: 4 | M10: 4 | N10: 3 | P10: 3 | Q10: 5 | R10: 3 | AI10: 4 | AJ10: =IFERROR(AVERAGE(C10:AI10),"Нет оценок") -> 3.8888889 | AK10: =COUNTIF(C10:AI10,"н/у") -> 0 | AL10: =COUNTIF(C10:AI10,"н") -> 0
A11: 7. | B11: Горшков Владислав Васильевич | D11: + | E11: + | F11: 2 | H11: н/у/отр | J11: + | K11: 3 | L11: 4 | M11: 3 | N11: 3 | P11: 3 | Q11: н/у/отр | R11: н/у/отр | T11: 3 | AI11: 3 | AJ11: =IFERROR(AVERAGE(C11:AI11),"Нет оценок") -> 3 | AK11: =COUNTIF(C11:AI11,"н/у") -> 0 | AL11: =COUNTIF(C11:AI11,"н") -> 0
A12: 8. | B12: Гришко Илья Алексеевич | D12: н/отр | E12: н/отр | F12: н/отр | G12: н/отр | J12: + | K12: 3 | M12: 3 | N12: 3 | P12: 3 | Q12: 4 | R12: 3 | T12: 3 | AI12: 3 | AJ12: =IFERROR(AVERAGE(C12:AI12),"Нет оценок") -> 3.125 | AK12: =COUNTIF(C12:AI12,"н/у") -> 0 | AL12: =COUNTIF(C12:AI12,"н") -> 0
A13: 9. | B13: Катков Константин Александрович | E13: - | F13: 3 | G13: н | H13: н | J13: н | K13: н | M13: 3 | N13: н | O13: 4 | P13: н | Q13: оп/2 | R13: 4 | T13: н | AI13: 2 | AJ13: =IFERROR(AVERAGE(C13:AI13),"Нет оценок") -> 3.2 | AK13: =COUNTIF(C13:AI13,"н/у") -> 0 | AL13: =COUNTIF(C13:AI13,"н") -> 7
A14: 10. | B14: Корнеев Андрей Александрович | D14: + | E14: + | F14: 2 | J14: н/отр | K14: н/отр | L14: н/отр | M14: 3 | N14: 2 | P14: 2 | Q14: 3 | R14: 3 | AI14: 2 | AJ14: =IFERROR(AVERAGE(C14:AI14),"Нет оценок") -> 2.4285714 | AK14: =COUNTIF(C14:AI14,"н/у") -> 0 | AL14: =COUNTIF(C14:AI14,"н") -> 0
A15: 11. | B15: Макаров Максим Алексеевич | D15: + | E15: + | F15: 3 | H15: оп | J15: + | K15: 3 | M15: 5 | N15: 2 | P15: 3 | Q15: 3 | R15: 4 | T15: 3 | AI15: 3 | AJ15: =IFERROR(AVERAGE(C15:AI15),"Нет оценок") -> 3.2222222 | AK15: =COUNTIF(C15:AI15,"н/у") -> 0 | AL15: =COUNTIF(C15:AI15,"н") -> 0
A16: 13. | B16: Муллагалиев Вадим Радмилович | D16: + | E16: + | F16: 5 | G16: н/отр | J16: н/отр | K16: 4 | M16: 3 | N16: н/отр | P16: 3 | Q16: н/отр | R16: н/отр | T16: 3 | AI16: 3 | AJ16: =IFERROR(AVERAGE(C16:AI16),"Нет оценок") -> 3.5 | AK16: =COUNTIF(C16:AI16,"н/у") -> 0 | AL16: =COUNTIF(C16:AI16,"н") -> 0
A17: 12. | B17: Натфуллин Камиль Данисович | D17: н/отр | E17: - | F17: 2 | H17: н/отр | I17: н/отр | J17: н/отр | K17: 3 | L17: н/отр | M17: 3 | N17: 2 | O17: н/отр | P17: н/отр | Q17: н/отр | R17: н/отр | S17: н/отр | T17: н/отр | AI17: 2 | AJ17: =IFERROR(AVERAGE(C17:AI17),"Нет оценок") -> 2.4 | AK17: =COUNTIF(C17:AI17,"н/у") -> 0 | AL17: =COUNTIF(C17:AI17,"н") -> 0
A18: 14. | B18: Носков Ярослав Евгеньевич | D18: + | E18: + | F18: 3 | I18: - | J18: н | K18: 3 | M18: 3 | N18: н | P18: 2 | Q18: 2 | R18: 3 | AI18: 2 | AJ18: =IFERROR(AVERAGE(C18:AI18),"Нет оценок") -> 2.5714286 | AK18: =COUNTIF(C18:AI18,"н/у") -> 0 | AL18: =COUNTIF(C18:AI18,"н") -> 2
A19: 15. | B19: Осыка Владислав Сергеевич | D19: + | E19: + | F19: 3 | H19: н/отр | J19: н/отр | K19: н/у/отр | M19: 3 | N19: 3 | O19: н/отр | P19: 3 | Q19: 4 | R19: 3 | T19: 3 | AI19: 3 | AJ19: =IFERROR(AVERAGE(C19:AI19),"Нет оценок") -> 3.125 | AK19: =COUNTIF(C19:AI19,"н/у") -> 0 | AL19: =COUNTIF(C19:AI19,"н") -> 0
A20: 16. | B20: Романов Михаил Васильевич | D20: + | E20: + | F20: 4 | J20: + | K20: 3 | M20: 4 | N20: 3 | P20: 3 | Q20: 4 | R20: 3 | AI20: 3 | AJ20: =IFERROR(AVERAGE(C20:AI20),"Нет оценок") -> 3.375 | AK20: =COUNTIF(C20:AI20,"н/у") -> 0 | AL20: =COUNTIF(C20:AI20,"н") -> 0
A21: 17. | B21: Руфуллаев Ибрагим Фуадович | D21: н/о | E21: - | F21: 3 | I21: - | K21: 3 | M21: 3 | N21: н/отр | P21: 3 | Q21: + | R21: 3 | S21: оп | T21: н/отр | AI21: 3 | AJ21: =IFERROR(AVERAGE(C21:AI21),"Нет оценок") -> 3 | AK21: =COUNTIF(C21:AI21,"н/у") -> 0 | AL21: =COUNTIF(C21:AI21,"н") -> 0
A22: 18. | B22: Сарычев Данила Андреевич | C22: н/отр | D22: н/отр | E22: + | F22: 4 | I22: н/отр | J22: + | K22: 3 | M22: 3 | N22: 3 | P22: 3 | Q22: 4 | R22: 3 | S22: н/отр | T22: 3 | AI22: 4 | AJ22: =IFERROR(AVERAGE(C22:AI22),"Нет оценок") -> 3.3333333 | AK22: =COUNTIF(C22:AI22,"н/у") -> 0 | AL22: =COUNTIF(C22:AI22,"н") -> 0
A23: 19. | B23: Сурков Кирилл Александрович | D23: + | E23: + | F23: 4 | H23: н/у/отр | I23: 4 | K23: 4 | L23: н/отр | M23: 4 | N23: н/отр | O23: н/отр | P23: н/отр | Q23: н/отр | R23: 3 | T23: н/отр | AI23: 4 | AJ23: =IFERROR(AVERAGE(C23:AI23),"Нет оценок") -> 3.8333333 | AK23: =COUNTIF(C23:AI23,"н/у") -> 0 | AL23: =COUNTIF(C23:AI23,"н") -> 0
A24: 20. | B24: Усатов Тимофей Анатольевич | D24: + | E24: + | F24: 4 | J24: + | K24: 4 | M24: 4 | N24: 2 | P24: 3 | Q24: 2 | R24: н/отр | T24: н/у/отр | AI24: 3 | AJ24: =IFERROR(AVERAGE(C24:AI24),"Нет оценок") -> 3.1428571 | AK24: =COUNTIF(C24:AI24,"н/у") -> 0 | AL24: =COUNTIF(C24:AI24,"н") -> 0
A25: 21. | B25: Халитов Кирилл Родионович | C25: 4 | D25: + | E25: + | F25: н/отр | H25: н/у/отр | I25: н/отр | J25: н/отр | K25: н/отр | L25: н/отр | M25: 3 | N25: н/отр | O25: н/отр | P25: 3 | Q25: 2 | R25: 3 | S25: н/отр | T25: н/отр | AI25: 3 | AJ25: =IFERROR(AVERAGE(C25:AI25),"Нет оценок") -> 3 | AK25: =COUNTIF(C25:AI25,"н/у") -> 0 | AL25: =COUNTIF(C25:AI25,"н") -> 0
A26: 21. | B26: Хорошилов Игорь Александрович | AJ26: =IFERROR(AVERAGE(C26:AI26),"Нет оценок") -> Нет оценок | AK26: =COUNTIF(C26:AI26,"н/у") -> 0 | AL26: =COUNTIF(C26:AI26,"н") -> 0
A27: 22. | B27: Хрычев Мирон Евгеньевич | D27: + | E27: + | F27: 2 | J27: н | K27: 3 | M27: 2 | N27: н/у | P27: 2 | Q27: н | R27: 3 | AI27: 2 | AJ27: =IFERROR(AVERAGE(C27:AI27),"Нет оценок") -> 2.3333333 | AK27: =COUNTIF(C27:AI27,"н/у") -> 1 | AL27: =COUNTIF(C27:AI27,"н") -> 2
A28: 23. | B28: Цапов Илья Валерьевич | D28: + | E28: - | F28: 3 | H28: н/отр | I28: н/у/отр | J28: н/у/отр | K28: н/у/отр | L28: н/у/отр | M28: 4 | N28: 2 | P28: 4 | Q28: 5 | R28: 3 | S28: оп | T28: н/отр | AI28: 3 | AJ28: =IFERROR(AVERAGE(C28:AI28),"Нет оценок") -> 3.4285714 | AK28: =COUNTIF(C28:AI28,"н/у") -> 0 | AL28: =COUNTIF(C28:AI28,"н") -> 0
A29: Дата | B29: Тема / ДЗ | AJ29: =IFERROR(AVERAGE(AJ5:AJ28),"") -> 3.1403037 | AK29: =SUM(AK5:AK28) -> 1 | AL29: =SUM(AL5:AL28) -> 13
A30: 02\09 | B30: Элементы теории погрешностей
A31: 04\09 | B31: Приближённые решения алгебраических и трансцендентных уравнений
A32: 08\09 | B32: Решение систем линейных алгебраических уравнений
A33: 16\09 | B33: Вычисление погрешностей результатов арифметических действий над приближёнными числами
A34: 17\09 | B34: Решение систем линейных алгебраических уравнений (домашнее) | U34: л
A35: 26\09 | B35: Интерполяция, экстраполяция, аппроксимация
A36: 10\10 | B36: Дифференциальные уравнения
A37: 15\10 | B37: Решение дифференциальных уравнениий. Задача Коши (3-10 слайд)
A38: 16\10 | B38: Дифференциальные уравнения
A39: 17\10 | B39: Дифференциальные уравнения
A40: 21\10 | B40: КОЛЛОКВИУМ
A41: 29\10 | B41: Решение систем линейных алгебраических уравнений (дист)
A42: 1\11 | B42: Решение дифференциальных уравнениий (на дом 2 уравнения)
A43: 11\11 | B43: Решение систем линейных алгебраических уравнений (с/р)
A44: 19\11 | B44: Решение дифференциальных уравнениий
A45: 19\11 | B45: Итоговый тест
A46: 2\12 | B46: Решение дифференциальных уравнениий 2-го порядка с постоянным коэффициентов (д/з)
A47: 13\12 | B47: Решение дифференциальных уравнениий 2-го порядка с постоянным коэффициентов

Sheet Комп сеть
A1: Наименование предмета | C1: Компьютерные сети
A2: ФИО преподавателя | C2: Трушина Александра Игоревна
A3: ИСиП 24/2 | B3: Месяц | D3: октябрь | M3: ноябрь | U3: декабрь | Y3: 3 сем | AA3: Пропуски
B4: Число | C4: 20 | D4: 6 | E4: 14 | F4: 14 | G4: 17 | H4: 21 | J4: 23 | K4: 27 | M4: 1 | N4: 6 | O4: 10 | P4: 11 | Q4: 12 | R4: 15 | S4: 17 | T4: 19 | U4: 2 | Y4: ДЗ | Z4: Средний балл | AA4: Уваж. | AB4: Неуваж.
A5: 1. | B5: Адилбеков Бектур | C5: 5 | D5: 4 | E5: 3 | F5: 2 | G5: о/3 | H5: 4 | I5: 2 | J5: 5 | K5: н | L5: 4 | M5: 4 | N5: 4 | O5: 4 | P5: 5 | Q5: н | R5: 4 | S5: 3 | U5: н | Y5: н | Z5: =IFERROR(AVERAGE(C5:Y5),"Нет оценок") -> 3.7857143 | AA5: =COUNTIF(C5:Y5,"н/у") -> 0 | AB5: =COUNTIF(C5:Y5,"н") -> 4
A6: 2. | B6: Ахметов Артём Рамилевич | C6: 3 | D6: 5 | E6: отр | F6: 3 | G6: отр | H6: 3 | I6: 4 | J6: 5 | K6: 5 | L6: 4 | M6: 4 | N6: 4 | O6: 5 | P6: 4 | Q6: 4 | R6: 5 | Y6: 4 | Z6: =IFERROR(AVERAGE(C6:Y6),"Нет оценок") -> 4.1333333 | AA6: =COUNTIF(C6:Y6,"н/у") -> 0 | AB6: =COUNTIF(C6:Y6,"н") -> 0
A7: 3. | B7: Бараников Владислав Михайлович | C7: 5 | D7: 5 | E7: 5 | F7: 5 | G7: 4 | H7: 5 | I7: 4 | J7: 4 | K7: 5 | L7: 4 | M7: 5 | N7: 5 | O7: 5 | P7: 5 | Q7: 5 | R7: 5 | Y7: 5 | Z7: =IFERROR(AVERAGE(C7:Y7),"Нет оценок") -> 4.7647059 | AA7: =COUNTIF(C7:Y7,"н/у") -> 0 | AB7: =COUNTIF(C7:Y7,"н") -> 0 | AD7: ПЛАН | AG7: ПРОШЛО | AJ7: ОСТАЛОСЬ
A8: 4. | B8: БОрсук Артём Дмитриевич | C8: отр | D8: 4 | E8: 3 | F8: 4 | G8: отр | H8: 5 | I8: 2 | J8: 5 | K8: 5 | L8: 2 | M8: 5 | N8: 5 | O8: 5 | P8: 5 | Q8: отр | R8: 5 | Y8: 4 | Z8: =IFERROR(AVERAGE(C8:Y8),"Нет оценок") -> 4.2142857 | AA8: =COUNTIF(C8:Y8,"н/у") -> 0 | AB8: =COUNTIF(C8:Y8,"н") -> 0 | AE8: Л | AF8: ПЗ | AH8: Л | AI8: ПЗ | AK8: Л | AL8: ПЗ
A9: 5. | B9: Гильманов Ильназ Максимович | C9: отр | D9: 5 | E9: 4 | F9: 5 | G9: 3 | H9: 3 | I9: 4 | J9: 5 | K9: 5 | L9: 2 | M9: 5 | N9: 5 | O9: 5 | P9: 5 | Q9: отр | R9: 5 | Y9: 4 | Z9: =IFERROR(AVERAGE(C9:Y9),"Нет оценок") -> 4.3333333 | AA9: =COUNTIF(C9:Y9,"н/у") -> 0 | AB9: =COUNTIF(C9:Y9,"н") -> 0 | AD9: П | AE9: =AE10/2 -> 12 | AF9: =AF10/2 -> 9 | AG9: П | AH9: =COUNTIF(C28:C108,"Л") -> 7 | AI9: =COUNTIF(C29:C80,"пз") -> 9 | AJ9: П | AK9: =AE9-AH9 -> 5 | AL9: =AF9-AI9 -> 0
A10: 6. | B10: Говтва Илья Денисович | C10: 5 | D10: 5 | E10: 5 | F10: 5 | G10: 5 | H10: 5 | I10: 4 | J10: 4 | K10: 5 | L10: 5 | M10: 5 | N10: 5 | O10: 5 | P10: 5 | Q10: 5 | R10: 5 | S10: 5 | Y10: 5 | Z10: =IFERROR(AVERAGE(C10:Y10),"Нет оценок") -> 4.8888889 | AA10: =COUNTIF(C10:Y10,"н/у") -> 0 | AB10: =COUNTIF(C10:Y10,"н") -> 0 | AD10: Ч | AE10: 24 | AF10: 18 | AG10: Ч | AH10: =AH9*2 -> 14 | AI10: =AI9*2 -> 18 | AJ10: Ч | AK10: =AK9*2 -> 10 | AL10: =AL9*2 -> 0
A11: 7. | B11: Горшков Владислав Васильевич | C11: 5 | D11: 4 | E11: 5 | F11: 3 | G11: 4 | H11: 5 | I11: 2 | J11: 5 | K11: 5 | L11: 2 | M11: 5 | N11: 5 | O11: 5 | P11: 5 | Q11: 5 | R11: 4 | Y11: 5 | Z11: =IFERROR(AVERAGE(C11:Y11),"Нет оценок") -> 4.3529412 | AA11: =COUNTIF(C11:Y11,"н/у") -> 0 | AB11: =COUNTIF(C11:Y11,"н") -> 0
A12: 8. | B12: Гришко Илья Алексеевич | C12: 5 | D12: 4 | E12: 5 | F12: 5 | G12: 3 | H12: 3 | I12: 4 | J12: 4 | K12: 5 | L12: 2 | M12: 3 | N12: 4 | O12: 4 | P12: 2 | Q12: 5 | Y12: 4 | Z12: =IFERROR(AVERAGE(C12:Y12),"Нет оценок") -> 3.875 | AA12: =COUNTIF(C12:Y12,"н/у") -> 0 | AB12: =COUNTIF(C12:Y12,"н") -> 0
A13: 9. | B13: Катков Константин Александрович | C13: 2 | D13: 2 | E13: 2 | F13: 2 | G13: 2 | H13: н | I13: 2 | J13: 2 | K13: 2 | L13: 2 | M13: н | N13: 4 | O13: 3 | P13: н | Q13: н | R13: 2 | Y13: н | Z13: =IFERROR(AVERAGE(C13:Y13),"Нет оценок") -> 2.25 | AA13: =COUNTIF(C13:Y13,"н/у") -> 0 | AB13: =COUNTIF(C13:Y13,"н") -> 5
A14: 10. | B14: Корнеев Андрей Александрович | C14: 5 | D14: н | E14: н | F14: н | G14: н | H14: н | I14: 2 | J14: н | K14: н | L14: 2 | M14: 2 | N14: н | O14: 4 | P14: 4 | Q14: 3 | R14: н | Y14: н | Z14: =IFERROR(AVERAGE(C14:Y14),"Нет оценок") -> 3.1428571 | AA14: =COUNTIF(C14:Y14,"н/у") -> 0 | AB14: =COUNTIF(C14:Y14,"н") -> 10
A15: 11. | B15: Макаров Максим Алексеевич | C15: 3 | D15: 5 | E15: 3 | F15: 5 | G15: 4 | H15: 5 | I15: 4 | J15: 4 | K15: 5 | L15: 3 | M15: 5 | N15: 5 | O15: 3 | P15: 5 | Q15: 4 | R15: 5 | Y15: 4 | Z15: =IFERROR(AVERAGE(C15:Y15),"Нет оценок") -> 4.2352941 | AA15: =COUNTIF(C15:Y15,"н/у") -> 0 | AB15: =COUNTIF(C15:Y15,"н") -> 0
A16: 12. | B16: Муллагалиев Вадим Радмилович | C16: 4 | D16: 4 | E16: 5 | F16: 5 | G16: 4 | H16: 4 | I16: 2 | J16: 4 | K16: 5 | L16: 5 | M16: отр | N16: 5 | O16: 4 | P16: 5 | R16: 5 | Y16: 5 | Z16: =IFERROR(AVERAGE(C16:Y16),"Нет оценок") -> 4.4 | AA16: =COUNTIF(C16:Y16,"н/у") -> 0 | AB16: =COUNTIF(C16:Y16,"н") -> 0
A17: 13. | B17: Натфуллин Камиль Данисович | D17: 4 | F17: 4 | H17: 5 | I17: 2 | J17: 5 | K17: 4 | L17: 2 | M17: отр | N17: 5 | O17: 4 | P17: отр | R17: н/у | Y17: н | Z17: =IFERROR(AVERAGE(C17:Y17),"Нет оценок") -> 3.8888889 | AA17: =COUNTIF(C17:Y17,"н/у") -> 1 | AB17: =COUNTIF(C17:Y17,"н") -> 1
A18: 14. | B18: НоскОв Ярослав Евгеньевич | C18: 3 | D18: 3 | E18: 5 | F18: 3 | G18: 5 | H18: 5 | I18: 4 | J18: 4 | K18: 4 | L18: 4 | M18: 4 | N18: 5 | O18: 4 | P18: 5 | R18: 5 | Y18: 4 | Z18: =IFERROR(AVERAGE(C18:Y18),"Нет оценок") -> 4.1875 | AA18: =COUNTIF(C18:Y18,"н/у") -> 0 | AB18: =COUNTIF(C18:Y18,"н") -> 0
A19: 15. | B19: Осыка Владислав Сергеевич | C19: 3 | D19: 4 | E19: 5 | F19: 5 | G19: 4 | H19: 2 | I19: 4 | J19: 4 | K19: 5 | L19: 5 | M19: 4 | N19: 5 | O19: 5 | P19: 5 | Q19: 5 | R19: 5 | Y19: 5 | Z19: =IFERROR(AVERAGE(C19:Y19),"Нет оценок") -> 4.4117647 | AA19: =COUNTIF(C19:Y19,"н/у") -> 0 | AB19: =COUNTIF(C19:Y19,"н") -> 0
A20: 16. | B20: Романов Михаил Васильевич | C20: 5 | D20: 5 | E20: 5 | F20: 5 | G20: 5 | H20: 5 | I20: 5 | J20: 5 | K20: 5 | L20: 4 | M20: 5 | N20: 5 | O20: 4 | P20: 5 | Q20: 5 | R20: 5 | S20: 5 | Y20: 5 | Z20: =IFERROR(AVERAGE(C20:Y20),"Нет оценок") -> 4.8888889 | AA20: =COUNTIF(C20:Y20,"н/у") -> 0 | AB20: =COUNTIF(C20:Y20,"н") -> 0
A21: 17. | B21: Руфуллаев Ибрагим Фуадович | C21: 5 | D21: 5 | E21: 5 | F21: 4 | G21: 3 | H21: 4 | I21: 4 | J21: 4 | K21: 5 | L21: 3 | M21: 3 | N21: отр | O21: 5 | P21: 5 | Y21: 4 | Z21: =IFERROR(AVERAGE(C21:Y21),"Нет оценок") -> 4.2142857 | AA21: =COUNTIF(C21:Y21,"н/у") -> 0 | AB21: =COUNTIF(C21:Y21,"н") -> 0
A22: 18. | B22: Сарычев Данила Андреевич | C22: 5 | D22: 4 | E22: 5 | F22: 4 | G22: 5 | H22: 4 | I22: 3 | J22: 5 | K22: 5 | L22: 4 | M22: 5 | N22: 4 | O22: 4 | P22: 4 | Q22: 5 | R22: 5 | Y22: 5 | Z22: =IFERROR(AVERAGE(C22:Y22),"Нет оценок") -> 4.4705882 | AA22: =COUNTIF(C22:Y22,"н/у") -> 0 | AB22: =COUNTIF(C22:Y22,"н") -> 0
A23: 19. | B23: Сурков Кирилл Александрович | D23: 5 | E23: 5 | F23: 5 | G23: 3 | H23: 5 | I23: 5 | J23: 5 | K23: 5 | L23: 5 | M23: 4 | N23: 5 | O23: 5 | P23: отр | Q23: отр | R23: отр | Y23: 5 | Z23: =IFERROR(AVERAGE(C23:Y23),"Нет оценок") -> 4.7692308 | AA23: =COUNTIF(C23:Y23,"н/у") -> 0 | AB23: =COUNTIF(C23:Y23,"н") -> 0
A24: 20. | B24: Усатов Тимофей Анатольевич | C24: 4 | D24: 5 | E24: 5 | F24: 5 | G24: 5 | H24: 4 | I24: 2 | J24: 4 | K24: 5 | L24: 5 | M24: 5 | N24: 5 | O24: 4 | P24: 5 | Q24: 5 | R24: 5 | S24: 5 | T24: н/отр | Y24: 5 | Z24: =IFERROR(AVERAGE(C24:Y24),"Нет оценок") -> 4.6111111 | AA24: =COUNTIF(C24:Y24,"н/у") -> 0 | AB24: =COUNTIF(C24:Y24,"н") -> 0
A25: 21. | B25: Халитов Кирилл Родионович | C25: н | D25: отр | E25: н | F25: 4 | G25: н | H25: 4 | I25: 2 | J25: 5 | K25: н | L25: 2 | M25: н | N25: 4 | O25: 4 | P25: 5 | Q25: н | R25: 5 | S25: н | U25: н/у | Y25: н | Z25: =IFERROR(AVERAGE(C25:Y25),"Нет оценок") -> 3.8888889 | AA25: =COUNTIF(C25:Y25,"н/у") -> 1 | AB25: =COUNTIF(C25:Y25,"н") -> 8
A26: 22. | B26: Хорошилов Игорь Александрович | Z26: =IFERROR(AVERAGE(C26:Y26),"Нет оценок") -> Нет оценок | AA26: =COUNTIF(C26:Y26,"н/у") -> 0 | AB26: =COUNTIF(C26:Y26,"н") -> 0
A27: 23. | B27: Хрычев Мирон Евгеньевич | C27: 4 | D27: 4 | E27: 5 | F27: 5 | G27: 2 | H27: 5 | I27: 4 | J27: 4 | K27: 4 | L27: 4 | M27: 4 | N27: 5 | O27: 3 | P27: 5 | Q27: 5 | R27: 3 | S27: 5 | Y27: 5 | Z27: =IFERROR(AVERAGE(C27:Y27),"Нет оценок") -> 4.2222222 | AA27: =COUNTIF(C27:Y27,"н/у") -> 0 | AB27: =COUNTIF(C27:Y27,"н") -> 0
A28: 24. | B28: Цапов Илья Валерьевич | D28: 5 | E28: отр | F28: 5 | G28: отр | H28: 5 | I28: 5 | J28: 5 | K28: 5 | L28: 5 | M28: 4 | N28: 5 | O28: 5 | P28: 5 | Q28: отр | R28: 5 | T28: отр | U28: отр | Y28: 5 | Z28: =IFERROR(AVERAGE(C28:Y28),"Нет оценок") -> 4.9230769 | AA28: =COUNTIF(C28:Y28,"н/у") -> 0 | AB28: =COUNTIF(C28:Y28,"н") -> 0
A29: Дата | B29: Тема / ДЗ | D29: ПР 1 | F29: ПР 2 | H29: ПР 3 | I29: ПР 4 | J29: ПР 5 | K29: ЛР 3 | L29: ЛР 4 | M29: ЛР 5 | N29: ЛР 6 | O29: К | P29: ЛР 7/1 | R29: Л7/2 | Z29: =IFERROR(AVERAGE(Z5:Z28),"") -> 4.2109913 | AA29: =SUM(AA5:AA28) -> 2 | AB29: =SUM(AB5:AB28) -> 28
A30: 45920 | B30: Лекция 1. Введение в сетевые технологии | C30: Л | X30: 5= | Y30: =COUNTIF(Y5:Y29,"5") -> 11
A31: 45936 | B31: Практическая работа №1. Изучение сервисов объединённых сетей | C31: ПЗ | X31: 4= | Y31: =COUNTIF(Y5:Y29,"4") -> 7
A32: 45944 | B32: Работа с рабочими тетрадями. Тема 1.1 | C32: Л | X32: 3= | Y32: =COUNTIF(Y5:Y29,"3") -> 0
A33: 45944 | B33: Практическая работа №2. Исследование возможностей программы Friendly Pinger | C33: ПЗ | F33: о | G33: - опоздал | X33: 2= | Y33: =COUNTIF(Y5:Y29,"2") -> 0
A34: 45947 | B34: Теоретическая лекционная работа: Изучение сетевых стандартов и их реальных документов | C34: Л | X34: н= | Y34: =COUNTIF(Y5:Y29,"н") -> 5
A35: 45951 | B35: Практическая работа 3 | C35: пз
B36: Практическая работа 4
A37: 45953 | B37: Практическая работа 5 | C37: пз
A38: 45957 | B38: Лабораторная работа №3. Построение простейшей компьютерной сети с использованием Cisco Packet Tracer | C38: пз
B39: Лабораторная работа №4.Основные команды операционной системы Cisco IOS
A40: 01.11. | B40: Лабораторная работа №5. Организация простейшей компьютерной сети с помощью коммутатора и концентратора | C40: пз
A41: 45971 | B41: Коллокквиум | C41: пз
A42: 45972 | B42: Лабораторная работа № 7. Изучение технологии виртуальных локальных сетей VLAN. Часть 1 | C42: пз
A43: 45973 | B43: Видео-лекция 12.11.2025 Тема 1.2 в рабочей тетради ИСИП-Р | C43: л
A44: 45672 | B44: Лабораторная работа №7. Изучение технологии виртуальных локальных сетей VLAN. Часть 2 | C44: пз
A45: 45978 | B45: Лекция. Тема 1.3 в рабочей тетради | C45: л
A46: 45980 | B46: Лекция. Раздел 2. Тем 2.1, Тема 2.2 / Сдача долгов, отработка ПЗ | C46: л
A47: 45993 | B47: Заполнение тетради | C47: л

Sheet Теор.вероят и мат.стат
A1: Наименование предмета | C1: Теория вероятности и математическая статистика
A2: ФИО преподавателя
A3: ИСиП 24/2 | B3: Месяц | C3: Январь | F3: Февраль | M3: Март | BX3: 4 сем | BZ3: Пропуски
B4: Число | C4: 14 | D4: 20 | E4: 28 | F4: 3 | G4: 5 | H4: 10 | I4: 11 | J4: 13 | K4: 18 | L4: 28 | M4: 2 | N4: 2 | O4: 3 | P4: 11 | BX4: ДЗ | BY4: Средний балл | BZ4: Уваж. | CA4: Неуваж.
A5: 1. | B5: Адилбеков Бектур | C5: н | E5: оп | F5: н | G5: 2 | I5: н | K5: н | L5: + | M5: н | N5: н | O5: н | P5: н | BY5: =IFERROR(AVERAGE(C5:BX5),"Нет оценок") -> 2 | BZ5: =COUNTIF(C5:BW5,"н/у") -> 0 | CA5: =COUNTIF(C5:BX5,"н") -> 8
A6: 2. | B6: Ахметов Артём Рамилевич | C6: н/отр | D6: н | E6: н | F6: 2 | G6: 3 | J6: н | K6: н | L6: н | M6: 3 | P6: 5 | BY6: =IFERROR(AVERAGE(C6:BX6),"Нет оценок") -> 3.25 | BZ6: =COUNTIF(C6:BW6,"н/у") -> 0 | CA6: =COUNTIF(C6:BX6,"н") -> 5
A7: 3. | B7: Бараников Владислав Михайлович | D7: + | F7: 5 | G7: 2 | K7: 5 | L7: + | M7: 4 | P7: 4 | BY7: =IFERROR(AVERAGE(C7:BX7),"Нет оценок") -> 4 | BZ7: =COUNTIF(C7:BW7,"н/у") -> 0 | CA7: =COUNTIF(C7:BX7,"н") -> 0
A8: 4. | B8: Борсук Артём Дмитриевич | F8: 4 | G8: 2 | J8: н | K8: н | L8: + | M8: оп | P8: 4 | BY8: =IFERROR(AVERAGE(C8:BX8),"Нет оценок") -> 3.3333333 | BZ8: =COUNTIF(C8:BW8,"н/у") -> 0 | CA8: =COUNTIF(C8:BX8,"н") -> 2
A9: 5. | B9: Гильманов Ильназ Максимович | C9: н/отр | D9: + | F9: 2 | G9: 2 | I9: н | K9: н | L9: + | M9: 4 | O9: оп | P9: . | BY9: =IFERROR(AVERAGE(C9:BX9),"Нет оценок") -> 2.6666667 | BZ9: =COUNTIF(C9:BW9,"н/у") -> 0 | CA9: =COUNTIF(C9:BX9,"н") -> 2
A10: 6. | B10: Говтва Илья Денисович | D10: + | F10: 5 | G10: 2 | J10: 5 | K10: 5 | L10: + | M10: 4 | O10: оп | P10: 5 | BY10: =IFERROR(AVERAGE(C10:BX10),"Нет оценок") -> 4.3333333 | BZ10: =COUNTIF(C10:BW10,"н/у") -> 0 | CA10: =COUNTIF(C10:BX10,"н") -> 0
A11: 7. | B11: Горшков Владислав Васильевич | D11: оп | E11: н | F11: 5 | G11: 2 | K11: 5 | L11: + | M11: 3 | P11: 4 | BY11: =IFERROR(AVERAGE(C11:BX11),"Нет оценок") -> 3.8 | BZ11: =COUNTIF(C11:BW11,"н/у") -> 0 | CA11: =COUNTIF(C11:BX11,"н") -> 1
A12: 8. | B12: Гришко Илья Алексеевич | C12: н/отр | D12: н | F12: 2 | G12: 2 | K12: н | L12: + | M12: 3 | P12: . | BY12: =IFERROR(AVERAGE(C12:BX12),"Нет оценок") -> 2.3333333 | BZ12: =COUNTIF(C12:BW12,"н/у") -> 0 | CA12: =COUNTIF(C12:BX12,"н") -> 2
A13: 9. | B13: Катков Константин Александрович | C13: 5 | D13: н | E13: оп | F13: н | G13: н | H13: н | I13: н | J13: н | K13: н | L13: н | M13: 2 | O13: н | P13: 3 | BY13: =IFERROR(AVERAGE(C13:BX13),"Нет оценок") -> 3.3333333 | BZ13: =COUNTIF(C13:BW13,"н/у") -> 0 | CA13: =COUNTIF(C13:BX13,"н") -> 9
A14: 10. | B14: Корнеев Андрей Александрович | C14: н | E14: оп | F14: 2 | G14: 2 | I14: оп | K14: н | L14: + | M14: 2 | P14: . | BY14: =IFERROR(AVERAGE(C14:BX14),"Нет оценок") -> 2 | BZ14: =COUNTIF(C14:BW14,"н/у") -> 0 | CA14: =COUNTIF(C14:BX14,"н") -> 2
A15: 11. | B15: Макаров Максим Алексеевич | F15: 2 | G15: 2 | K15: 4 | L15: + | M15: 2 | P15: 5 | BY15: =IFERROR(AVERAGE(C15:BX15),"Нет оценок") -> 3 | BZ15: =COUNTIF(C15:BW15,"н/у") -> 0 | CA15: =COUNTIF(C15:BX15,"н") -> 0
A16: 13. | B16: Муллагалиев Вадим Радмилович | D16: н | F16: 2 | G16: 3 | K16: 5 | L16: + | M16: 3 | P16: 4 | BY16: =IFERROR(AVERAGE(C16:BX16),"Нет оценок") -> 3.4 | BZ16: =COUNTIF(C16:BW16,"н/у") -> 0 | CA16: =COUNTIF(C16:BX16,"н") -> 1
A17: 12. | B17: Натфуллин Камиль Данисович | C17: н/отр | E17: н | F17: 2 | G17: 3 | I17: 3 | K17: н | L17: + | M17: 5 | O17: н | P17: н | BY17: =IFERROR(AVERAGE(C17:BX17),"Нет оценок") -> 3.25 | BZ17: =COUNTIF(C17:BW17,"н/у") -> 0 | CA17: =COUNTIF(C17:BX17,"н") -> 4
A18: 14. | B18: Носков Ярослав Евгеньевич | D18: оп | F18: н | G18: 2 | K18: н | L18: н | M18: 2 | O18: н | P18: . | BY18: =IFERROR(AVERAGE(C18:BX18),"Нет оценок") -> 2 | BZ18: =COUNTIF(C18:BW18,"н/у") -> 0 | CA18: =COUNTIF(C18:BX18,"н") -> 4
A19: 15. | B19: Осыка Владислав Сергеевич | D19: н/отр | F19: 4 | G19: 3 | H19: н | K19: 5 | L19: + | M19: 2 | N19: н | O19: оп | P19: 4 | BY19: =IFERROR(AVERAGE(C19:BX19),"Нет оценок") -> 3.6 | BZ19: =COUNTIF(C19:BW19,"н/у") -> 0 | CA19: =COUNTIF(C19:BX19,"н") -> 2
A20: 16. | B20: Романов Михаил Васильевич | C20: н | D20: н | F20: 4 | G20: н | K20: 4 | L20: н | M20: 2 | P20: 4 | BY20: =IFERROR(AVERAGE(C20:BX20),"Нет оценок") -> 3.5 | BZ20: =COUNTIF(C20:BW20,"н/у") -> 0 | CA20: =COUNTIF(C20:BX20,"н") -> 4
A21: 17. | B21: Руфуллаев Ибрагим Фуадович | C21: н | D21: н | F21: 2 | G21: 2 | H21: н | I21: 3 | K21: н | L21: + | M21: 2 | O21: н | P21: 4 | BY21: =IFERROR(AVERAGE(C21:BX21),"Нет оценок") -> 2.6 | BZ21: =COUNTIF(C21:BW21,"н/у") -> 0 | CA21: =COUNTIF(C21:BX21,"н") -> 5
A22: 18. | B22: Сарычев Данила Андреевич | F22: 4 | G22: 3 | J22: н | K22: 5 | L22: + | M22: 4 | P22: 5 | BY22: =IFERROR(AVERAGE(C22:BX22),"Нет оценок") -> 4.2 | BZ22: =COUNTIF(C22:BW22,"н/у") -> 0 | CA22: =COUNTIF(C22:BX22,"н") -> 1
A23: 19. | B23: Сурков Кирилл Александрович | C23: н | D23: н | F23: 2 | G23: 4 | H23: н | I23: оп | J23: н | K23: н | L23: н | M23: н | N23: н | O23: оп | P23: н | BY23: =IFERROR(AVERAGE(C23:BX23),"Нет оценок") -> 3 | BZ23: =COUNTIF(C23:BW23,"н/у") -> 0 | CA23: =COUNTIF(C23:BX23,"н") -> 9
A24: 20. | B24: Усатов Тимофей Анатольевич | D24: + | F24: 4 | G24: 2 | K24: н/отр | L24: + | M24: 3 | P24: 4 | BY24: =IFERROR(AVERAGE(C24:BX24),"Нет оценок") -> 3.25 | BZ24: =COUNTIF(C24:BW24,"н/у") -> 0 | CA24: =COUNTIF(C24:BX24,"н") -> 0
A25: 21. | B25: Халитов Кирилл Родионович | C25: н | D25: н | E25: н | F25: н | G25: н | J25: н | K25: н | L25: оп | M25: н | N25: н | P25: . | BY25: =IFERROR(AVERAGE(C25:BX25),"Нет оценок") -> Нет оценок | BZ25: =COUNTIF(C25:BW25,"н/у") -> 0 | CA25: =COUNTIF(C25:BX25,"н") -> 9
A26: 21. | B26: Хорошилов Игорь Александрович | BY26: =IFERROR(AVERAGE(C26:BX26),"Нет оценок") -> Нет оценок | BZ26: =COUNTIF(C26:BW26,"н/у") -> 0 | CA26: =COUNTIF(C26:BX26,"н") -> 0
A27: 22. | B27: Хрычев Мирон Евгеньевич | F27: н | G27: 2 | K27: н | L27: + | M27: 2 | P27: . | BY27: =IFERROR(AVERAGE(C27:BX27),"Нет оценок") -> 2 | BZ27: =COUNTIF(C27:BW27,"н/у") -> 0 | CA27: =COUNTIF(C27:BX27,"н") -> 2
A28: 23. | B28: Цапов Илья Валерьевич | C28: н | D28: + | F28: н | G28: 4 | H28: н | K28: н | L28: н | M28: н | N28: н | O28: оп | P28: 4 | BY28: =IFERROR(AVERAGE(C28:BX28),"Нет оценок") -> 4 | BZ28: =COUNTIF(C28:BW28,"н/у") -> 0 | CA28: =COUNTIF(C28:BX28,"н") -> 7
A29: Дата | B29: Тема / ДЗ | BY29: =IFERROR(AVERAGE(BY5:BY28),"") -> 3.1295455 | BZ29: =SUM(BZ5:BZ28) -> 0 | CA29: =SUM(CA5:CA28) -> 79
A30: 14\01 | B30: Случайные события. Вероятность случайного события.
A31: 20\01 | B31: Случайные события. Вероятность случайного события. (задачи)
A32: 28\01 | B32: Формула Бернулли
A33: 03\02 | B33: Решение задач (дист)
A34: 05\02 | B34: Случайные события. Вероятность случайного события. (с/р)
A35: 10\02 | B35: Случайные величины (проверить таблицу и мат.ожид.)
A36: 11\02 | B36: Случайные дискретные величины
A37: 13\02 | B37: Случайные дискретные величины
A38: 18\02 | B38: Дискретная случайная величина, решение задач (дист)
A39: 28\02 | B39: Дискретная случайная величина, решение задач
A40: 02\03 | B40: Дискретная случайная величина (с/р)
A41: 02\03 | B41: Дискретная случайная величина (с/р)
... A43: 11\03 | B43: Математическая статистика (тест)

Sheet Дискрет.мат 
A1: Наименование предмета | C1: Дискретная математика
A2: ФИО преподавателя
A3: ИСиП 24/2 | B3: Месяц | C3: Январь | F3: Февраль | J3: Март | M3: Апрель | BQ3: 4 сем | BS3: Пропуски
B4: Число | C4: 16 | D4: 21 | E4: 30 | F4: 4 | G4: 9 | H4: 10 | I4: 24 | J4: 11 | K4: 14 | L4: 31 | M4: 8 | N4: 10 | BQ4: ДЗ | BR4: Средний балл | BS4: Уваж. | BT4: Неуваж.
A5: 1. | B5: Адилбеков Бектур | C5: + | D5: н | E5: + | G5: оп | H5: 2 | I5: н | J5: н | K5: н | L5: н | M5: н | BR5: =IFERROR(AVERAGE(C5:BQ5),"Нет оценок") -> 2 | BS5: =COUNTIF(C5:BQ5,"н/у") -> 0 | BT5: =COUNTIF(C5:BQ5,"н") -> 6
A6: 2. | B6: Ахметов Артём Рамилевич | C6: н | D6: 2 | E6: н | F6: н | H6: 2 | I6: н | J6: оп | M6: н | BR6: =IFERROR(AVERAGE(C6:BQ6),"Нет оценок") -> 2 | BS6: =COUNTIF(C6:BQ6,"н/у") -> 0 | BT6: =COUNTIF(C6:BQ6,"н") -> 5
A7: 3. | B7: Бараников Владислав Михайлович | C7: + | D7: 4 | E7: + | H7: 3 | I7: + | K7: 5 | M7: + | BR7: =IFERROR(AVERAGE(C7:BQ7),"Нет оценок") -> 4 | BS7: =COUNTIF(C7:BQ7,"н/у") -> 0 | BT7: =COUNTIF(C7:BQ7,"н") -> 0
A8: 4. | B8: Борсук Артём Дмитриевич | C8: н | D8: 3 | E8: оп | H8: 2 | I8: + | M8: + | BR8: =IFERROR(AVERAGE(C8:BQ8),"Нет оценок") -> 2.5 | BS8: =COUNTIF(C8:BQ8,"н/у") -> 0 | BT8: =COUNTIF(C8:BQ8,"н") -> 1
A9: 5. | B9: Гильманов Ильназ Максимович | C9: ? | D9: н | E9: оп | F9: + | H9: 2 | I9: + | J9: н | M9: н | BR9: =IFERROR(AVERAGE(C9:BQ9),"Нет оценок") -> 2 | BS9: =COUNTIF(C9:BQ9,"н/у") -> 0 | BT9: =COUNTIF(C9:BQ9,"н") -> 3
A10: 6. | B10: Говтва Илья Денисович | C10: + | D10: 5 | E10: + | H10: 3 | I10: + | K10: 5 | L10: 5 | M10: + | BR10: =IFERROR(AVERAGE(C10:BQ10),"Нет оценок") -> 4.5 | BS10: =COUNTIF(C10:BQ10,"н/у") -> 0 | BT10: =COUNTIF(C10:BQ10,"н") -> 0
A11: 7. | B11: Горшков Владислав Васильевич | C11: н | D11: 4 | E11: оп | F11: + | H11: 2 | I11: + | J11: оп | K11: 4 | M11: + | BR11: =IFERROR(AVERAGE(C11:BQ11),"Нет оценок") -> 3.3333333 | BS11: =COUNTIF(C11:BQ11,"н/у") -> 0 | BT11: =COUNTIF(C11:BQ11,"н") -> 1
A12: 8. | B12: Гришко Илья Алексеевич | C12: н/отр | D12: 5 | E12: + | F12: + | H12: 2 | I12: + | M12: н | BR12: =IFERROR(AVERAGE(C12:BQ12),"Нет оценок") -> 3.5 | BS12: =COUNTIF(C12:BQ12,"н/у") -> 0 | BT12: =COUNTIF(C12:BQ12,"н") -> 1
A13: 9. | B13: Катков Константин Александрович | C13: н | D13: н | E13: н | G13: н | H13: 2 | I13: н | K13: оп | L13: н | M13: н | BR13: =IFERROR(AVERAGE(C13:BQ13),"Нет оценок") -> 2 | BS13: =COUNTIF(C13:BQ13,"н/у") -> 0 | BT13: =COUNTIF(C13:BQ13,"н") -> 7
A14: 10. | B14: Корнеев Андрей Александрович | C14: ? | D14: н | E14: оп | H14: 2 | I14: - | M14: + | BR14: =IFERROR(AVERAGE(C14:BQ14),"Нет оценок") -> 2 | BS14: =COUNTIF(C14:BQ14,"н/у") -> 0 | BT14: =COUNTIF(C14:BQ14,"н") -> 1
A15: 11. | B15: Макаров Максим Алексеевич | C15: + | D15: 2 | E15: + | H15: 3 | I15: + | K15: 5 | L15: н | M15: н | BR15: =IFERROR(AVERAGE(C15:BQ15),"Нет оценок") -> 3.3333333 | BS15: =COUNTIF(C15:BQ15,"н/у") -> 0 | BT15: =COUNTIF(C15:BQ15,"н") -> 2
A16: 13. | B16: Муллагалиев Вадим Радмилович | C16: ? | D16: 2 | E16: + | F16: н | H16: 3 | I16: + | K16: 5 | M16: н | BR16: =IFERROR(AVERAGE(C16:BQ16),"Нет оценок") -> 3.3333333 | BS16: =COUNTIF(C16:BQ16,"н/у") -> 0 | BT16: =COUNTIF(C16:BQ16,"н") -> 2
A17: 12. | B17: Натфуллин Камиль Данисович | C17: н | D17: н | E17: оп | G17: оп | H17: 2 | I17: н | J17: н | K17: н | L17: н | M17: + | BR17: =IFERROR(AVERAGE(C17:BQ17),"Нет оценок") -> 2 | BS17: =COUNTIF(C17:BQ17,"н/у") -> 0 | BT17: =COUNTIF(C17:BQ17,"н") -> 6
A18: 14. | B18: Носков Ярослав Евгеньевич | C18: ? | D18: н | E18: - | H18: 2 | I18: + | L18: н | M18: н | BR18: =IFERROR(AVERAGE(C18:BQ18),"Нет оценок") -> 2 | BS18: =COUNTIF(C18:BQ18,"н/у") -> 0 | BT18: =COUNTIF(C18:BQ18,"н") -> 3
A19: 15. | B19: Осыка Владислав Сергеевич | C19: ? | D19: 5 | E19: + | F19: + | H19: н | I19: + | M19: + | BR19: =IFERROR(AVERAGE(C19:BQ19),"Нет оценок") -> 5 | BS19: =COUNTIF(C19:BQ19,"н/у") -> 0 | BT19: =COUNTIF(C19:BQ19,"н") -> 1
A20: 16. | B20: Романов Михаил Васильевич | C20: + | D20: 4 | E20: + | F20: н | G20: н | H20: 2 | I20: + | M20: + | BR20: =IFERROR(AVERAGE(C20:BQ20),"Нет оценок") -> 3 | BS20: =COUNTIF(C20:BQ20,"н/у") -> 0 | BT20: =COUNTIF(C20:BQ20,"н") -> 2
A21: 17. | B21: Руфуллаев Ибрагим Фуадович | C21: н | D21: 2 | E21: н | H21: 2 | I21: + | K21: 3 | L21: оп | M21: н | BR21: =IFERROR(AVERAGE(C21:BQ21),"Нет оценок") -> 2.3333333 | BS21: =COUNTIF(C21:BQ21,"н/у") -> 0 | BT21: =COUNTIF(C21:BQ21,"н") -> 3
A22: 18. | B22: Сарычев Данила Андреевич | C22: н | D22: 4 | E22: + | F22: + | H22: 2 | I22: н | K22: н | L22: н/у | M22: н | BR22: =IFERROR(AVERAGE(C22:BQ22),"Нет оценок") -> 3 | BS22: =COUNTIF(C22:BQ22,"н/у") -> 1 | BT22: =COUNTIF(C22:BQ22,"н") -> 4
A23: 19. | B23: Сурков Кирилл Александрович | C23: н | D23: 5 | E23: н | F23: н | G23: оп | H23: н | I23: н | J23: н | K23: н | L23: н | M23: н | BR23: =IFERROR(AVERAGE(C23:BQ23),"Нет оценок") -> 5 | BS23: =COUNTIF(C23:BQ23,"н/у") -> 0 | BT23: =COUNTIF(C23:BQ23,"н") -> 9
A24: 20. | B24: Усатов Тимофей Анатольевич | C24: + | D24: 5 | E24: оп | G24: + | H24: 2 | I24: + | K24: 5 | L24: н/отр | M24: н | BR24: =IFERROR(AVERAGE(C24:BQ24),"Нет оценок") -> 4 | BS24: =COUNTIF(C24:BQ24,"н/у") -> 0 | BT24: =COUNTIF(C24:BQ24,"н") -> 1
A25: 21. | B25: Халитов Кирилл Родионович | C25: н | D25: н | E25: оп | F25: н | G25: оп | H25: 2 | I25: + | K25: н | L25: н | M25: н | BR25: =IFERROR(AVERAGE(C25:BQ25),"Нет оценок") -> 2 | BS25: =COUNTIF(C25:BQ25,"н/у") -> 0 | BT25: =COUNTIF(C25:BQ25,"н") -> 6
A26: 21. | B26: Хорошилов Игорь Александрович | BR26: =IFERROR(AVERAGE(C26:BQ26),"Нет оценок") -> Нет оценок | BS26: =COUNTIF(C26:BQ26,"н/у") -> 0 | BT26: =COUNTIF(C26:BQ26,"н") -> 0
A27: 22. | B27: Хрычев Мирон Евгеньевич | C27: н | D27: н | E27: + | H27: 2 | I27: - | K27: н | M27: н | BR27: =IFERROR(AVERAGE(C27:BQ27),"Нет оценок") -> 2 | BS27: =COUNTIF(C27:BQ27,"н/у") -> 0 | BT27: =COUNTIF(C27:BQ27,"н") -> 4
A28: 23. | B28: Цапов Илья Валерьевич | C28: н | D28: 4 | E28: н | F28: н | G28: оп | H28: н | I28: + | K28: 4 | M28: н | BR28: =IFERROR(AVERAGE(C28:BQ28),"Нет оценок") -> 4 | BS28: =COUNTIF(C28:BQ28,"н/у") -> 0 | BT28: =COUNTIF(C28:BQ28,"н") -> 5
A29: Дата | B29: Тема / ДЗ | BR29: =IFERROR(AVERAGE(BR5:BR28),"") -> 2.9927536 | BS29: =SUM(BS5:BS28) -> 1 | BT29: =SUM(BT5:BT28) -> 73
A30: 16\01 | B30: Множества (дописать законы де Моргана)
A31: 21\01 | B31: Множества (дист)
A32: 30\01 | B32: Множества, операции над ними
A33: 04\02 | B33: Множества, операции над ними
A34: 09\02 | B34: Множества, операции над ними (подготовиться к самост. работе)
A35: 10\02 | B35: Множества, операции над ними: итоговая работа по теме
A36: 24\02 | B36: Логика высказываний (подг. к устному опросу)
A37: 11\03 | B37: Составление таблиц истинности. Предикаты
A38: 14\03 | B38: Составление таблиц истинности. Равносильность формул
A39: 31\03 | B39: Высказывания и логические операции над ними

Sheet Внедр.подд.комп.систем
A1: Наименование предмета | C1: Внедрение и поддержка компьютерных систем
A2: ФИО преподавателя
A3: ИСиП 24/2 | B3: Месяц | BD3: Пропуски
B4: Число | BC4: Средний балл | BD4: Уваж. | BE4: Неуваж.
A5: 1. | B5: Адилбеков Бектур | BC5: =IFERROR(AVERAGE(C5:BB5),"Нет оценок") -> Нет оценок | BD5: =COUNTIF(C5:BB5,"н/у") -> 0 | BE5: =COUNTIF(C5:BB5,"н") -> 0
A6: 2. | B6: Ахметов Артём Рамилевич | BC6: =IFERROR(AVERAGE(C6:BB6),"Нет оценок") -> Нет оценок | BD6: =COUNTIF(C6:BB6,"н/у") -> 0 | BE6: =COUNTIF(C6:BB6,"н") -> 0
A7: 3. | B7: Бараников Владислав Михайлович | BC7: =IFERROR(AVERAGE(C7:BB7),"Нет оценок") -> Нет оценок | BD7: =COUNTIF(C7:BB7,"н/у") -> 0 | BE7: =COUNTIF(C7:BB7,"н") -> 0
A8: 4. | B8: Борсук Артём Дмитриевич | BC8: =IFERROR(AVERAGE(C8:BB8),"Нет оценок") -> Нет оценок | BD8: =COUNTIF(C8:BB8,"н/у") -> 0 | BE8: =COUNTIF(C8:BB8,"н") -> 0
A9: 5. | B9: Гильманов Ильназ Максимович | BC9: =IFERROR(AVERAGE(C9:BB9),"Нет оценок") -> Нет оценок | BD9: =COUNTIF(C9:BB9,"н/у") -> 0 | BE9: =COUNTIF(C9:BB9,"н") -> 0
A10: 6. | B10: Говтва Илья Денисович | BC10: =IFERROR(AVERAGE(C10:BB10),"Нет оценок") -> Нет оценок | BD10: =COUNTIF(C10:BB10,"н/у") -> 0 | BE10: =COUNTIF(C10:BB10,"н") -> 0
A11: 7. | B11: Горшков Владислав Васильевич | BC11: =IFERROR(AVERAGE(C11:BB11),"Нет оценок") -> Нет оценок | BD11: =COUNTIF(C11:BB11,"н/у") -> 0 | BE11: =COUNTIF(C11:BB11,"н") -> 0
A12: 8. | B12: Гришко Илья Алексеевич | BC12: =IFERROR(AVERAGE(C12:BB12),"Нет оценок") -> Нет оценок | BD12: =COUNTIF(C12:BB12,"н/у") -> 0 | BE12: =COUNTIF(C12:BB12,"н") -> 0
A13: 9. | B13: Катков Константин Александрович | BC13: =IFERROR(AVERAGE(C13:BB13),"Нет оценок") -> Нет оценок | BD13: =COUNTIF(C13:BB13,"н/у") -> 0 | BE13: =COUNTIF(C13:BB13,"н") -> 0
A14: 10. | B14: Корнеев Андрей Александрович | BC14: =IFERROR(AVERAGE(C14:BB14),"Нет оценок") -> Нет оценок | BD14: =COUNTIF(C14:BB14,"н/у") -> 0 | BE14: =COUNTIF(C14:BB14,"н") -> 0
A15: 11. | B15: Макаров Максим Алексеевич | BC15: =IFERROR(AVERAGE(C15:BB15),"Нет оценок") -> Нет оценок | BD15: =COUNTIF(C15:BB15,"н/у") -> 0 | BE15: =COUNTIF(C15:BB15,"н") -> 0
A16: 13. | B16: Муллагалиев Вадим Радмилович | BC16: =IFERROR(AVERAGE(C16:BB16),"Нет оценок") -> Нет оценок | BD16: =COUNTIF(C16:BB16,"н/у") -> 0 | BE16: =COUNTIF(C16:BB16,"н") -> 0
... A28: 23. | B28: Цапов Илья Валерьевич | BC28: =IFERROR(AVERAGE(C28:BB28),"Нет оценок") -> Нет оценок | BD28: =COUNTIF(C28:BB28,"н/у") -> 0 | BE28: =COUNTIF(C28:BB28,"н") -> 0
A29: Дата | B29: Тема / ДЗ | BC29: =IFERROR(AVERAGE(BC5:BC28),"") | BD29: =SUM(BD5:BD28) -> 0 | BE29: =SUM(BE5:BE28) -> 0

Sheet Разработка кода ИС
A1: Наименование предмета | C1: Разработка кода ИС
A2: ФИО преподавателя
A3: ИСиП 24/2 | B3: Месяц | C3: 2 | D3: 3 | E3: 3 | F3: 3 | G3: 3 | H3: 3 | I3: 4 | J3: 4 | AO3: 4 сем | AQ3: Пропуски
B4: Число | C4: 16 | D4: 3 | E4: 4 | F4: 7 | G4: 12 | H4: 30 | I4: 4 | J4: 7 | AO4: ДЗ | AP4: Средний балл | AQ4: Уваж. | AR4: Неуваж.
A5: 1. | B5: Адилбеков Бектур | C5: н | E5: н | F5: н | H5: н | I5: н | J5: н | AP5: =IFERROR(AVERAGE(C5:AO5),"Нет оценок") -> Нет оценок | AQ5: =COUNTIF(C5:AO5,"н/у") -> 0 | AR5: =COUNTIF(C5:AO5,"н") -> 6
A6: 2. | B6: Ахметов Артём Рамилевич | C6: н | D6: 3 | E6: н | G6: н | I6: 2 | AP6: =IFERROR(AVERAGE(C6:AO6),"Нет оценок") -> 2.5 | AQ6: =COUNTIF(C6:AO6,"н/у") -> 0 | AR6: =COUNTIF(C6:AO6,"н") -> 3
A7: 3. | B7: Бараников Владислав Михайлович | D7: 5 | AP7: =IFERROR(AVERAGE(C7:AO7),"Нет оценок") -> 5 | AQ7: =COUNTIF(C7:AO7,"н/у") -> 0 | AR7: =COUNTIF(C7:AO7,"н") -> 0
A8: 4. | B8: Борсук Артём Дмитриевич | C8: н | G8: о | AP8: =IFERROR(AVERAGE(C8:AO8),"Нет оценок") -> Нет оценок | AQ8: =COUNTIF(C8:AO8,"н/у") -> 0 | AR8: =COUNTIF(C8:AO8,"н") -> 1
A9: 5. | B9: Гильманов Ильназ Максимович | D9: 2 | E9: н | G9: + | I9: 2 | AP9: =IFERROR(AVERAGE(C9:AO9),"Нет оценок") -> 2 | AQ9: =COUNTIF(C9:AO9,"н/у") -> 0 | AR9: =COUNTIF(C9:AO9,"н") -> 1
A10: 6. | B10: Говтва Илья Денисович | D10: 5 | AP10: =IFERROR(AVERAGE(C10:AO10),"Нет оценок") -> 5 | AQ10: =COUNTIF(C10:AO10,"н/у") -> 0 | AR10: =COUNTIF(C10:AO10,"н") -> 0
A11: 7. | B11: Горшков Владислав Васильевич | C11: н | D11: 2 | I11: н | AP11: =IFERROR(AVERAGE(C11:AO11),"Нет оценок") -> 2 | AQ11: =COUNTIF(C11:AO11,"н/у") -> 0 | AR11: =COUNTIF(C11:AO11,"н") -> 2
A12: 8. | B12: Гришко Илья Алексеевич | D12: 2 | AP12: =IFERROR(AVERAGE(C12:AO12),"Нет оценок") -> 2 | AQ12: =COUNTIF(C12:AO12,"н/у") -> 0 | AR12: =COUNTIF(C12:AO12,"н") -> 0
A13: 9. | B13: Катков Константин Александрович | C13: н | D13: 2 | F13: н | G13: о | H13: н | AP13: =IFERROR(AVERAGE(C13:AO13),"Нет оценок") -> 2 | AQ13: =COUNTIF(C13:AO13,"н/у") -> 0 | AR13: =COUNTIF(C13:AO13,"н") -> 3
A14: 10. | B14: Корнеев Андрей Александрович | D14: 2 | AP14: =IFERROR(AVERAGE(C14:AO14),"Нет оценок") -> 2 | AQ14: =COUNTIF(C14:AO14,"н/у") -> 0 | AR14: =COUNTIF(C14:AO14,"н") -> 0
A15: 11. | B15: Макаров Максим Алексеевич | D15: 2 | G15: о | AP15: =IFERROR(AVERAGE(C15:AO15),"Нет оценок") -> 2 | AQ15: =COUNTIF(C15:AO15,"н/у") -> 0 | AR15: =COUNTIF(C15:AO15,"н") -> 0
A16: 13. | B16: Муллагалиев Вадим Радмилович | H16: н | J16: н | AP16: =IFERROR(AVERAGE(C16:AO16),"Нет оценок") -> Нет оценок | AQ16: =COUNTIF(C16:AO16,"н/у") -> 0 | AR16: =COUNTIF(C16:AO16,"н") -> 2
A17: 12. | B17: Натфуллин Камиль Данисович | C17: н | D17: 2 | E17: н | H17: н | I17: н | AP17: =IFERROR(AVERAGE(C17:AO17),"Нет оценок") -> 2 | AQ17: =COUNTIF(C17:AO17,"н/у") -> 0 | AR17: =COUNTIF(C17:AO17,"н") -> 4
A18: 14. | B18: Носков Ярослав Евгеньевич | D18: 2 | AP18: =IFERROR(AVERAGE(C18:AO18),"Нет оценок") -> 2 | AQ18: =COUNTIF(C18:AO18,"н/у") -> 0 | AR18: =COUNTIF(C18:AO18,"н") -> 0
A19: 15. | B19: Осыка Владислав Сергеевич | D19: 2 | E19: н | G19: н | I19: 2 | AP19: =IFERROR(AVERAGE(C19:AO19),"Нет оценок") -> 2 | AQ19: =COUNTIF(C19:AO19,"н/у") -> 0 | AR19: =COUNTIF(C19:AO19,"н") -> 2
A20: 16. | B20: Романов Михаил Васильевич | E20: н | I20: н | AP20: =IFERROR(AVERAGE(C20:AO20),"Нет оценок") -> Нет оценок | AQ20: =COUNTIF(C20:AO20,"н/у") -> 0 | AR20: =COUNTIF(C20:AO20,"н") -> 2
A21: 17. | B21: Руфуллаев Ибрагим Фуадович | D21: 3 | G21: н | H21: н | I21: 2 | AP21: =IFERROR(AVERAGE(C21:AO21),"Нет оценок") -> 2.5 | AQ21: =COUNTIF(C21:AO21,"н/у") -> 0 | AR21: =COUNTIF(C21:AO21,"н") -> 2
A22: 18. | B22: Сарычев Данила Андреевич | D22: 5 | G22: н | H22: н/у | AP22: =IFERROR(AVERAGE(C22:AO22),"Нет оценок") -> 5 | AQ22: =COUNTIF(C22:AO22,"н/у") -> 1 | AR22: =COUNTIF(C22:AO22,"н") -> 1
A23: 19. | B23: Сурков Кирилл Александрович | E23: н | F23: н | G23: н | H23: н | J23: н | AP23: =IFERROR(AVERAGE(C23:AO23),"Нет оценок") -> Нет оценок | AQ23: =COUNTIF(C23:AO23,"н/у") -> 0 | AR23: =COUNTIF(C23:AO23,"н") -> 5
A24: 20. | B24: Усатов Тимофей Анатольевич | D24: 5 | AP24: =IFERROR(AVERAGE(C24:AO24),"Нет оценок") -> 5 | AQ24: =COUNTIF(C24:AO24,"н/у") -> 0 | AR24: =COUNTIF(C24:AO24,"н") -> 0
A25: 21. | B25: Халитов Кирилл Родионович | C25: н | F25: н | G25: н | H25: н | J25: н | AP25: =IFERROR(AVERAGE(C25:AO25),"Нет оценок") -> Нет оценок | AQ25: =COUNTIF(C25:AO25,"н/у") -> 0 | AR25: =COUNTIF(C25:AO25,"н") -> 5
A26: 21. | B26: Хорошилов Игорь Александрович | AP26: =IFERROR(AVERAGE(C26:AO26),"Нет оценок") -> Нет оценок | AQ26: =COUNTIF(C26:AO26,"н/у") -> 0 | AR26: =COUNTIF(C26:AO26,"н") -> 0
A27: 22. | B27: Хрычев Мирон Евгеньевич | D27: 2 | H27: н | AP27: =IFERROR(AVERAGE(C27:AO27),"Нет оценок") -> 2 | AQ27: =COUNTIF(C27:AO27,"н/у") -> 0 | AR27: =COUNTIF(C27:AO27,"н") -> 1
A28: 23. | B28: Цапов Илья Валерьевич | D28: 2 | E28: н | H28: н | AP28: =IFERROR(AVERAGE(C28:AO28),"Нет оценок") -> 2 | AQ28: =COUNTIF(C28:AO28,"н/у") -> 0 | AR28: =COUNTIF(C28:AO28,"н") -> 2
A29: Дата | B29: Тема / ДЗ | AP29: =IFERROR(AVERAGE(AP5:AP28),"") -> 2.7647059 | AQ29: =SUM(AQ5:AQ28) -> 1 | AR29: =SUM(AR5:AR28) -> 42
A30: 46069 | B30: Вводная лекция | C30: л
A31: 46084 | B31: Практическая работа 1 | C31: п | P31: Л | Q31: П
A32: 46085 | B32: Практическая работа 2 | C32: п | O32: План | P32: 28 | Q32: 28
A33: 46088 | B33: Практическая работа 3 | C33: п | G33: =COUNTIF(C30:C80,"Л") -> 4 | O33: Факт | P33: =G33*2 -> 8 | Q33: =G34*2 -> 8
A34: 46093 | B34: Типы данных | C34: л | G34: =COUNTIF(C30:C80,"П") -> 4
A35: 46111 | B35: Типы данных | C35: л
A36: 46116 | B36: Арифметика | C36: л
A37: 46119 | C37: п

Sheet Псих.общ
A1: Наименование предмета | C1: Психология общения
A2: ФИО преподавателя | C2: Малова Мария Станиславовна
A3: ИСиП 24/2 | B3: Месяц | C3: 1 | D3: 2 | E3: 2 | F3: 2 | G3: 2 | H3: 2 | I3: 2 | J3: 2 | K3: 3 | L3: 4 | M3: 4 | BV3: 4 сем | BX3: Пропуски
B4: Число | C4: 29 | D4: 2 | E4: 2 | F4: 12 | G4: 16 | H4: 17 | I4: 18 | J4: 19 | K4: 7 | L4: 2 | M4: 4 | BV4: Зачет | BW4: Средний балл | BX4: Уваж. | BY4: Неуваж.
A5: 1. | B5: Адилбеков Бектур | D5: н | E5: н | I5: н | J5: н | K5: н | L5: н | M5: н | BW5: =IFERROR(AVERAGE(C5:BV5),"Нет оценок") -> Нет оценок | BX5: =COUNTIF(C5:BV5,"н/у") -> 0 | BY5: =COUNTIF(C5:BV5,"н") -> 7
A6: 2. | B6: Ахметов Артём Рамилевич | C6: н | G6: н | I6: н | J6: н | K6: 4 | M6: + | BW6: =IFERROR(AVERAGE(C6:BV6),"Нет оценок") -> 4 | BX6: =COUNTIF(C6:BV6,"н/у") -> 0 | BY6: =COUNTIF(C6:BV6,"н") -> 4
A7: 3. | B7: Бараников Владислав Михайлович | E7: 4 | H7: 5 | K7: 4 | M7: 4 | BW7: =IFERROR(AVERAGE(C7:BV7),"Нет оценок") -> 4.25 | BX7: =COUNTIF(C7:BV7,"н/у") -> 0 | BY7: =COUNTIF(C7:BV7,"н") -> 0
A8: 4. | B8: Борсук Артём Дмитриевич | H8: 4 | K8: 3 | M8: - | BW8: =IFERROR(AVERAGE(C8:BV8),"Нет оценок") -> 3.5 | BX8: =COUNTIF(C8:BV8,"н/у") -> 0 | BY8: =COUNTIF(C8:BV8,"н") -> 0
A9: 5. | B9: Гильманов Ильназ Максимович | I9: 3 | K9: н | L9: н | M9: - | BW9: =IFERROR(AVERAGE(C9:BV9),"Нет оценок") -> 3 | BX9: =COUNTIF(C9:BV9,"н/у") -> 0 | BY9: =COUNTIF(C9:BV9,"н") -> 2
A10: 6. | B10: Говтва Илья Денисович | E10: 4 | H10: 5 | K10: 4 | M10: + | BW10: =IFERROR(AVERAGE(C10:BV10),"Нет оценок") -> 4.3333333 | BX10: =COUNTIF(C10:BV10,"н/у") -> 0 | BY10: =COUNTIF(C10:BV10,"н") -> 0
A11: 7. | B11: Горшков Владислав Васильевич | H11: 4 | K11: + | M11: н | BW11: =IFERROR(AVERAGE(C11:BV11),"Нет оценок") -> 4 | BX11: =COUNTIF(C11:BV11,"н/у") -> 0 | BY11: =COUNTIF(C11:BV11,"н") -> 1
A12: 8. | B12: Гришко Илья Алексеевич | E12: 4 | I12: 4 | K12: 3 | M12: + | BW12: =IFERROR(AVERAGE(C12:BV12),"Нет оценок") -> 3.6666667 | BX12: =COUNTIF(C12:BV12,"н/у") -> 0 | BY12: =COUNTIF(C12:BV12,"н") -> 0
A13: 9. | B13: Катков Константин Александрович | D13: н | E13: н | G13: н | H13: 4 | K13: н | L13: н | BW13: =IFERROR(AVERAGE(C13:BV13),"Нет оценок") -> 4 | BX13: =COUNTIF(C13:BV13,"н/у") -> 0 | BY13: =COUNTIF(C13:BV13,"н") -> 5
A14: 10. | B14: Корнеев Андрей Александрович | I14: 4 | K14: 4 | L14: н | BW14: =IFERROR(AVERAGE(C14:BV14),"Нет оценок") -> 4 | BX14: =COUNTIF(C14:BV14,"н/у") -> 0 | BY14: =COUNTIF(C14:BV14,"н") -> 1
A15: 11. | B15: Макаров Максим Алексеевич | F15: 5 | H15: 4 | K15: 4 | M15: + | BW15: =IFERROR(AVERAGE(C15:BV15),"Нет оценок") -> 4.3333333 | BX15: =COUNTIF(C15:BV15,"н/у") -> 0 | BY15: =COUNTIF(C15:BV15,"н") -> 0
A16: 13. | B16: Муллагалиев Вадим Радмилович | C16: н | H16: н | I16: 3 | J16: н | K16: 4 | L16: н | M16: - | BW16: =IFERROR(AVERAGE(C16:BV16),"Нет оценок") -> 3.5 | BX16: =COUNTIF(C16:BV16,"н/у") -> 0 | BY16: =COUNTIF(C16:BV16,"н") -> 4
A17: 12. | B17: Натфуллин Камиль Данисович | F17: н | G17: н | H17: н | I17: н | K17: + | L17: н | M17: н | BW17: =IFERROR(AVERAGE(C17:BV17),"Нет оценок") -> Нет оценок | BX17: =COUNTIF(C17:BV17,"н/у") -> 0 | BY17: =COUNTIF(C17:BV17,"н") -> 6
A18: 14. | B18: Носков Ярослав Евгеньевич | F18: н | I18: н | J18: н | K18: 4 | M18: + | BW18: =IFERROR(AVERAGE(C18:BV18),"Нет оценок") -> 4 | BX18: =COUNTIF(C18:BV18,"н/у") -> 0 | BY18: =COUNTIF(C18:BV18,"н") -> 3
A19: 15. | B19: Осыка Владислав Сергеевич | G19: н | I19: н | J19: н | K19: + | M19: + | BW19: =IFERROR(AVERAGE(C19:BV19),"Нет оценок") -> Нет оценок | BX19: =COUNTIF(C19:BV19,"н/у") -> 0 | BY19: =COUNTIF(C19:BV19,"н") -> 3
A20: 16. | B20: Романов Михаил Васильевич | F20: н | H20: 4 | K20: 5 | L20: н | M20: н | BW20: =IFERROR(AVERAGE(C20:BV20),"Нет оценок") -> 4.5 | BX20: =COUNTIF(C20:BV20,"н/у") -> 0 | BY20: =COUNTIF(C20:BV20,"н") -> 3
A21: 17. | B21: Руфуллаев Ибрагим Фуадович | F21: н | G21: н | H21: 4 | J21: н | K21: 4 | L21: н | M21: н | BW21: =IFERROR(AVERAGE(C21:BV21),"Нет оценок") -> 4 | BX21: =COUNTIF(C21:BV21,"н/у") -> 0 | BY21: =COUNTIF(C21:BV21,"н") -> 5
A22: 18. | B22: Сарычев Данила Андреевич | E22: 4 | F22: н/отр | H22: 5 | K22: 4 | M22: + | BW22: =IFERROR(AVERAGE(C22:BV22),"Нет оценок") -> 4.3333333 | BX22: =COUNTIF(C22:BV22,"н/у") -> 0 | BY22: =COUNTIF(C22:BV22,"н") -> 0
A23: 19. | B23: Сурков Кирилл Александрович | C23: н | F23: н | H23: н | I23: 4 | J23: н | K23: н | L23: н/у | M23: + | BW23: =IFERROR(AVERAGE(C23:BV23),"Нет оценок") -> 4 | BX23: =COUNTIF(C23:BV23,"н/у") -> 1 | BY23: =COUNTIF(C23:BV23,"н") -> 5
A24: 20. | B24: Усатов Тимофей Анатольевич | E24: 4 | H24: 5 | K24: 4 | M24: 4 | BW24: =IFERROR(AVERAGE(C24:BV24),"Нет оценок") -> 4.25 | BX24: =COUNTIF(C24:BV24,"н/у") -> 0 | BY24: =COUNTIF(C24:BV24,"н") -> 0
A25: 21. | B25: Халитов Кирилл Родионович | C25: н | G25: н | H25: н | I25: н | J25: н | K25: н | BW25: =IFERROR(AVERAGE(C25:BV25),"Нет оценок") -> Нет оценок | BX25: =COUNTIF(C25:BV25,"н/у") -> 0 | BY25: =COUNTIF(C25:BV25,"н") -> 6
A26: 21. | B26: Хорошилов Игорь Александрович | BW26: =IFERROR(AVERAGE(C26:BV26),"Нет оценок") -> Нет оценок | BX26: =COUNTIF(C26:BV26,"н/у") -> 0 | BY26: =COUNTIF(C26:BV26,"н") -> 0
A27: 22. | B27: Хрычев Мирон Евгеньевич | C27: н | F27: н | G27: н | I27: 4 | K27: + | L27: н | BW27: =IFERROR(AVERAGE(C27:BV27),"Нет оценок") -> 4 | BX27: =COUNTIF(C27:BV27,"н/у") -> 0 | BY27: =COUNTIF(C27:BV27,"н") -> 4
A28: 23. | B28: Цапов Илья Валерьевич | F28: н | H28: н | I28: н | K28: + | L28: н | BW28: =IFERROR(AVERAGE(C28:BV28),"Нет оценок") -> Нет оценок | BX28: =COUNTIF(C28:BV28,"н/у") -> 0 | BY28: =COUNTIF(C28:BV28,"н") -> 4
A29: Дата | B29: Тема / ДЗ | BW29: =IFERROR(AVERAGE(BW5:BW28),"") -> 3.9814815 | BX29: =SUM(BX5:BX28) -> 1 | BY29: =SUM(BY5:BY28) -> 63
A30: ВНИМАНИЕ! ДЛЯ ОТРАБОТКИ Н (неуваж.) ПРИНЕСТИ КОНСПЕКТ ПО ТЕМЕ ПАРЫ И ЗНАТЬ УСТНЫЙ ПЕРЕСКАЗ ТЕЗИСНО!
A31: 29.01. | B31: Теории формировании и развития личности (Усатов, Говтва, Бараников, Руфуллаев, Осыка, Сарычев, Гришко, Цапов)
A32: 29.01. | B32: Тема: Психология личности и общения
A33: 02.02. | B33: Тема: Типология характеров,Конституционные теории, Акцентуальные теории, Социальная типология, Социальные характеристики личности.
A34: 02.02. | B34: ДЗ: Доклады по теме 1
A35: 12.02. | B35: Общение как коммуникация. Базовые понятия по теме общение как коммуникация
A36: 16.02. | B36: Коммуникативная сторона общения и барьеры коммуникаций.
A37: 17.02. | B37: Практическая отработка. Доклады по теме 2
A38: 18.02. | B38: Практическая отработка. Доклады по теме 2
A39: 19.02. | B39: Самоорганизация личности.
A40: 19.02. ДЗ: ДЗ: Заполнить таблицу "Я реальное" и "Я идеальное".
A41: 07.03. | B41: Обсуждение дз, доработка по теме самоорганизация.

Sheet Тех.разра.БД
A1: Наименование предмета | C1: Технология разработки и защиты баз данных
A2: ФИО преподавателя
A3: ИСиП 24/2 | B3: Месяц | AB3: Пропуски
B4: Число | AA4: Средний балл | AB4: Уваж. | AC4: Неуваж.
A5: 1. | B5: Ахметов Артём Рамилевич | AA5: =IFERROR(AVERAGE(C5:Z5),"Нет оценок") -> Нет оценок | AB5: =COUNTIF(C5:Z5,"н/у") -> 0 | AC5: =COUNTIF(C5:Z5,"н") -> 0
A6: 2. | B6: Адилбеков Бектур | AA6: =IFERROR(AVERAGE(C6:Z6),"Нет оценок") -> Нет оценок | AB6: =COUNTIF(C6:Z6,"н/у") -> 0 | AC6: =COUNTIF(C6:Z6,"н") -> 0
A7: 3. | B7: Бараников Владислав Михайлович | AA7: =IFERROR(AVERAGE(C7:Z7),"Нет оценок") -> Нет оценок | AB7: =COUNTIF(C7:Z7,"н/у") -> 0 | AC7: =COUNTIF(C7:Z7,"н") -> 0
A8: 4. | B8: Борсук Артём Дмитриевич | AA8: =IFERROR(AVERAGE(C8:Z8),"Нет оценок") -> Нет оценок | AB8: =COUNTIF(C8:Z8,"н/у") -> 0 | AC8: =COUNTIF(C8:Z8,"н") -> 0
A9: 5. | B9: Гильманов Ильназ Максимович | AA9: =IFERROR(AVERAGE(C9:Z9),"Нет оценок") -> Нет оценок | AB9: =COUNTIF(C9:Z9,"н/у") -> 0 | AC9: =COUNTIF(C9:Z9,"н") -> 0
A10: 6. | B10: Говтва Илья Денисович | AA10: =IFERROR(AVERAGE(C10:Z10),"Нет оценок") -> Нет оценок | AB10: =COUNTIF(C10:Z10,"н/у") -> 0 | AC10: =COUNTIF(C10:Z10,"н") -> 0
A11: 7. | B11: Горшков Владислав Васильевич | AA11: =IFERROR(AVERAGE(C11:Z11),"Нет оценок") -> Нет оценок | AB11: =COUNTIF(C11:Z11,"н/у") -> 0 | AC11: =COUNTIF(C11:Z11,"н") -> 0
A12: 8. | B12: Гришко Илья Алексеевич | AA12: =IFERROR(AVERAGE(C12:Z12),"Нет оценок") -> Нет оценок | AB12: =COUNTIF(C12:Z12,"н/у") -> 0 | AC12: =COUNTIF(C12:Z12,"н") -> 0
A13: 9. | B13: Катков Константин Александрович | AA13: =IFERROR(AVERAGE(C13:Z13),"Нет оценок") -> Нет оценок | AB13: =COUNTIF(C13:Z13,"н/у") -> 0 | AC13: =COUNTIF(C13:Z13,"н") -> 0
A14: 10. | B14: Корнеев Андрей Александрович | AA14: =IFERROR(AVERAGE(C14:Z14),"Нет оценок") -> Нет оценок | AB14: =COUNTIF(C14:Z14,"н/у") -> 0 | AC14: =COUNTIF(C14:Z14,"н") -> 0
A15: 11. | B15: Макаров Максим Алексеевич | AA15: =IFERROR(AVERAGE(C15:Z15),"Нет оценок") -> Нет оценок | AB15: =COUNTIF(C15:Z15,"н/у") -> 0 | AC15: =COUNTIF(C15:Z15,"н") -> 0
A16: 13. | B16: Муллагалиев Вадим Радмилович | AA16: =IFERROR(AVERAGE(C16:Z16),"Нет оценок") -> Нет оценок | AB16: =COUNTIF(C16:Z16,"н/у") -> 0 | AC16: =COUNTIF(C16:Z16,"н") -> 0
... A28: 23. | B28: Цапов Илья Валерьевич | AA28: =IFERROR(AVERAGE(C28:Z28),"Нет оценок") -> Нет оценок | AB28: =COUNTIF(C28:Z28,"н/у") -> 0 | AC28: =COUNTIF(C28:Z28,"н") -> 0
A29: Дата | B29: Тема / ДЗ | AA29: =IFERROR(AVERAGE(AA5:AA28),"") | AB29: =SUM(AB5:AB28) -> 0 | AC29: =SUM(AC5:AC28) -> 0

Sheet Проектирование и дизайн ИС
A1: Наименование предмета | C1: Проектирование и дизайн информационных систем
A2: ФИО преподавателя | C2: Долгова Виктория Терентьевна
A3: ИСиП 24/2 | B3: Месяц | C3: Cентябрь | M3: Октябрь | P3: Январь | U3: Февраль | AB3: Март | AE3: Апрель | AO3: 4 сем | AQ3: Пропуски
B4: Число | C4: 3 | D4: 3 | E4: 9 | F4: 10 | G4: 12 | H4: 15 | I4: 18 | J4: 22 | K4: 22 | L4: 26 | M4: 6 | N4: 6 | O4: 10 | P4: 14 | Q4: 16 | R4: 19 | S4: 23 | T4: 28 | U4: 6 | V4: 9 | W4: 11 | X4: 14 | Y4: 25 | Z4: 26 | AA4: 27 | AB4: 6 | AC4: 13 | AD4: 30 | AE4: 1 | AF4: 10 | AG4: 11 | AO4: ДЗ | AP4: Средний балл | AQ4: Уваж. | AR4: Неуваж.
A5: 1. | B5: Адилбеков Бектур | E5: н | F5: н | G5: н | I5: 2 | J5: н | K5: н | L5: н | O5: н | R5: 5 | S5: н | U5: 5 | V5: . | W5: + | X5: н | Y5: н | Z5: н | AA5: н | AB5: н | AC5: н | AD5: н | AP5: =IFERROR(AVERAGE(C5:AO5),"Нет оценок") -> 4 | AQ5: =COUNTIF(C5:AO5,"н/у") -> 0 | AR5: =COUNTIF(C5:AO5,"н") -> 15
A6: 2. | B6: Ахметов Артём Рамилевич | I6: 4 | J6: 5 | K6: 2 | R6: 5 | S6: 5 | T6: 4 | U6: 4 | V6: 5 | W6: н | X6: 2 | Z6: 5 | AA6: . | AC6: . | AD6: 5 | AP6: =IFERROR(AVERAGE(C6:AO6),"Нет оценок") -> 4.1818182 | AQ6: =COUNTIF(C6:AO6,"н/у") -> 0 | AR6: =COUNTIF(C6:AO6,"н") -> 1
A7: 3. | B7: Бараников Владислав Михайлович | I7: 5 | J7: 5 | K7: 5 | L7: 5 | R7: 5 | S7: 5 | T7: 5 | U7: 5 | V7: 4 | W7: + | X7: н | Z7: 5 | AA7: 5 | AB7: 5 | AC7: 4 | AD7: 4 | AP7: =IFERROR(AVERAGE(C7:AO7),"Нет оценок") -> 4.7857143 | AQ7: =COUNTIF(C7:AO7,"н/у") -> 0 | AR7: =COUNTIF(C7:AO7,"н") -> 1
A8: 4. | B8: Борсук Артём Дмитриевич | F8: н | H8: н | I8: 5 | J8: 3 | K8: н | R8: 4 | S8: 5 | T8: 3 | U8: 3 | V8: 5 | W8: + | X8: н | Z8: 5 | AA8: 5 | AB8: 5 | AC8: н | AD8: 4 | AP8: =IFERROR(AVERAGE(C8:AO8),"Нет оценок") -> 4.2727273 | AQ8: =COUNTIF(C8:AO8,"н/у") -> 0 | AR8: =COUNTIF(C8:AO8,"н") -> 5
A9: 5. | B9: Гильманов Ильназ Максимович | I9: 4 | J9: н | K9: н | L9: 5 | R9: 5 | S9: 5 | T9: 5 | U9: 5 | V9: 5 | W9: + | X9: н | Z9: 5 | AA9: 5 | AB9: 4 | AC9: . | AD9: 3 | AP9: =IFERROR(AVERAGE(C9:AO9),"Нет оценок") -> 4.6363636 | AQ9: =COUNTIF(C9:AO9,"н/у") -> 0 | AR9: =COUNTIF(C9:AO9,"н") -> 3
A10: 6. | B10: Говтва Илья Денисович | I10: 5 | J10: 5 | K10: 5 | L10: 5 | R10: 5 | S10: 5 | T10: 5 | U10: 5 | V10: 5 | W10: + | X10: + | Z10: 5 | AA10: 5 | AB10: 5 | AC10: 5 | AD10: 4 | AP10: =IFERROR(AVERAGE(C10:AO10),"Нет оценок") -> 4.9285714 | AQ10: =COUNTIF(C10:AO10,"н/у") -> 0 | AR10: =COUNTIF(C10:AO10,"н") -> 0
A11: 7. | B11: Горшков Владислав Васильевич | G11: н | I11: 4 | J11: 4 | K11: 2 | L11: н/у | R11: 4 | S11: 5 | T11: н | U11: 5 | V11: 5 | W11: н | X11: 2 | Z11: 5 | AA11: . | AC11: . | AD11: 4 | AP11: =IFERROR(AVERAGE(C11:AO11),"Нет оценок") -> 4 | AQ11: =COUNTIF(C11:AO11,"н/у") -> 1 | AR11: =COUNTIF(C11:AO11,"н") -> 3
A12: 8. | B12: Гришко Илья Алексеевич | D12: н | F12: н | G12: н | H12: н | I12: 3 | J12: н | K12: н | P12: н | R12: 5 | S12: 5 | T12: 4 | U12: 5 | V12: 5 | W12: + | X12: + | Z12: . | AA12: . | AC12: . | AD12: 5 | AP12: =IFERROR(AVERAGE(C12:AO12),"Нет оценок") -> 4.5714286 | AQ12: =COUNTIF(C12:AO12,"н/у") -> 0 | AR12: =COUNTIF(C12:AO12,"н") -> 7
A13: 9. | B13: Катков Константин Александрович | E13: н | I13: 2 | J13: 2 | K13: 2 | L13: н | R13: 3 | S13: н | T13: 3 | U13: 2 | V13: 3 | W13: н | X13: 2 | Y13: н | Z13: . | AA13: . | AB13: н | AC13: н | AD13: н | AE13: н | AP13: =IFERROR(AVERAGE(C13:AO13),"Нет оценок") -> 2.375 | AQ13: =COUNTIF(C13:AO13,"н/у") -> 0 | AR13: =COUNTIF(C13:AO13,"н") -> 9
A14: 10. | B14: Корнеев Андрей Александрович | I14: 5 | J14: 3 | K14: 2 | L14: 4 | M14: н | N14: н | R14: 4 | S14: 5 | T14: 3 | U14: 2 | V14: 5 | W14: + | X14: + | Z14: 5 | AA14: 5 | AC14: . | AD14: н/у | AP14: =IFERROR(AVERAGE(C14:AO14),"Нет оценок") -> 3.9090909 | AQ14: =COUNTIF(C14:AO14,"н/у") -> 1 | AR14: =COUNTIF(C14:AO14,"н") -> 2
A15: 11. | B15: Макаров Максим Алексеевич | I15: 5 | J15: н/у | K15: н/у | L15: 5 | R15: 4 | S15: 4 | T15: 5 | U15: 5 | V15: 5 | W15: + | X15: + | Z15: 3 | AA15: 5 | AB15: н | AC15: . | AD15: 4 | AP15: =IFERROR(AVERAGE(C15:AO15),"Нет оценок") -> 4.5 | AQ15: =COUNTIF(C15:AO15,"н/у") -> 2 | AR15: =COUNTIF(C15:AO15,"н") -> 1
A16: 13. | B16: Муллагалиев Вадим Радмилович | I16: 2 | J16: 5 | K16: 5 | L16: 5 | R16: 5 | S16: 5 | T16: 5 | U16: 3 | V16: 2 | W16: + | X16: + | Y16: н | Z16: 4 | AA16: 4 | AB16: н | AC16: . | AD16: 5 | AP16: =IFERROR(AVERAGE(C16:AO16),"Нет оценок") -> 4.1666667 | AQ16: =COUNTIF(C16:AO16,"н/у") -> 0 | AR16: =COUNTIF(C16:AO16,"н") -> 2
A17: 12. | B17: Натфуллин Камиль Данисович | E17: н | F17: н | G17: н | I17: 5 | J17: 4 | K17: 2 | L17: н | O17: н | Q17: н | R17: 4 | S17: 4 | T17: н | U17: 5 | V17: 4 | W17: + | X17: + | Z17: н | AA17: н | AB17: н | AC17: н | AD17: н | AP17: =IFERROR(AVERAGE(C17:AO17),"Нет оценок") -> 4 | AQ17: =COUNTIF(C17:AO17,"н/у") -> 0 | AR17: =COUNTIF(C17:AO17,"н") -> 12
A18: 14. | B18: Носков Ярослав Евгеньевич | I18: 5 | J18: 5 | K18: 5 | L18: 5 | R18: 5 | S18: 5 | T18: 4 | U18: 5 | V18: 0 | W18: + | X18: + | Z18: 2 | AA18: 5 | AB18: 4 | AC18: . | AD18: 4 | AP18: =IFERROR(AVERAGE(C18:AO18),"Нет оценок") -> 4.1538462 | AQ18: =COUNTIF(C18:AO18,"н/у") -> 0 | AR18: =COUNTIF(C18:AO18,"н") -> 0
A19: 15. | B19: Осыка Владислав Сергеевич | I19: 5 | J19: 5 | K19: 4 | L19: 5 | R19: 4 | S19: 5 | T19: 4 | U19: 4 | V19: 5 | X19: + | Z19: 4 | AA19: 4 | AB19: 5 | AC19: 5 | AD19: 4 | AP19: =IFERROR(AVERAGE(C19:AO19),"Нет оценок") -> 4.5 | AQ19: =COUNTIF(C19:AO19,"н/у") -> 0 | AR19: =COUNTIF(C19:AO19,"н") -> 0
A20: 16. | B20: Романов Михаил Васильевич | G20: + | I20: 5 | J20: 5 | K20: 4 | L20: 5 | P20: + | R20: 4 | S20: 5 | T20: 4 | U20: 4 | V20: 4 | W20: + | X20: + | Z20: 5 | AA20: 5 | AB20: 5 | AC20: н | AD20: 5 | AP20: =IFERROR(AVERAGE(C20:AO20),"Нет оценок") -> 4.6153846 | AQ20: =COUNTIF(C20:AO20,"н/у") -> 0 | AR20: =COUNTIF(C20:AO20,"н") -> 1
A21: 17. | B21: Руфуллаев Ибрагим Фуадович | C21: н | D21: н | E21: н | I21: 2 | J21: 5 | K21: 3 | L21: 5 | Q21: н | R21: 3 | S21: 5 | T21: 4 | U21: 4 | V21: 4 | W21: 2 | X21: 2 | Y21: н | Z21: 4 | AA21: 4 | AC21: . | AD21: 4 | AP21: =IFERROR(AVERAGE(C21:AO21),"Нет оценок") -> 3.6428571 | AQ21: =COUNTIF(C21:AO21,"н/у") -> 0 | AR21: =COUNTIF(C21:AO21,"н") -> 5
A22: 18. | B22: Сарычев Данила Андреевич | C22: н | D22: н | I22: 5 | J22: н | K22: н | L22: 5 | M22: н | N22: н | O22: н | Q22: 5 | R22: 5 | S22: 5 | T22: 5 | U22: 5 | V22: 5 | W22: н | X22: н | Z22: 5 | AA22: 5 | AB22: 5 | AC22: н | AD22: н/у | AE22: н/у | AP22: =IFERROR(AVERAGE(C22:AO22),"Нет оценок") -> 5 | AQ22: =COUNTIF(C22:AO22,"н/у") -> 2 | AR22: =COUNTIF(C22:AO22,"н") -> 10
A23: 19. | B23: Сурков Кирилл Александрович | H23: н | I23: 5 | J23: 3 | K23: н/у | L23: н/у | O23: н | Q23: н | R23: 4 | S23: 5 | T23: 4 | U23: 5 | V23: 4 | W23: + | X23: + | Z23: 5 | AA23: 5 | AB23: н | AC23: н | AD23: н | AP23: =IFERROR(AVERAGE(C23:AO23),"Нет оценок") -> 4.4444444 | AQ23: =COUNTIF(C23:AO23,"н/у") -> 2 | AR23: =COUNTIF(C23:AO23,"н") -> 6
A24: 20. | B24: Усатов Тимофей Анатольевич | I24: 5 | J24: 5 | K24: 5 | L24: 5 | R24: 5 | S24: 5 | T24: 5 | U24: 5 | V24: 5 | W24: + | X24: + | Z24: 5 | AA24: 5 | AB24: 4 | AC24: 5 | AD24: 4 | AE24: 5 | AP24: =IFERROR(AVERAGE(C24:AO24),"Нет оценок") -> 4.8666667 | AQ24: =COUNTIF(C24:AO24,"н/у") -> 0 | AR24: =COUNTIF(C24:AO24,"н") -> 0
A25: 21. | B25: Халитов Кирилл Родионович | E25: н | I25: 5 | J25: н | K25: н | L25: н/у | N25: н/у | O25: н | P25: н | Q25: н | R25: 5 | S25: н | T25: н | U25: 5 | V25: 4 | W25: + | X25: н | Y25: н | Z25: 5 | AA25: 5 | AB25: н | AC25: . | AD25: н | AE25: н | AP25: =IFERROR(AVERAGE(C25:AO25),"Нет оценок") -> 4.8333333 | AQ25: =COUNTIF(C25:AO25,"н/у") -> 2 | AR25: =COUNTIF(C25:AO25,"н") -> 13
A26: 21. | B26: Хорошилов Игорь Александрович | AP26: =IFERROR(AVERAGE(C26:AO26),"Нет оценок") -> Нет оценок | AQ26: =COUNTIF(C26:AO26,"н/у") -> 0 | AR26: =COUNTIF(C26:AO26,"н") -> 0
A27: 22. | B27: Хрычев Мирон Евгеньевич | H27: н | I27: 2 | J27: 3 | K27: 2 | L27: 5 | R27: 4 | S27: 5 | T27: 3 | U27: 5 | V27: 5 | W27: 2 | X27: 2 | Y27: н | Z27: 5 | AA27: 4 | AB27: 3 | AC27: . | AD27: 3 | AP27: =IFERROR(AVERAGE(C27:AO27),"Нет оценок") -> 3.5333333 | AQ27: =COUNTIF(C27:AO27,"н/у") -> 0 | AR27: =COUNTIF(C27:AO27,"н") -> 2
A28: 23. | B28: Цапов Илья Валерьевич | E28: н | I28: 4 | J28: 5 | K28: 5 | L28: н | N28: н | O28: н/у | R28: 4 | S28: 5 | T28: 4 | U28: 5 | V28: н | W28: + | X28: н | Z28: н | AA28: . | AB28: н | AC28: . | AD28: н | AE28: н | AP28: =IFERROR(AVERAGE(C28:AO28),"Нет оценок") -> 4.5714286 | AQ28: =COUNTIF(C28:AO28,"н/у") -> 1 | AR28: =COUNTIF(C28:AO28,"н") -> 9
A29: Дата | B29: Тема / ДЗ | AP29: =IFERROR(AVERAGE(AP5:AP28),"") -> 4.2821163 | AQ29: =SUM(AQ5:AQ28) -> 11 | AR29: =SUM(AR5:AR28) -> 107
A30: 45903 | B30: Л1. Основные понятия и определения ИС. | C30: Л
A31: 45903 | B31: Л2. Основные понятия и определения ИС. | C31: Л | G31: ПЛАН | K31: ФАКТ | O31: ОСТАЛОСЬ
A32: 45909 | B32: Л3. Организация и методы сбора информации. | C32: Л | G32: Л | H32: 46 | I32: ЧАСОВ В ГОД | K32: Л | L32: =COUNTIF(C30:C103,"Л")*2 -> 34 | M32: ПРОВЕДЕНО ЧАСОВ | O32: Л | P32: =H32-L32 -> 12 | Q32: ЧАСОВ | R32: =P32/2 -> 6 | S32: ПАР
A33: 45910 | B33: Л4. Постановка задачи обработки данных. | C33: Л | G33: ПЗ | H33: 42 | K33: ПЗ | L33: =COUNTIF(C30:C103,"ПЗ")*2 -> 22 | O33: ПЗ | P33: =H33-L33 -> 20 | R33: =P33/2 -> 10
A34: 45912 | B34: Л5. Основные модели построения информационной системы. | C34: Л | G34: К | H34: 4 | K34: К | L34: =COUNTIF(C30:C103,"К")*2 -> 2 | O34: К | P34: =H34-L34 -> 2 | R34: =P34/2 -> 1
A35: 45915 | B35: Л6. Основные модели построения информационной системы. | C35: Л | O35: ВСЕГО | R35: =SUM(R32:R34) -> 17
A36: 45918 | B36: ПР1. Знакомство с элементами Figma. Создание прототипа. | C36: ПЗ
A37: 45922 | B37: ПР2. Работа с векторными формами. | C37: ПЗ
A38: 45922 | B38: ПР3. Работа с текстом и изображениями. | C38: ПЗ
A39: 45926 | B39: ПР4. Презентации. | C39: ПЗ
A40: 45936 | B40: Л7. Сервис-ориентированная архитектура (SOA) | C40: Л
A41: 45936 | B41: ПР5. Создание лендинга. | C41: ПЗ
A42: 45940 | B42: ПР6. Создание лендинга. | C42: ПЗ
A43: 46036 | B43: Л8. Методы и средства проектирования ИС. | C43: Л
A44: 46038 | B44: Л9. Принципы построения модели IDEF0. | C44: Л
A45: 46041 | B45: ПР7. 1. Анализ предметной области методом контент-анализа. | C45: ПЗ
A46: 46045 | B46: КОНТРОЛЬНАЯ РАБОТА | C46: К
A47: 46050 | B47: Л10. Диаграммы IDEF0: декомпозиция, деревья узлов и FEO. | C47: Л
... A58: 46113 | B58: ПР11. 8. Оценка экономической эффективности информационной системы. | C58: ПЗ

Sheet Осн.фин.грам.и предприн.
A1: Наименование предмета | C1: Основы финансовой грамотности и предпринимательства
A2: ФИО преподавателя | C2: Семенова Татьяна Андреевна
A3: ИСиП 24/2 | B3: Месяц | C3: 9 | D3: 9 | E3: 9 | F3: 9 | G3: 9 | H3: 9 | I3: 9 | J3: 10 | K3: 10 | L3: 10 | M3: 10 | N3: 11 | O3: 11 | P3: 11 | Q3: 11 | R3: 11 | S3: 11 | T3: 11 | U3: 12 | V3: 12 | W3: 12 | X3: 12 | Y3: 12 | Z3: 12 | AA3: 12 | AC3: Пропуски
B4: Число | C4: 4 | D4: 5 | E4: 6 | F4: 6 | G4: 15 | H4: 19 | I4: 22 | J4: 6 | K4: 10 | L4: 14 | M4: 23 | N4: 1 | O4: 12 | P4: 13 | Q4: 26 | R4: 27 | S4: 29 | T4: 29 | U4: 1 | V4: 3 | W4: 8 | X4: 9 | Y4: 10 | Z4: 11 | AA4: 22 | AB4: Средний балл | AC4: Уваж. | AD4: Неуваж.
A5: 1. | B5: Адилбеков Бектур | G5: 5 | K5: 5 | L5: 5 | O5: 5 | P5: 5 | R5: 5 | T5: 4 | U5: 5 | AA5: 4 | AB5: =IFERROR(AVERAGE(C5:Z5),"Нет оценок") -> 4.875 | AC5: =COUNTIF(C5:Z5,"н/у") -> 0 | AD5: =COUNTIF(C5:Z5,"н") -> 0
A6: 2. | B6: Ахметов Артём Рамилевич | G6: 5 | K6: 3 | O6: 5 | P6: 4 | R6: 4 | T6: 5 | U6: 4 | Y6: 4 | AA6: 4 | AB6: =IFERROR(AVERAGE(C6:Z6),"Нет оценок") -> 4.25 | AC6: =COUNTIF(C6:Z6,"н/у") -> 0 | AD6: =COUNTIF(C6:Z6,"н") -> 0
A7: 3. | B7: Бараников Владислав Михайлович | G7: 4 | K7: 4 | L7: 5 | M7: 5 | O7: 5 | P7: 5 | R7: 5 | U7: 5 | Y7: 4 | AA7: 4 | AB7: =IFERROR(AVERAGE(C7:Z7),"Нет оценок") -> 4.6666667 | AC7: =COUNTIF(C7:Z7,"н/у") -> 0 | AD7: =COUNTIF(C7:Z7,"н") -> 0
A8: 4. | B8: Борсук Артём Дмитриевич | P8: 3 | R8: 4 | T8: 5 | U8: 3 | Y8: 5 | AA8: 4 | AB8: =IFERROR(AVERAGE(C8:Z8),"Нет оценок") -> 4 | AC8: =COUNTIF(C8:Z8,"н/у") -> 0 | AD8: =COUNTIF(C8:Z8,"н") -> 0
A9: 5. | B9: Гильманов Ильназ Максимович | G9: 4 | L9: 5 | M9: 5 | P9: 5 | R9: 5 | T9: 5 | U9: 5 | Y9: 5 | AA9: 4 | AB9: =IFERROR(AVERAGE(C9:Z9),"Нет оценок") -> 4.875 | AC9: =COUNTIF(C9:Z9,"н/у") -> 0 | AD9: =COUNTIF(C9:Z9,"н") -> 0
A10: 6. | B10: Говтва Илья Денисович | G10: 4 | K10: 5 | L10: 5 | M10: 5 | O10: 5 | P10: 4 | R10: 5 | T10: 5 | U10: 5 | Y10: 5 | AA10: 4 | AB10: =IFERROR(AVERAGE(C10:Z10),"Нет оценок") -> 4.8 | AC10: =COUNTIF(C10:Z10,"н/у") -> 0 | AD10: =COUNTIF(C10:Z10,"н") -> 0
A11: 7. | B11: Горшков Владислав Васильевич | G11: 5 | K11: 3 | M11: 5 | R11: 4 | T11: 5 | U11: 4 | Y11: 4 | AA11: 4 | AB11: =IFERROR(AVERAGE(C11:Z11),"Нет оценок") -> 4.2857143 | AC11: =COUNTIF(C11:Z11,"н/у") -> 0 | AD11: =COUNTIF(C11:Z11,"н") -> 0
A12: 8. | B12: Гришко Илья Алексеевич | K12: 5 | L12: 5 | M12: 4 | P12: 3 | R12: 5 | T12: 5 | U12: 4 | Y12: 4 | AA12: 5 | AB12: =IFERROR(AVERAGE(C12:Z12),"Нет оценок") -> 4.375 | AC12: =COUNTIF(C12:Z12,"н/у") -> 0 | AD12: =COUNTIF(C12:Z12,"н") -> 0
A13: 9. | B13: Катков Константин Александрович | G13: 4 | U13: 3 | Y13: 2 | AA13: 3 | AB13: =IFERROR(AVERAGE(C13:Z13),"Нет оценок") -> 3 | AC13: =COUNTIF(C13:Z13,"н/у") -> 0 | AD13: =COUNTIF(C13:Z13,"н") -> 0
A14: 10. | B14: Корнеев Андрей Александрович | G14: 3 | K14: 2 | O14: 5 | P14: 3 | R14: 5 | T14: 4 | U14: 3 | Y14: 4 | AA14: 4 | AB14: =IFERROR(AVERAGE(C14:Z14),"Нет оценок") -> 3.625 | AC14: =COUNTIF(C14:Z14,"н/у") -> 0 | AD14: =COUNTIF(C14:Z14,"н") -> 0
A15: 11. | B15: Макаров Максим Алексеевич | G15: 3 | K15: 4 | L15: 5 | O15: 5 | P15: 4 | R15: 5 | T15: 5 | U15: 3 | Y15: 5 | AA15: 4 | AB15: =IFERROR(AVERAGE(C15:Z15),"Нет оценок") -> 4.3333333 | AC15: =COUNTIF(C15:Z15,"н/у") -> 0 | AD15: =COUNTIF(C15:Z15,"н") -> 0
A16: 13. | B16: Муллагалиев Вадим Радмилович | G16: 4 | K16: 4 | L16: 5 | M16: 5 | O16: 5 | P16: 5 | R16: 5 | T16: 5 | U16: 5 | Y16: 5 | AA16: 4 | AB16: =IFERROR(AVERAGE(C16:Z16),"Нет оценок") -> 4.8 | AC16: =COUNTIF(C16:Z16,"н/у") -> 0 | AD16: =COUNTIF(C16:Z16,"н") -> 0
A17: 12. | B17: Натфуллин Камиль Данисович | G17: 5 | T17: 5 | U17: 4 | Y17: 4 | AA17: 4 | AB17: =IFERROR(AVERAGE(C17:Z17),"Нет оценок") -> 4.5 | AC17: =COUNTIF(C17:Z17,"н/у") -> 0 | AD17: =COUNTIF(C17:Z17,"н") -> 0
A18: 14. | B18: Носков Ярослав Евгеньевич | G18: 4 | K18: 4 | L18: 5 | M18: 3 | O18: 5 | P18: 4 | R18: 5 | T18: 4 | U18: 5 | Y18: 5 | AA18: 4 | AB18: =IFERROR(AVERAGE(C18:Z18),"Нет оценок") -> 4.4 | AC18: =COUNTIF(C18:Z18,"н/у") -> 0 | AD18: =COUNTIF(C18:Z18,"н") -> 0
A19: 15. | B19: Осыка Владислав Сергеевич | G19: 4 | K19: 4 | L19: 5 | M19: 5 | O19: 5 | P19: 5 | R19: 5 | T19: 5 | U19: 5 | Y19: 5 | AA19: 4 | AB19: =IFERROR(AVERAGE(C19:Z19),"Нет оценок") -> 4.8 | AC19: =COUNTIF(C19:Z19,"н/у") -> 0 | AD19: =COUNTIF(C19:Z19,"н") -> 0
A20: 16. | B20: Романов Михаил Васильевич | G20: 3 | K20: 4 | L20: 5 | M20: 5 | O20: 5 | P20: 5 | R20: 5 | T20: 5 | U20: 3 | Y20: 4 | AA20: 5 | AB20: =IFERROR(AVERAGE(C20:Z20),"Нет оценок") -> 4.4 | AC20: =COUNTIF(C20:Z20,"н/у") -> 0 | AD20: =COUNTIF(C20:Z20,"н") -> 0
A21: 17. | B21: Руфуллаев Ибрагим Фуадович | G21: 5 | K21: 4 | L21: 5 | M21: 5 | O21: 4 | P21: 5 | Q21: 2 | R21: 5 | T21: 4 | U21: 4 | Y21: 5 | AA21: 4 | AB21: =IFERROR(AVERAGE(C21:Z21),"Нет оценок") -> 4.3636364 | AC21: =COUNTIF(C21:Z21,"н/у") -> 0 | AD21: =COUNTIF(C21:Z21,"н") -> 0
A22: 18. | B22: Сарычев Данила Андреевич | G22: 4 | K22: 4 | L22: 5 | M22: 5 | O22: 5 | P22: 3 | R22: 5 | T22: 5 | U22: 5 | Y22: 5 | AA22: 4 | AB22: =IFERROR(AVERAGE(C22:Z22),"Нет оценок") -> 4.6 | AC22: =COUNTIF(C22:Z22,"н/у") -> 0 | AD22: =COUNTIF(C22:Z22,"н") -> 0
A23: 19. | B23: Сурков Кирилл Александрович | G23: 5 | K23: 4 | L23: 5 | M23: 5 | T23: 5 | AA23: 4 | AB23: =IFERROR(AVERAGE(C23:Z23),"Нет оценок") -> 4.8 | AC23: =COUNTIF(C23:Z23,"н/у") -> 0 | AD23: =COUNTIF(C23:Z23,"н") -> 0
A24: 20. | B24: Усатов Тимофей Анатольевич | G24: 4 | K24: 5 | L24: 5 | M24: 5 | O24: 5 | P24: 5 | R24: 5 | T24: 5 | U24: 4 | AA24: 4 | AB24: =IFERROR(AVERAGE(C24:Z24),"Нет оценок") -> 4.7777778 | AC24: =COUNTIF(C24:Z24,"н/у") -> 0 | AD24: =COUNTIF(C24:Z24,"н") -> 0
A25: 21. | B25: Халитов Кирилл Родионович | G25: 5 | P25: 3 | T25: 4 | Y25: 3 | AA25: 3 | AB25: =IFERROR(AVERAGE(C25:Z25),"Нет оценок") -> 3.75 | AC25: =COUNTIF(C25:Z25,"н/у") -> 0 | AD25: =COUNTIF(C25:Z25,"н") -> 0
A26: 21. | B26: Хорошилов Игорь Александрович | AB26: =IFERROR(AVERAGE(C26:Z26),"Нет оценок") -> Нет оценок | AC26: =COUNTIF(C26:Z26,"н/у") -> 0 | AD26: =COUNTIF(C26:Z26,"н") -> 0
A27: 22. | B27: Хрычев Мирон Евгеньевич | G27: 3 | K27: 2 | O27: 5 | P27: 4 | Q27: 2 | R27: 4 | T27: 5 | U27: 3 | Y27: 4 | AA27: 4 | AB27: =IFERROR(AVERAGE(C27:Z27),"Нет оценок") -> 3.5555556 | AC27: =COUNTIF(C27:Z27,"н/у") -> 0 | AD27: =COUNTIF(C27:Z27,"н") -> 0
A28: 23. | B28: Цапов Илья Валерьевич | G28: 4 | M28: 4 | O28: 5 | P28: 3 | R28: 5 | T28: 4 | Y28: 4 | AA28: 5 | AB28: =IFERROR(AVERAGE(C28:Z28),"Нет оценок") -> 4.1428571 | AC28: =COUNTIF(C28:Z28,"н/у") -> 0 | AD28: =COUNTIF(C28:Z28,"н") -> 0
A29: Дата | B29: Тема / ДЗ | AB29: =IFERROR(AVERAGE(AB6:AB28),"") -> 4.3227519 | AC29: =SUM(AC6:AC28) -> 0 | AD29: =SUM(AD6:AD28) -> 0
A30: 45904 | B30: Цели и задачи ОФГ и предпринимательства. Актуальность повышения уровня ФГ населения РФ.
A31: 45905 | B31: Источники финансовых средств семьи. Виды денежных средств. Доходы и способы их получения. Расчет личного и семейного бюджета.
A32: 45906 | B32: ПЗ. Деловая игра: составление личного и семейного бюджета, оценка их баланса.
A33: 45906 | B33: Банки. Банковские услуги населению. Валюта. Валютный рынок.
A34: 45915 | B34: Тест. Лекция по теме Основные виды кредитов: потребительский и ипотечный.
A35: 45919 | B35: Долговая нагрузка. Личное банкротство.
A36: 45922 | B36: ПЗ. Банкротство
A37: 45936 | B37: Необходимость и формы сбережений. Принципы инвестирования
A38: 45940 | B38: Самостоятельная работа по теме: "Банковская система РФ"
A39: 45944 | B39: Прохождение Всероссийского онлайн-зачета по ФГ с выдачей сертификатов
A40: 45953 | B40: ПЗ.Сравнительный анализ страхования и видов страхования РФ и зарубежных стран
A41: 45962 | B41: Л. Ценные бумаги как объект инвестирования
... A54: 46013 | B54: ДИФФ. ЗАЧЕТ

Sheet БЖ
A1: Наименование предмета | C1: Безопасность жизнедеятельности
A2: ФИО преподавателя | C2: Патраков Андрей Иванович
A3: ИСиП 24/2 | B3: Месяц | C3: сен | D3: окт | E3: окт | F3: окт | G3: окт | H3: окт | I3: окт | J3: окт | K3: ноя | L3: ноя | M3: ноя | N3: ноя | O3: ноя | P3: ноя | Q3: ноя | R3: ноя | S3: дек | Z3: Д.З | AB3: Пропуски
B4: Число | C4: 27 | D4: 7 | E4: 9 | F4: 11 | G4: 11 | H4: 13 | I4: 20 | J4: 23 | K4: 3 | L4: 7 | M4: 8 | N4: 8 | O4: 13 | P4: 13 | Q4: 20 | R4: 27 | S4: 20 | AA4: Средний балл | AB4: Уваж. | AC4: Неуваж.
A5: 1. | B5: Адилбеков Бектур | C5: н/отр | D5: 5 | E5: 2 | H5: 3 | I5: оп/3 | J5: 5 | K5: 3 | M5: 4 | N5: 4 | O5: 4 | Q5: 3 | Z5: хор | AA5: =IFERROR(AVERAGE(C5:Z5),"Нет оценок") -> 3.6666667 | AB5: =COUNTIF(C5:Z5,"н/у") -> 0 | AC5: =COUNTIF(C5:Z5,"н") -> 0
A6: 2. | B6: Ахметов Артём Рамилевич | D6: 3 | F6: 4 | H6: 3 | I6: 3 | J6: оп/4 | M6: н/3 | O6: 3 | P6: 5 | Q6: 3 | Z6: хор | AA6: =IFERROR(AVERAGE(C6:Z6),"Нет оценок") -> 3.4285714 | AB6: =COUNTIF(C6:Z6,"н/у") -> 0 | AC6: =COUNTIF(C6:Z6,"н") -> 0
A7: 3. | B7: Бараников Владислав Михайлович | D7: 3 | E7: 3 | H7: оп/3 | I7: 5 | J7: 5 | M7: 5 | O7: 4 | P7: 4 | Z7: отл | AA7: =IFERROR(AVERAGE(C7:Z7),"Нет оценок") -> 4.1428571 | AB7: =COUNTIF(C7:Z7,"н/у") -> 0 | AC7: =COUNTIF(C7:Z7,"н") -> 0
A8: 4. | B8: Борсук Артём Дмитриевич | D8: 3 | E8: 2 | F8: 5 | G8: 5 | H8: 3 | I8: 4 | J8: 3 | L8: 3 | M8: н/3 | N8: 3 | O8: 3 | P8: 2 | Z8: хор | AA8: =IFERROR(AVERAGE(C8:Z8),"Нет оценок") -> 3.2727273 | AB8: =COUNTIF(C8:Z8,"н/у") -> 0 | AC8: =COUNTIF(C8:Z8,"н") -> 0
A9: 5. | B9: Гильманов Ильназ Максимович | D9: оп/3 | E9: 3 | I9: оп/3 | J9: оп/4 | M9: 5 | N9: 5 | O9: 5 | P9: 5 | Z9: отл | AA9: =IFERROR(AVERAGE(C9:Z9),"Нет оценок") -> 4.6 | AB9: =COUNTIF(C9:Z9,"н/у") -> 0 | AC9: =COUNTIF(C9:Z9,"н") -> 0
A10: 6. | B10: Говтва Илья Денисович | D10: 3 | E10: 5 | F10: 4 | G10: 4 | H10: 5 | I10: 5 | J10: 5 | M10: 3 | N10: 5 | O10: 5 | P10: 4 | Z10: отл | AA10: =IFERROR(AVERAGE(C10:Z10),"Нет оценок") -> 4.3636364 | AB10: =COUNTIF(C10:Z10,"н/у") -> 0 | AC10: =COUNTIF(C10:Z10,"н") -> 0
A11: 7. | B11: Горшков Владислав Васильевич | C11: 3 | D11: 3 | E11: 3 | F11: 3 | G11: 3 | H11: 3 | I11: 3 | J11: 3 | M11: 3 | O11: 3 | P11: 3 | Q11: 3 | Z11: хор | AA11: =IFERROR(AVERAGE(C11:Z11),"Нет оценок") -> 3 | AB11: =COUNTIF(C11:Z11,"н/у") -> 0 | AC11: =COUNTIF(C11:Z11,"н") -> 0
A12: 8. | B12: Гришко Илья Алексеевич | D12: 3 | E12: 3 | F12: 5 | G12: 4 | H12: 5 | I12: 4 | J12: 3 | K12: 3 | M12: 3 | N12: 3 | O12: 4 | P12: 3 | Z12: хор | AA12: =IFERROR(AVERAGE(C12:Z12),"Нет оценок") -> 3.5833333 | AB12: =COUNTIF(C12:Z12,"н/у") -> 0 | AC12: =COUNTIF(C12:Z12,"н") -> 0
A13: 9. | B13: Катков Константин Александрович | D13: н | E13: 2 | F13: н | G13: н | H13: н | I13: оп/2 | J13: 2 | L13: н | M13: н | O13: н | P13: н | Z13: неявка | AA13: =IFERROR(AVERAGE(C13:Z13),"Нет оценок") -> 2 | AB13: =COUNTIF(C13:Z13,"н/у") -> 0 | AC13: =COUNTIF(C13:Z13,"н") -> 8
A14: 10. | B14: Корнеев Андрей Александрович | D14: 5 | E14: 5 | F14: 5 | G14: 5 | H14: н | I14: н | J14: н | M14: 5 | N14: 5 | O14: 4 | P14: 4 | Z14: хор | AA14: =IFERROR(AVERAGE(C14:Z14),"Нет оценок") -> 4.75 | AB14: =COUNTIF(C14:Z14,"н/у") -> 0 | AC14: =COUNTIF(C14:Z14,"н") -> 3
A15: 11. | B15: Макаров Максим Алексеевич | E15: 3 | F15: 5 | G15: 5 | H15: 4 | I15: 5 | J15: 4 | M15: 3 | O15: 3 | P15: 3 | Z15: хор | AA15: =IFERROR(AVERAGE(C15:Z15),"Нет оценок") -> 3.8888889 | AB15: =COUNTIF(C15:Z15,"н/у") -> 0 | AC15: =COUNTIF(C15:Z15,"н") -> 0
A16: 13. | B16: Муллагалиев Вадим Радмилович | D16: 3 | E16: 3 | F16: 4 | G16: 4 | H16: 3 | I16: 5 | J16: оп/4 | L16: 3 | M16: 4 | N16: 3 | O16: 3 | P16: 3 | Q16: н/у | R16: 3 | Z16: хор | AA16: =IFERROR(AVERAGE(C16:Z16),"Нет оценок") -> 3.4166667 | AB16: =COUNTIF(C16:Z16,"н/у") -> 1 | AC16: =COUNTIF(C16:Z16,"н") -> 0
A17: 12. | B17: Натфуллин Камиль Данисович | C17: н | D17: н | E17: н | F17: 3 | G17: 3 | H17: н | I17: н | J17: оп/3 | K17: н | L17: н | M17: 3 | N17: 3 | O17: н | P17: н | Q17: н | Z17: неявка | AA17: =IFERROR(AVERAGE(C17:Z17),"Нет оценок") -> 3 | AB17: =COUNTIF(C17:Z17,"н/у") -> 0 | AC17: =COUNTIF(C17:Z17,"н") -> 10
A18: 14. | B18: Носков Ярослав Евгеньевич | D18: 3 | E18: 3 | F18: 3 | H18: 4 | I18: 5 | J18: 4 | M18: 3 | O18: 4 | Z18: хор | AA18: =IFERROR(AVERAGE(C18:Z18),"Нет оценок") -> 3.625 | AB18: =COUNTIF(C18:Z18,"н/у") -> 0 | AC18: =COUNTIF(C18:Z18,"н") -> 0
A19: 15. | B19: Осыка Владислав Сергеевич | D19: н/3 | E19: 3 | F19: 3 | G19: 3 | H19: 5 | I19: 5 | J19: 3 | L19: 3 | M19: н/3 | N19: 3 | O19: 3 | P19: 3 | R19: 3 | Z19: хор | AA19: =IFERROR(AVERAGE(C19:Z19),"Нет оценок") -> 3.3636364 | AB19: =COUNTIF(C19:Z19,"н/у") -> 0 | AC19: =COUNTIF(C19:Z19,"н") -> 0
A20: 16. | B20: Романов Михаил Васильевич | D20: 5 | E20: 5 | F20: 5 | G20: 5 | H20: 5 | I20: 5 | J20: 5 | M20: 5 | O20: 5 | P20: 5 | Z20: отл | AA20: =IFERROR(AVERAGE(C20:Z20),"Нет оценок") -> 5 | AB20: =COUNTIF(C20:Z20,"н/у") -> 0 | AC20: =COUNTIF(C20:Z20,"н") -> 0
A21: 17. | B21: Руфуллаев Ибрагим Фуадович | D21: оп/3 | E21: 3 | F21: 3 | G21: 3 | H21: 5 | I21: оп/3 | J21: 5 | M21: 5 | O21: 3 | P21: 3 | Z21: хор | AA21: =IFERROR(AVERAGE(C21:Z21),"Нет оценок") -> 3.75 | AB21: =COUNTIF(C21:Z21,"н/у") -> 0 | AC21: =COUNTIF(C21:Z21,"н") -> 0
A22: 18. | B22: Сарычев Данила Андреевич | D22: 5 | E22: 5 | F22: 5 | G22: 5 | H22: 5 | I22: 5 | J22: 5 | M22: н/3 | N22: н/3 | O22: 3 | P22: 4 | Z22: хор | AA22: =IFERROR(AVERAGE(C22:Z22),"Нет оценок") -> 4.6666667 | AB22: =COUNTIF(C22:Z22,"н/у") -> 0 | AC22: =COUNTIF(C22:Z22,"н") -> 0
A23: 19. | B23: Сурков Кирилл Александрович | C23: н | D23: оп/3 | E23: 5 | F23: н | H23: н | I23: н | J23: н | L23: н | M23: н | O23: н | P23: н | R23: н | Z23: хор | AA23: =IFERROR(AVERAGE(C23:Z23),"Нет оценок") -> 5 | AB23: =COUNTIF(C23:Z23,"н/у") -> 0 | AC23: =COUNTIF(C23:Z23,"н") -> 10
A24: 20. | B24: Усатов Тимофей Анатольевич | D24: 5 | E24: 5 | H24: 5 | I24: 5 | J24: 5 | M24: 5 | O24: 4 | P24: 5 | Z24: отл | AA24: =IFERROR(AVERAGE(C24:Z24),"Нет оценок") -> 4.875 | AB24: =COUNTIF(C24:Z24,"н/у") -> 0 | AC24: =COUNTIF(C24:Z24,"н") -> 0
A25: 21. | B25: Халитов Кирилл Родионович | C25: н | D25: н | E25: н | F25: 3 | G25: 3 | H25: н | I25: оп/3 | J25: оп/4 | L25: н | M25: н | O25: н | P25: 2 | Q25: н | R25: 3 | Z25: неуд | AA25: =IFERROR(AVERAGE(C25:Z25),"Нет оценок") -> 2.75 | AB25: =COUNTIF(C25:Z25,"н/у") -> 0 | AC25: =COUNTIF(C25:Z25,"н") -> 8
A26: 21. | B26: Хорошилов Игорь Александрович | AA26: =IFERROR(AVERAGE(C26:Z26),"Нет оценок") -> Нет оценок | AB26: =COUNTIF(C26:Z26,"н/у") -> 0 | AC26: =COUNTIF(C26:Z26,"н") -> 0
A27: 22. | B27: Хрычев Мирон Евгеньевич | C27: 3 | D27: 5 | E27: 5 | F27: 5 | G27: 4 | H27: 5 | I27: 5 | J27: 5 | K27: н/у | L27: н/3 | M27: 3 | N27: 4 | O27: 3 | P27: 5 | R27: 3 | Z27: хор | AA27: =IFERROR(AVERAGE(C27:Z27),"Нет оценок") -> 4.2307692 | AB27: =COUNTIF(C27:Z27,"н/у") -> 1 | AC27: =COUNTIF(C27:Z27,"н") -> 0
A28: 23. | B28: Цапов Илья Валерьевич | C28: н/3 | D28: оп/3 | E28: 3 | F28: 3 | G28: 3 | H28: 3 | I28: 3 | J28: 3 | M28: 3 | O28: 3 | P28: 3 | R28: 3 | AA28: =IFERROR(AVERAGE(C28:Z28),"Нет оценок") -> 3 | AB28: =COUNTIF(C28:Z28,"н/у") -> 0 | AC28: =COUNTIF(C28:Z28,"н") -> 0
A29: Дата | B29: Тема / ДЗ | AA29: =IFERROR(AVERAGE(AA6:AA28),"") -> 3.8048979 | AB29: =SUM(AB6:AB28) -> 2 | AC29: =SUM(AC6:AC28) -> 39
A30: 45927 | B30: Введение в дисциплину БЖД
A31: 45937 | B31: Потенциальные опасности и их последствия в профессиональной деятельности
A32: 45939 | B32: Чрезвычайные ситуации мирного времени и защита от них
A33: 45941 | B33: Чрезвычайные ситуации мирного времени и защита от них
A34: 45941 | B34: Оружие массового поражения и способы защиты населения
A35: 45943 | B35: Оружие массового поражения и способы защиты населения
A36: 45950 | B36: Оружие массового поражения и способы защиты населения
A37: 45953 | B37: Гражданская оборона - составная часть обороноспособности страны
A38: 45964 | B38: Гражданская оборона - составная часть обороноспособности страны
A39: 45968 | B39: Гражданская оборона - составная часть обороноспособности страны
A40: 45969 | B40: Основы обороны государства и воинская обязанность
A41: 45969 | B41: Основы обороны государства и воинская обязанность
... A43: 45974 | B43: Организация и порядок призыва граждан на военную службу
A44: 45981
A45: 45988

Sheet Обе.без.веб-прил.
A1: Наименование предмета | C1: Обеспечение безопасности веб-приложений
A2: ФИО преподавателя | C2: Трушина Александра Игоревна
A3: ИСиП 24/2 | B3: Месяц | C3: Январь | G3: Февраль | I3: Март | L3: Апрель | AB3: Пропуски
B4: Число | C4: 13 | D4: 17 | E4: 27 | F4: 31 | G4: 24 | H4: 26 | I4: 4 | J4: 10 | K4: 12 | L4: 3 | M4: 3 | AA4: Средний балл | AB4: Уваж. | AC4: Неуваж.
A5: 1. | B5: Ахметов Артём Рамилевич | C5: 5 | E5: 5 | F5: н | G5: 5 | H5: 5 | I5: н | J5: н | K5: 2 | L5: н | M5: н | AA5: =IFERROR(AVERAGE(C5:Z5),"Нет оценок") -> 4.4 | AB5: =COUNTIF(C5:Z5,"н/у") -> 0 | AC5: =COUNTIF(C5:Z5,"н") -> 5
A6: 2. | B6: Адилбеков Бектур | C6: н | D6: н | E6: 4 | F6: н | G6: н | H6: 4 | I6: н | J6: н | K6: 2 | AA6: =IFERROR(AVERAGE(C6:Z6),"Нет оценок") -> 3.3333333 | AB6: =COUNTIF(C6:Z6,"н/у") -> 0 | AC6: =COUNTIF(C6:Z6,"н") -> 6
A7: 3. | B7: Бараников Владислав Михайлович | C7: 5 | E7: 4 | F7: 5 | G7: 5 | H7: 4 | I7: 5 | J7: 5 | K7: 2 | AA7: =IFERROR(AVERAGE(C7:Z7),"Нет оценок") -> 4.375 | AB7: =COUNTIF(C7:Z7,"н/у") -> 0 | AC7: =COUNTIF(C7:Z7,"н") -> 0
A8: 4. | B8: Борсук Артём Дмитриевич | C8: 5 | E8: 4 | F8: н | G8: 5 | H8: 5 | I8: 5 | J8: н | K8: 3 | AA8: =IFERROR(AVERAGE(C8:Z8),"Нет оценок") -> 4.5 | AB8: =COUNTIF(C8:Z8,"н/у") -> 0 | AC8: =COUNTIF(C8:Z8,"н") -> 2
A9: 5. | B9: Гильманов Ильназ Максимович | C9: н | E9: 4 | F9: 5 | G9: 5 | H9: 5 | I9: 5 | J9: 5 | K9: 4 | AA9: =IFERROR(AVERAGE(C9:Z9),"Нет оценок") -> 4.7142857 | AB9: =COUNTIF(C9:Z9,"н/у") -> 0 | AC9: =COUNTIF(C9:Z9,"н") -> 1
A10: 6. | B10: Говтва Илья Денисович | C10: 5 | E10: 5 | F10: 5 | G10: 5 | H10: 5 | I10: 5 | J10: 5 | K10: 4 | AA10: =IFERROR(AVERAGE(C10:Z10),"Нет оценок") -> 4.875 | AB10: =COUNTIF(C10:Z10,"н/у") -> 0 | AC10: =COUNTIF(C10:Z10,"н") -> 0
A11: 7. | B11: Горшков Владислав Васильевич | C11: 5 | E11: 5 | F11: 5 | G11: 5 | H11: 4 | I11: 4 | J11: 5 | K11: 3 | AA11: =IFERROR(AVERAGE(C11:Z11),"Нет оценок") -> 4.5 | AB11: =COUNTIF(C11:Z11,"н/у") -> 0 | AC11: =COUNTIF(C11:Z11,"н") -> 0
A12: 8. | B12: Гришко Илья Алексеевич | C12: 5 | E12: 3 | F12: 5 | G12: 5 | H12: 3 | I12: 5 | J12: н | K12: 2 | AA12: =IFERROR(AVERAGE(C12:Z12),"Нет оценок") -> 4 | AB12: =COUNTIF(C12:Z12,"н/у") -> 0 | AC12: =COUNTIF(C12:Z12,"н") -> 1
A13: 9. | B13: Катков Константин Александрович | C13: н | F13: 3 | G13: 5 | H13: 2 | I13: 2 | J13: н | K13: 2 | AA13: =IFERROR(AVERAGE(C13:Z13),"Нет оценок") -> 2.8 | AB13: =COUNTIF(C13:Z13,"н/у") -> 0 | AC13: =COUNTIF(C13:Z13,"н") -> 2
A14: 10. | B14: Корнеев Андрей Александрович | C14: н | E14: 4 | F14: 4 | G14: 5 | H14: 5 | I14: 4 | J14: 5 | K14: 2 | AA14: =IFERROR(AVERAGE(C14:Z14),"Нет оценок") -> 4.1428571 | AB14: =COUNTIF(C14:Z14,"н/у") -> 0 | AC14: =COUNTIF(C14:Z14,"н") -> 1
A15: 11. | B15: Макаров Максим Алексеевич | C15: 5 | E15: 5 | F15: 5 | G15: 4 | H15: 4 | I15: 4 | J15: 5 | K15: 3 | AA15: =IFERROR(AVERAGE(C15:Z15),"Нет оценок") -> 4.375 | AB15: =COUNTIF(C15:Z15,"н/у") -> 0 | AC15: =COUNTIF(C15:Z15,"н") -> 0
A16: 13. | B16: Муллагалиев Вадим Радмилович | C16: н | E16: 4 | F16: 5 | G16: 5 | H16: 4 | I16: 5 | J16: 2 | K16: 2 | AA16: =IFERROR(AVERAGE(C16:Z16),"Нет оценок") -> 3.8571429 | AB16: =COUNTIF(C16:Z16,"н/у") -> 0 | AC16: =COUNTIF(C16:Z16,"н") -> 1
A17: 12. | B17: Натфуллин Камиль Данисович | C17: 5 | E17: н | F17: н | G17: н | H17: 4 | I17: н | J17: н | K17: 4 | AA17: =IFERROR(AVERAGE(C17:Z17),"Нет оценок") -> 4.3333333 | AB17: =COUNTIF(C17:Z17,"н/у") -> 0 | AC17: =COUNTIF(C17:Z17,"н") -> 5
A18: 14. | B18: Носков Ярослав Евгеньевич | C18: н | E18: 3 | F18: 3 | G18: 3 | H18: 4 | I18: 5 | J18: н | K18: 2 | AA18: =IFERROR(AVERAGE(C18:Z18),"Нет оценок") -> 3.3333333 | AB18: =COUNTIF(C18:Z18,"н/у") -> 0 | AC18: =COUNTIF(C18:Z18,"н") -> 2
A19: 15. | B19: Осыка Владислав Сергеевич | C19: 5 | E19: 4 | F19: 5 | G19: 5 | H19: 4 | I19: н | J19: о/5 | K19: о/4 | AA19: =IFERROR(AVERAGE(C19:Z19),"Нет оценок") -> 4.6 | AB19: =COUNTIF(C19:Z19,"н/у") -> 0 | AC19: =COUNTIF(C19:Z19,"н") -> 1
A20: 16. | B20: Романов Михаил Васильевич | C20: 5 | E20: 5 | F20: 5 | G20: 5 | H20: 5 | I20: н | J20: 5 | K20: 4 | AA20: =IFERROR(AVERAGE(C20:Z20),"Нет оценок") -> 4.8571429 | AB20: =COUNTIF(C20:Z20,"н/у") -> 0 | AC20: =COUNTIF(C20:Z20,"н") -> 1
A21: 17. | B21: Руфуллаев Ибрагим Фуадович | C21: н | E21: 5 | F21: 4 | G21: 3 | H21: 3 | I21: 5 | J21: н | K21: 2 | AA21: =IFERROR(AVERAGE(C21:Z21),"Нет оценок") -> 3.6666667 | AB21: =COUNTIF(C21:Z21,"н/у") -> 0 | AC21: =COUNTIF(C21:Z21,"н") -> 2
A22: 18. | B22: Сарычев Данила Андреевич | C22: 5 | E22: 5 | F22: н | G22: н | H22: 5 | I22: 4 | J22: 5 | K22: н | AA22: =IFERROR(AVERAGE(C22:Z22),"Нет оценок") -> 4.8 | AB22: =COUNTIF(C22:Z22,"н/у") -> 0 | AC22: =COUNTIF(C22:Z22,"н") -> 3
A23: 19. | B23: Сурков Кирилл Александрович | C23: н | D23: н | E23: н | F23: 5 | G23: н | H23: 4 | I23: н | J23: н | K23: н | L23: н/у | M23: н/у | AA23: =IFERROR(AVERAGE(C23:Z23),"Нет оценок") -> 4.5 | AB23: =COUNTIF(C23:Z23,"н/у") -> 2 | AC23: =COUNTIF(C23:Z23,"н") -> 7
A24: 20. | B24: Усатов Тимофей Анатольевич | C24: 5 | E24: 5 | F24: 5 | H24: 5 | I24: 5 | J24: 5 | K24: 3 | AA24: =IFERROR(AVERAGE(C24:Z24),"Нет оценок") -> 4.7142857 | AB24: =COUNTIF(C24:Z24,"н/у") -> 0 | AC24: =COUNTIF(C24:Z24,"н") -> 0
A25: 21. | B25: Халитов Кирилл Родионович | C25: н | E25: н | F25: н | G25: 4 | H25: 4 | I25: 5 | J25: н | K25: 3 | AA25: =IFERROR(AVERAGE(C25:Z25),"Нет оценок") -> 4 | AB25: =COUNTIF(C25:Z25,"н/у") -> 0 | AC25: =COUNTIF(C25:Z25,"н") -> 4
A26: 21. | B26: Хорошилов Игорь Александрович | AA26: =IFERROR(AVERAGE(C26:Z26),"Нет оценок") -> Нет оценок | AB26: =COUNTIF(C26:Z26,"н/у") -> 0 | AC26: =COUNTIF(C26:Z26,"н") -> 0
A27: 22. | B27: Хрычев Мирон Евгеньевич | C27: н | E27: 4 | F27: 5 | G27: н | H27: 4 | I27: 3 | J27: н | K27: 2 | AA27: =IFERROR(AVERAGE(C27:Z27),"Нет оценок") -> 3.6 | AB27: =COUNTIF(C27:Z27,"н/у") -> 0 | AC27: =COUNTIF(C27:Z27,"н") -> 3
A28: 23. | B28: Цапов Илья Валерьевич | C28: н | E28: н | F28: 5 | G28: н | H28: 4 | I28: н | J28: н | K28: 3 | AA28: =IFERROR(AVERAGE(C28:Z28),"Нет оценок") -> 4 | AB28: =COUNTIF(C28:Z28,"н/у") -> 0 | AC28: =COUNTIF(C28:Z28,"н") -> 5
A29: Дата | B29: Тема / ДЗ | AA29: =IFERROR(AVERAGE(AA5:AA28),"") -> 4.1859731 | AB29: =SUM(AB5:AB28) -> 2 | AC29: =SUM(AC5:AC28) -> 52
A30: 46035 | B30: Задание по Лекция 1. История информационной безопасности веб-приложений | C30: л | F30: ПЛАН | I30: ПРОШЛО | L30: ОСТАЛОСЬ
A31: 46039 | B31: 1 Основные понятия обеспечения безопасности веб приложений до 14 слайда | C31: л | G31: Л | H31: П | J31: Л | K31: П | M31: Л | N31: П
A32: 46049 | B32: 1 Основные понятия обеспечения безопасности веб приложений / Тест по лекции | C32: л | F32: П | G32: =G33/2 -> 11 | H32: =H33/2 -> 10 | I32: П | J32: =COUNTIF(C30:C99,"Л") -> 7 | K32: =COUNTIF(C30:C102,"ПЗ") -> 4 | L32: П | M32: =G32-J32 -> 4 | N32: =H32-K32 -> 6
A33: 46053 | B33: Лабораторная работа № 1. Сбор информации о web-ПРИЛОЖЕНИИ | C33: пз | F33: Ч | G33: 22 | H33: 20 | I33: Ч | J33: =J32*2 -> 14 | K33: =K32*2 -> 8 | L33: Ч | M33: =G33-J33 -> 8 | N33: =H33-K33 -> 12
A34: 46077 | B34: Основные принципы Построения безопасных Сайтов | C34: л
A35: 46079 | B35: Практическая работа № 1. Анализ примеров нарушений информационной безопасности. Выявление значимых составляющих информационной безопасности и характеристик информационной системы в конкретных ситуациях | C35: пз
A36: 46085 | B36: Практическая работа № 2 Анализ нормативно-правовой документации по организации и функционированию режима защиты государственной тайны | C36: пз
A37: 46091 | B37: 2.2.2. Частотность запросов / 2.2.3. Процесс сбора семантического ядра. Лекция | C37: л
A38: 46093 | B38: Практическая работа № 3 Оценка уязвимости информации | C38: пз
A39: 46115 | B39: Производительность веб-приложений: основы и актуальность - В счет оптимизации | C39: л
A40: 46115 | B40: Обзор и ключевые темы информационной безопасности веб-приложений | C40: л

Sheet Оптими.веб-прил.
A1: Наименование предмета | C1: Оптимизация веб-приложений
A2: ФИО преподавателя | C2: Трушина Александра Игоревна
A3: ИСиП 24/2 | B3: Месяц | C3: Январь | F3: Март | I3: Апрель | AA3: Пропуски
B4: Число | C4: 22 | D4: 22 | E4: 16 | F4: 5 | G4: 5 | H4: 30 | I4: 2 | Z4: Средний балл | AA4: Уваж. | AB4: Неуваж.
A5: 1. | B5: Ахметов Артём Рамилевич | C5: н | D5: н | F5: н | G5: н | H5: 5 | I5: + | Z5: =IFERROR(AVERAGE(C5:Y5),"Нет оценок") -> 5 | AA5: =COUNTIF(C5:Y5,"н/у") -> 0 | AB5: =COUNTIF(C5:Y5,"н") -> 4
A6: 2. | B6: Адилбеков Бектур | C6: н | D6: н | E6: н | F6: н | G6: н | H6: н | I6: н | Z6: =IFERROR(AVERAGE(C6:Y6),"Нет оценок") -> Нет оценок | AA6: =COUNTIF(C6:Y6,"н/у") -> 0 | AB6: =COUNTIF(C6:Y6,"н") -> 7
A7: 3. | B7: Бараников Владислав Михайлович | C7: 5 | D7: 5 | F7: 5 | G7: + | H7: 5 | I7: + | Z7: =IFERROR(AVERAGE(C7:Y7),"Нет оценок") -> 5 | AA7: =COUNTIF(C7:Y7,"н/у") -> 0 | AB7: =COUNTIF(C7:Y7,"н") -> 0
A8: 4. | B8: Борсук Артём Дмитриевич | C8: 5 | D8: 5 | G8: + | H8: 5 | I8: + | Z8: =IFERROR(AVERAGE(C8:Y8),"Нет оценок") -> 5 | AA8: =COUNTIF(C8:Y8,"н/у") -> 0 | AB8: =COUNTIF(C8:Y8,"н") -> 0
A9: 5. | B9: Гильманов Ильназ Максимович | C9: 5 | D9: 4 | G9: + | H9: 5 | I9: н | Z9: =IFERROR(AVERAGE(C9:Y9),"Нет оценок") -> 4.6666667 | AA9: =COUNTIF(C9:Y9,"н/у") -> 0 | AB9: =COUNTIF(C9:Y9,"н") -> 1
A10: 6. | B10: Говтва Илья Денисович | C10: 5 | D10: 5 | F10: 5 | G10: + | H10: 5 | I10: + | Z10: =IFERROR(AVERAGE(C10:Y10),"Нет оценок") -> 5 | AA10: =COUNTIF(C10:Y10,"н/у") -> 0 | AB10: =COUNTIF(C10:Y10,"н") -> 0
A11: 7. | B11: Горшков Владислав Васильевич | C11: 5 | D11: 4 | G11: + | H11: 5 | I11: + | Z11: =IFERROR(AVERAGE(C11:Y11),"Нет оценок") -> 4.6666667 | AA11: =COUNTIF(C11:Y11,"н/у") -> 0 | AB11: =COUNTIF(C11:Y11,"н") -> 0
A12: 8. | B12: Гришко Илья Алексеевич | C12: 2 | D12: 4 | G12: + | H12: 2 | I12: + | Z12: =IFERROR(AVERAGE(C12:Y12),"Нет оценок") -> 2.6666667 | AA12: =COUNTIF(C12:Y12,"н/у") -> 0 | AB12: =COUNTIF(C12:Y12,"н") -> 0
A13: 9. | B13: Катков Константин Александрович | C13: н | D13: н | E13: н | F13: н | G13: н | H13: 2 | I13: н | Z13: =IFERROR(AVERAGE(C13:Y13),"Нет оценок") -> 2 | AA13: =COUNTIF(C13:Y13,"н/у") -> 0 | AB13: =COUNTIF(C13:Y13,"н") -> 6
A14: 10. | B14: Корнеев Андрей Александрович | C14: н | D14: н | F14: н | G14: н | H14: н/у | I14: о/+ | Z14: =IFERROR(AVERAGE(C14:Y14),"Нет оценок") -> Нет оценок | AA14: =COUNTIF(C14:Y14,"н/у") -> 1 | AB14: =COUNTIF(C14:Y14,"н") -> 4
A15: 11. | B15: Макаров Максим Алексеевич | C15: 4 | D15: 4 | G15: + | H15: 5 | I15: + | Z15: =IFERROR(AVERAGE(C15:Y15),"Нет оценок") -> 4.3333333 | AA15: =COUNTIF(C15:Y15,"н/у") -> 0 | AB15: =COUNTIF(C15:Y15,"н") -> 0
A16: 13. | B16: Муллагалиев Вадим Радмилович | C16: н | D16: н | F16: 5 | G16: + | H16: 2 | I16: + | Z16: =IFERROR(AVERAGE(C16:Y16),"Нет оценок") -> 3.5 | AA16: =COUNTIF(C16:Y16,"н/у") -> 0 | AB16: =COUNTIF(C16:Y16,"н") -> 2
A17: 12. | B17: Натфуллин Камиль Данисович | C17: 4 | D17: 4 | E17: н | G17: + | H17: 5 | I17: н | Z17: =IFERROR(AVERAGE(C17:Y17),"Нет оценок") -> 4.3333333 | AA17: =COUNTIF(C17:Y17,"н/у") -> 0 | AB17: =COUNTIF(C17:Y17,"н") -> 2
A18: 14. | B18: Носков Ярослав Евгеньевич | C18: н | D18: н | F18: 3 | G18: + | H18: 2 | I18: + | Z18: =IFERROR(AVERAGE(C18:Y18),"Нет оценок") -> 2.5 | AA18: =COUNTIF(C18:Y18,"н/у") -> 0 | AB18: =COUNTIF(C18:Y18,"н") -> 2
A19: 15. | B19: Осыка Владислав Сергеевич | C19: н | D19: н | F19: 5 | G19: + | H19: н | I19: + | Z19: =IFERROR(AVERAGE(C19:Y19),"Нет оценок") -> 5 | AA19: =COUNTIF(C19:Y19,"н/у") -> 0 | AB19: =COUNTIF(C19:Y19,"н") -> 3
A20: 16. | B20: Романов Михаил Васильевич | C20: 5 | D20: 5 | G20: + | H20: 5 | I20: н | Z20: =IFERROR(AVERAGE(C20:Y20),"Нет оценок") -> 5 | AA20: =COUNTIF(C20:Y20,"н/у") -> 0 | AB20: =COUNTIF(C20:Y20,"н") -> 1
A21: 17. | B21: Руфуллаев Ибрагим Фуадович | C21: н | D21: н | G21: + | H21: 5 | I21: + | Z21: =IFERROR(AVERAGE(C21:Y21),"Нет оценок") -> 5 | AA21: =COUNTIF(C21:Y21,"н/у") -> 0 | AB21: =COUNTIF(C21:Y21,"н") -> 2
A22: 18. | B22: Сарычев Данила Андреевич | C22: 5 | D22: 5 | G22: + | H22: н/у | I22: + | Z22: =IFERROR(AVERAGE(C22:Y22),"Нет оценок") -> 5 | AA22: =COUNTIF(C22:Y22,"н/у") -> 1 | AB22: =COUNTIF(C22:Y22,"н") -> 0
A23: 19. | B23: Сурков Кирилл Александрович | C23: н | D23: н | E23: н | F23: 5 | G23: + | H23: 5 | I23: н | Z23: =IFERROR(AVERAGE(C23:Y23),"Нет оценок") -> 5 | AA23: =COUNTIF(C23:Y23,"н/у") -> 0 | AB23: =COUNTIF(C23:Y23,"н") -> 4
A24: 20. | B24: Усатов Тимофей Анатольевич | C24: отр | D24: 4 | F24: 5 | G24: + | H24: 5 | I24: + | Z24: =IFERROR(AVERAGE(C24:Y24),"Нет оценок") -> 4.6666667 | AA24: =COUNTIF(C24:Y24,"н/у") -> 0 | AB24: =COUNTIF(C24:Y24,"н") -> 0
A25: 21. | B25: Халитов Кирилл Родионович | C25: н | D25: н | E25: н | F25: н | G25: н | H25: н | I25: н | Z25: =IFERROR(AVERAGE(C25:Y25),"Нет оценок") -> Нет оценок | AA25: =COUNTIF(C25:Y25,"н/у") -> 0 | AB25: =COUNTIF(C25:Y25,"н") -> 7
A26: 21. | B26: Хорошилов Игорь Александрович | C26: н | D26: н | E26: н | F26: н | G26: н | H26: н | Z26: =IFERROR(AVERAGE(C26:Y26),"Нет оценок") -> Нет оценок | AA26: =COUNTIF(C26:Y26,"н/у") -> 0 | AB26: =COUNTIF(C26:Y26,"н") -> 6
A27: 22. | B27: Хрычев Мирон Евгеньевич | C27: н | D27: н | G27: н | H27: 5 | I27: н | Z27: =IFERROR(AVERAGE(C27:Y27),"Нет оценок") -> 5 | AA27: =COUNTIF(C27:Y27,"н/у") -> 0 | AB27: =COUNTIF(C27:Y27,"н") -> 4
A28: 23. | B28: Цапов Илья Валерьевич | C28: н | D28: н | E28: н | G28: н | H28: н | I28: + | Z28: =IFERROR(AVERAGE(C28:Y28),"Нет оценок") -> Нет оценок | AA28: =COUNTIF(C28:Y28,"н/у") -> 0 | AB28: =COUNTIF(C28:Y28,"н") -> 5
D29: ПР 1 | F29: ЛР 1 | H29: ЛР 2
A30: Дата | B30: Тема / ДЗ | Z30: =IFERROR(AVERAGE(Z5:Z28),"") -> 4.3859649 | AA30: =SUM(AA5:AA28) -> 2 | AB30: =SUM(AB5:AB28) -> 60
A31: 46044 | B31: 2.1.1. Цели поисковой оптимизации / 2.1.2. Основные понятия | C31: л | E31: ПЛАН | H31: ПРОШЛО | J31: ОСТАЛОСЬ
A32: 46044 | B32: Практическая работа 1 «Поисковая оптимизация и продвижение сайта» | C32: пз | F32: Л | G32: П | I32: П | K32: Л | L32: П
A33: 46069 | B33: 2.1.3. Фильтры поисковых систем | C33: л | E33: П | F33: =F34/2 -> 11 | G33: =G34/2 -> 11 | H33: П | I33: =COUNTIF(C31:C103,"ПЗ") -> 3 | J33: П | K33: =F33-#REF! -> #REF! | L33: =G33-I33 -> 8
A34: 46086 | B34: Лабораторная работа №1 «Проведение общего аудита сайта: SEO, юзабилити, тексты» | C34: пз | E34: Ч | F34: 22 | G34: 22 | H34: Ч | I34: =I33*2 -> 6 | J34: Ч | K34: =F34-#REF! -> #REF! | L34: =G34-I34 -> 16
A35: 46086 | B35: 2.2.1. Семантическое ядро | C35: л
A36: 46091 | B36: 2.2.2. Частотность запросов | C36: л
A37: 46111 | B37: Лабораторная работа № 2 | C37: пз
A38: 46114 | B38: Работа с учебником. Глава 2. Оптизимизация веб-приложений. Техническая оптимизация | C38: л

Sheet Тестирование ИС
A1: Наименование предмета | C1: Тестирование информационных систем
A2: ФИО преподавателя | C2: Коваленко Даниил Романович
A3: ИСиП 24/2 | B3: Месяц | C3: Январь | F3: Февраль | CB3: Пропуски
B4: Число | C4: 12 | D4: 20 | E4: 26 | F4: 5 | G4: 19 | H4: 20 | CA4: Средний балл | CB4: Уваж. | CC4: Неуваж.
A5: 1. | B5: Адилбеков Бектур | C5: н | D5: н | E5: н | G5: н | CA5: =IFERROR(AVERAGE(C5:BZ5),"Нет оценок") -> Нет оценок | CB5: =COUNTIF(C5:BZ5,"н/у") -> 0 | CC5: =COUNTIF(C5:BZ5,"н") -> 4
A6: 2. | B6: Ахметов Артём Рамилевич | D6: н | E6: 5 | I6: .4 | CA6: =IFERROR(AVERAGE(C6:BZ6),"Нет оценок") -> 5 | CB6: =COUNTIF(C6:BZ6,"н/у") -> 0 | CC6: =COUNTIF(C6:BZ6,"н") -> 1
A7: 3. | B7: Бараников Владислав Михайлович | D7: н | E7: 5 | I7: .5 | CA7: =IFERROR(AVERAGE(C7:BZ7),"Нет оценок") -> 5 | CB7: =COUNTIF(C7:BZ7,"н/у") -> 0 | CC7: =COUNTIF(C7:BZ7,"н") -> 1
A8: 4. | B8: Борсук Артём Дмитриевич | E8: н | F8: н | G8: н | H8: н | CA8: =IFERROR(AVERAGE(C8:BZ8),"Нет оценок") -> Нет оценок | CB8: =COUNTIF(C8:BZ8,"н/у") -> 0 | CC8: =COUNTIF(C8:BZ8,"н") -> 4
A9: 5. | B9: Гильманов Ильназ Максимович | E9: 5 | CA9: =IFERROR(AVERAGE(C9:BZ9),"Нет оценок") -> 5 | CB9: =COUNTIF(C9:BZ9,"н/у") -> 0 | CC9: =COUNTIF(C9:BZ9,"н") -> 0
A10: 6. | B10: Говтва Илья Денисович | E10: 5 | I10: .2 | CA10: =IFERROR(AVERAGE(C10:BZ10),"Нет оценок") -> 5 | CB10: =COUNTIF(C10:BZ10,"н/у") -> 0 | CC10: =COUNTIF(C10:BZ10,"н") -> 0
A11: 7. | B11: Горшков Владислав Васильевич | E11: 5 | G11: н | CA11: =IFERROR(AVERAGE(C11:BZ11),"Нет оценок") -> 5 | CB11: =COUNTIF(C11:BZ11,"н/у") -> 0 | CC11: =COUNTIF(C11:BZ11,"н") -> 1
A12: 8. | B12: Гришко Илья Алексеевич | E12: 5 | G12: н | H12: н | CA12: =IFERROR(AVERAGE(C12:BZ12),"Нет оценок") -> 5 | CB12: =COUNTIF(C12:BZ12,"н/у") -> 0 | CC12: =COUNTIF(C12:BZ12,"н") -> 2
A13: 9. | B13: Катков Константин Александрович | D13: н | E13: н | I13: .6 | CA13: =IFERROR(AVERAGE(C13:BZ13),"Нет оценок") -> Нет оценок | CB13: =COUNTIF(C13:BZ13,"н/у") -> 0 | CC13: =COUNTIF(C13:BZ13,"н") -> 2
A14: 10. | B14: Корнеев Андрей Александрович | E14: 5 | CA14: =IFERROR(AVERAGE(C14:BZ14),"Нет оценок") -> 5 | CB14: =COUNTIF(C14:BZ14,"н/у") -> 0 | CC14: =COUNTIF(C14:BZ14,"н") -> 0
A15: 11. | B15: Макаров Максим Алексеевич | E15: 5 | CA15: =IFERROR(AVERAGE(C15:BZ15),"Нет оценок") -> 5 | CB15: =COUNTIF(C15:BZ15,"н/у") -> 0 | CC15: =COUNTIF(C15:BZ15,"н") -> 0
A16: 13. | B16: Муллагалиев Вадим Радмилович | D16: н | E16: 5 | G16: н | I16: .1 | CA16: =IFERROR(AVERAGE(C16:BZ16),"Нет оценок") -> 5 | CB16: =COUNTIF(C16:BZ16,"н/у") -> 0 | CC16: =COUNTIF(C16:BZ16,"н") -> 2
A17: 12. | B17: Натфуллин Камиль Данисович | C17: н | E17: 5 | F17: н | G17: н | CA17: =IFERROR(AVERAGE(C17:BZ17),"Нет оценок") -> 5 | CB17: =COUNTIF(C17:BZ17,"н/у") -> 0 | CC17: =COUNTIF(C17:BZ17,"н") -> 3
A18: 14. | B18: Носков Ярослав Евгеньевич | D18: н | E18: н | G18: н | CA18: =IFERROR(AVERAGE(C18:BZ18),"Нет оценок") -> Нет оценок | CB18: =COUNTIF(C18:BZ18,"н/у") -> 0 | CC18: =COUNTIF(C18:BZ18,"н") -> 3
A19: 15. | B19: Осыка Владислав Сергеевич | E19: 5 | H19: н | I19: .3 | CA19: =IFERROR(AVERAGE(C19:BZ19),"Нет оценок") -> 5 | CB19: =COUNTIF(C19:BZ19,"н/у") -> 0 | CC19: =COUNTIF(C19:BZ19,"н") -> 1
A20: 16. | B20: Романов Михаил Васильевич | D20: н | E20: 5 | F20: н | H20: н | CA20: =IFERROR(AVERAGE(C20:BZ20),"Нет оценок") -> 5 | CB20: =COUNTIF(C20:BZ20,"н/у") -> 0 | CC20: =COUNTIF(C20:BZ20,"н") -> 3
A21: 17. | B21: Руфуллаев Ибрагим Фуадович | D21: н | E21: 5 | G21: н | I21: .3 | CA21: =IFERROR(AVERAGE(C21:BZ21),"Нет оценок") -> 5 | CB21: =COUNTIF(C21:BZ21,"н/у") -> 0 | CC21: =COUNTIF(C21:BZ21,"н") -> 2
A22: 18. | B22: Сарычев Данила Андреевич | E22: 5 | I22: .5 | CA22: =IFERROR(AVERAGE(C22:BZ22),"Нет оценок") -> 5 | CB22: =COUNTIF(C22:BZ22,"н/у") -> 0 | CC22: =COUNTIF(C22:BZ22,"н") -> 0
A23: 19. | B23: Сурков Кирилл Александрович | C23: н | D23: н | E23: н | G23: н | H23: н | CA23: =IFERROR(AVERAGE(C23:BZ23),"Нет оценок") -> Нет оценок | CB23: =COUNTIF(C23:BZ23,"н/у") -> 0 | CC23: =COUNTIF(C23:BZ23,"н") -> 5
A24: 20. | B24: Усатов Тимофей Анатольевич | E24: 5 | I24: .2 | CA24: =IFERROR(AVERAGE(C24:BZ24),"Нет оценок") -> 5 | CB24: =COUNTIF(C24:BZ24,"н/у") -> 0 | CC24: =COUNTIF(C24:BZ24,"н") -> 0
A25: 21. | B25: Халитов Кирилл Родионович | C25: н | D25: н | E25: н | F25: н | G25: н | H25: н | CA25: =IFERROR(AVERAGE(C25:BZ25),"Нет оценок") -> Нет оценок | CB25: =COUNTIF(C25:BZ25,"н/у") -> 0 | CC25: =COUNTIF(C25:BZ25,"н") -> 6
A26: 21. | B26: Хорошилов Игорь Александрович | CA26: =IFERROR(AVERAGE(C26:BZ26),"Нет оценок") -> Нет оценок | CB26: =COUNTIF(C26:BZ26,"н/у") -> 0 | CC26: =COUNTIF(C26:BZ26,"н") -> 0
A27: 22. | B27: Хрычев Мирон Евгеньевич | E27: 5 | CA27: =IFERROR(AVERAGE(C27:BZ27),"Нет оценок") -> 5 | CB27: =COUNTIF(C27:BZ27,"н/у") -> 0 | CC27: =COUNTIF(C27:BZ27,"н") -> 0
A28: 23. | B28: Цапов Илья Валерьевич | D28: н | E28: 5 | CA28: =IFERROR(AVERAGE(C28:BZ28),"Нет оценок") -> 5 | CB28: =COUNTIF(C28:BZ28,"н/у") -> 0 | CC28: =COUNTIF(C28:BZ28,"н") -> 1
CA29: =IFERROR(AVERAGE(CA5:CA28),"") -> 5 | CB29: =SUM(CB5:CB28) -> 0 | CC29: =SUM(CC5:CC28) -> 41
A30: Дата | B30: Тема / ДЗ
A31: 46034 | B31: Тема 1.1. Основные понятия теории надёжности
A32: 46042 | B32: Тема 1.2. Качество программных средств
A33: 46048 | B33: Тема 1.2. Качество программных средств
A34: 46058 | B34: Тема 1.3. Модели качества информационных систем
A35: 46072 | B35: Тема 2.1. Моеди качества ИС
A36: 46073 | B36: Работа по индивидуальному дневнику

Sheet Граф диз и мульт
A1: Наименование предмета | C1: Графический дизайн и мультимедия
A2: ФИО преподавателя | C2: Коваленко Даниил Романович
A3: ИСиП 24/2 | B3: Месяц | C3: Январь | F3: Февраль | I3: Март | L3: Апрель | Z3: 4 сем | AA3: Средний балл | AB3: Пропуски
B4: Число | C4: 15 | D4: 24 | E4: 29 | F4: 17 | G4: 17 | H4: 20 | I4: 10 | J4: 13 | K4: 30 | L4: 1 | M4: 1 | N4: 6 | O4: 7 | P4: 7 | Z4: ДЗ | AB4: Уваж. | AC4: Неуваж.
A5: 1. | B5: Ахметов Артём Рамилевич | J5: 5 | L5: 3- | M5: 5 | O5: 3 | AA5: =IFERROR(AVERAGE(C5:Z5),"Нет оценок") -> 4.3333333 | AB5: =COUNTIF(C5:Z5,"н/у") -> 0 | AC5: =COUNTIF(C5:Z5,"н") -> 0
A6: 2. | B6: Адилбеков Бектур | E6: 2 | H6: н | I6: н | J6: н | L6: 3 | M6: 5 | N6: н | O6: н | P6: н | AA6: =IFERROR(AVERAGE(C6:Z6),"Нет оценок") -> 3.3333333 | AB6: =COUNTIF(C6:Z6,"н/у") -> 0 | AC6: =COUNTIF(C6:Z6,"н") -> 6
A7: 3. | B7: Бараников Владислав Михайлович | E7: 5 | J7: 5 | L7: 5 | M7: 5 | N7: н | O7: 5 | AA7: =IFERROR(AVERAGE(C7:Z7),"Нет оценок") -> 5 | AB7: =COUNTIF(C7:Z7,"н/у") -> 0 | AC7: =COUNTIF(C7:Z7,"н") -> 1
A8: 4. | B8: Борсук Артём Дмитриевич | E8: 4 | H8: н | I8: н | J8: н | L8: 5 | M8: 5 | N8: 5 | O8: 4 | AA8: =IFERROR(AVERAGE(C8:Z8),"Нет оценок") -> 4.6 | AB8: =COUNTIF(C8:Z8,"н/у") -> 0 | AC8: =COUNTIF(C8:Z8,"н") -> 3
A9: 5. | B9: Гильманов Ильназ Максимович | E9: 5 | H9: н | L9: 5 | M9: 5 | O9: 5 | AA9: =IFERROR(AVERAGE(C9:Z9),"Нет оценок") -> 5 | AB9: =COUNTIF(C9:Z9,"н/у") -> 0 | AC9: =COUNTIF(C9:Z9,"н") -> 1
A10: 6. | B10: Говтва Илья (Илюха) Денисович | E10: 5 | I10: 5 | J10: 5 | L10: 5 | M10: 5 | N10: 5 | O10: 5 | AA10: =IFERROR(AVERAGE(C10:Z10),"Нет оценок") -> 5 | AB10: =COUNTIF(C10:Z10,"н/у") -> 0 | AC10: =COUNTIF(C10:Z10,"н") -> 0
A11: 7. | B11: Горшков Владислав Васильевич | E11: 4 | I11: 5 | J11: 5 | L11: 5 | M11: 5 | N11: 5 | O11: 5 | AA11: =IFERROR(AVERAGE(C11:Z11),"Нет оценок") -> 4.8571429 | AB11: =COUNTIF(C11:Z11,"н/у") -> 0 | AC11: =COUNTIF(C11:Z11,"н") -> 0
A12: 8. | B12: Гришко Илья Алексеевич | E12: 5 | H12: н | L12: 5 | M12: 5 | N12: 4 | O12: 5 | AA12: =IFERROR(AVERAGE(C12:Z12),"Нет оценок") -> 4.8 | AB12: =COUNTIF(C12:Z12,"н/у") -> 0 | AC12: =COUNTIF(C12:Z12,"н") -> 1
A13: 9. | B13: Катков Константин Александрович | E13: 2 | I13: н | J13: н | L13: н | M13: н | N13: 5 | O13: 2 | AA13: =IFERROR(AVERAGE(C13:Z13),"Нет оценок") -> 3 | AB13: =COUNTIF(C13:Z13,"н/у") -> 0 | AC13: =COUNTIF(C13:Z13,"н") -> 4
A14: 10. | B14: Корнеев Андрей Александрович | E14: 5 | H14: н | K14: н/у | L14: 5 | M14: 5 | O14: 5 | AA14: =IFERROR(AVERAGE(C14:Z14),"Нет оценок") -> 5 | AB14: =COUNTIF(C14:Z14,"н/у") -> 1 | AC14: =COUNTIF(C14:Z14,"н") -> 1
A15: 11. | B15: Макаров Максим Алексеевич | E15: 2 | L15: 5 | M15: 5 | N15: 5 | O15: 5 | AA15: =IFERROR(AVERAGE(C15:Z15),"Нет оценок") -> 4.4 | AB15: =COUNTIF(C15:Z15,"н/у") -> 0 | AC15: =COUNTIF(C15:Z15,"н") -> 0
A16: 13. | B16: Муллагалиев Вадим Радмилович | J16: 5 | L16: 3 | M16: 5 | N16: 5 | O16: 4 | AA16: =IFERROR(AVERAGE(C16:Z16),"Нет оценок") -> 4.4 | AB16: =COUNTIF(C16:Z16,"н/у") -> 0 | AC16: =COUNTIF(C16:Z16,"н") -> 0
A17: 12. | B17: Натфуллин Камиль Данисович | E17: 4 | H17: н | J17: н | L17: 4 | M17: 5 | N17: н | O17: 3 | AA17: =IFERROR(AVERAGE(C17:Z17),"Нет оценок") -> 4 | AB17: =COUNTIF(C17:Z17,"н/у") -> 0 | AC17: =COUNTIF(C17:Z17,"н") -> 3
A18: 14. | B18: Носков Ярослав Евгеньевич | E18: 4 | J18: 5 | L18: 4 | M18: 5 | O18: 4 | AA18: =IFERROR(AVERAGE(C18:Z18),"Нет оценок") -> 4.4 | AB18: =COUNTIF(C18:Z18,"н/у") -> 0 | AC18: =COUNTIF(C18:Z18,"н") -> 0
A19: 15. | B19: Осыка Владислав Сергеевич | E19: 5 | J19: 5 | L19: 5 | M19: 5 | N19: 5 | O19: 5 | AA19: =IFERROR(AVERAGE(C19:Z19),"Нет оценок") -> 5 | AB19: =COUNTIF(C19:Z19,"н/у") -> 0 | AC19: =COUNTIF(C19:Z19,"н") -> 0
A20: 16. | B20: Романов Михаил Васильевич | E20: 5 | H20: н | J20: н | L20: 4 | M20: 5 | N20: 5 | O20: 5 | AA20: =IFERROR(AVERAGE(C20:Z20),"Нет оценок") -> 4.8 | AB20: =COUNTIF(C20:Z20,"н/у") -> 0 | AC20: =COUNTIF(C20:Z20,"н") -> 2
A21: 17. | B21: Руфуллаев Ибрагим Фуадович | E21: 4 | J21: 5 | L21: 3 | M21: 5 | N21: н | O21: 3 | AA21: =IFERROR(AVERAGE(C21:Z21),"Нет оценок") -> 4 | AB21: =COUNTIF(C21:Z21,"н/у") -> 0 | AC21: =COUNTIF(C21:Z21,"н") -> 1
A22: 18. | B22: Сарычев Данила Андреевич | E22: 5 | J22: н | K22: н/у | L22: 4 | M22: н/у | N22: 5 | O22: 5 | AA22: =IFERROR(AVERAGE(C22:Z22),"Нет оценок") -> 4.75 | AB22: =COUNTIF(C22:Z22,"н/у") -> 2 | AC22: =COUNTIF(C22:Z22,"н") -> 1
A23: 19. | B23: Сурков Кирилл Александрович | H23: н | I23: н | J23: н | L23: 5 | M23: 5 | O23: н | P23: н | AA23: =IFERROR(AVERAGE(C23:Z23),"Нет оценок") -> 5 | AB23: =COUNTIF(C23:Z23,"н/у") -> 0 | AC23: =COUNTIF(C23:Z23,"н") -> 5
A24: 20. | B24: Усатов Тимофей Анатольевич | E24: 5 | J24: 5 | L24: 5 | M24: 5 | N24: 5 | AA24: =IFERROR(AVERAGE(C24:Z24),"Нет оценок") -> 5 | AB24: =COUNTIF(C24:Z24,"н/у") -> 0 | AC24: =COUNTIF(C24:Z24,"н") -> 0
A25: 21. | B25: Халитов Кирилл Родионович | H25: н | I25: 2 | K25: н | L25: 4 | M25: 5 | N25: н | O25: н | P25: н | AA25: =IFERROR(AVERAGE(C25:Z25),"Нет оценок") -> 3.6666667 | AB25: =COUNTIF(C25:Z25,"н/у") -> 0 | AC25: =COUNTIF(C25:Z25,"н") -> 5
A26: 21. | B26: Хорошилов Игорь Александрович | AA26: =IFERROR(AVERAGE(C26:Z26),"Нет оценок") -> Нет оценок | AB26: =COUNTIF(C26:Z26,"н/у") -> 0 | AC26: =COUNTIF(C26:Z26,"н") -> 0
A27: 22. | B27: Хрычев Мирон Евгеньевич | L27: 3- | M27: 5 | N27: н | O27: н | AA27: =IFERROR(AVERAGE(C27:Z27),"Нет оценок") -> 5 | AB27: =COUNTIF(C27:Z27,"н/у") -> 0 | AC27: =COUNTIF(C27:Z27,"н") -> 2
A28: 23. | B28: Цапов Илья Валерьевич | E28: 5 | L28: 5 | M28: 5 | N28: 5 | AA28: =IFERROR(AVERAGE(C28:Z28),"Нет оценок") -> 5 | AB28: =COUNTIF(C28:Z28,"н/у") -> 0 | AC28: =COUNTIF(C28:Z28,"н") -> 0
A29: Дата | B29: Тема / ДЗ | AA29: =IFERROR(AVERAGE(AA5:AA28),"") -> 4.5365424 | AB29: =SUM(AB5:AB28) -> 3 | AC29: =SUM(AC5:AC28) -> 36
A30: 46037 | B30: Тема 1. Коммуникативный дизайн
A31: 46046 | B31: Тема 1. Коммуникативный дизайн
A32: 46051 | B32: Письменная работа по теме 1. Коммуникативный дизайн
A33: 46070 | B33: Настройка и работа с графическим планшетом
